Workbook
Name Slicer_Diabetes_Status1: #N/A
Name Slicer_Weight_Status1: #N/A

Sheet Customer Names
A1: Customer ID | B1: name
A2: Id1 | B2: Hawks, Ms. Kelly
A3: Id2 | B3: Lehner, Mr. Matthew D
A4: Id3 | B4: Lu, Mr. Phil
A5: Id4 | B5: Osborne, Ms. Kelsey
A6: Id5 | B6: Kadala, Ms. Kristyn
A7: Id6 | B7: Baker, Mr. Russell B.
A8: Id7 | B8: Macpherson, Mr. Scott
A9: Id8 | B9: Hallman, Mr. Stephen
A10: Id9 | B10: Moran, Mr. Patrick R.
A11: Id10 | B11: Benner, Ms. Brooke N.
A12: Id11 | B12: Fierro Vargas, Ms. Paola Andrea
... A2336: Id2335 | B2336: German, Mr. Aaron K

Sheet Medical Examinations
A1: Customer ID | B1: BMI | C1: HBA1C | D1: Heart Issues | E1: Any Transplants | F1: Cancer history | G1: NumberOfMajorSurgeries | H1: smoker
A2: Id1 | B2: 47.41 | C2: 7.47 | D2: No | E2: No | F2: No | G2: No major surgery | H2: yes
A3: Id2 | B3: 30.36 | C3: 5.77 | D3: No | E3: No | F3: No | G3: No major surgery | H3: yes
A4: Id3 | B4: 34.485 | C4: 11.87 | D4: yes | E4: No | F4: No | G4: 2 | H4: yes
A5: Id4 | B5: 38.095 | C5: 6.05 | D5: No | E5: No | F5: No | G5: No major surgery | H5: yes
A6: Id5 | B6: 35.53 | C6: 5.45 | D6: No | E6: No | F6: No | G6: No major surgery | H6: yes
A7: Id6 | B7: 32.8 | C7: 6.59 | D7: No | E7: No | F7: No | G7: No major surgery | H7: yes
A8: Id7 | B8: 36.4 | C8: 6.07 | D8: No | E8: No | F8: No | G8: No major surgery | H8: yes
A9: Id8 | B9: 36.96 | C9: 7.93 | D9: No | E9: No | F9: No | G9: 3 | H9: yes
A10: Id9 | B10: 41.14 | C10: 9.58 | D10: yes | E10: No | F10: Yes | G10: 1 | H10: yes
A11: Id10 | B11: 38.06 | C11: 10.79 | D11: No | E11: No | F11: No | G11: No major surgery | H11: yes
A12: Id11 | B12: 37.7 | C12: 5.96 | D12: yes | E12: No | F12: No | G12: 2 | H12: yes
A13: Id12 | B13: 42.13 | C13: 11.9 | D13: No | E13: No | F13: No | G13: No major surgery | H13: yes
A14: Id13 | B14: 40.92 | C14: 8.41 | D14: No | E14: No | F14: No | G14: No major surgery | H14: yes
A15: Id14 | B15: 40.565 | C15: 7.02 | D15: No | E15: No | F15: No | G15: No major surgery | H15: yes
A16: Id15 | B16: 36.385 | C16: 7.59 | D16: yes | E16: No | F16: No | G16: 2 | H16: yes
A17: Id16 | B17: 39.9 | C17: 11.32 | D17: No | E17: No | F17: No | G17: No major surgery | H17: yes
A18: Id17 | B18: 33.8 | C18: 7.67 | D18: No | E18: No | F18: No | G18: 3 | H18: yes
A19: Id18 | B19: 36.765 | C19: 7.29 | D19: yes | E19: No | F19: Yes | G19: 1 | H19: yes
A20: Id19 | B20: 36.955 | C20: 4.72 | D20: yes | E20: No | F20: No | G20: 1 | H20: yes
A21: Id20 | B21: 42.9 | C21: 11.41 | D21: No | E21: No | F21: No | G21: No major surgery | H21: yes
A22: Id21 | B22: 36.3 | C22: 11.5 | D22: yes | E22: No | F22: No | G22: 2 | H22: yes
A23: Id22 | B23: 32.2 | C23: 6.22 | D23: yes | E23: No | F23: No | G23: 2 | H23: yes
A24: Id23 | B24: 31.3 | C24: 11.38 | D24: No | E24: No | F24: No | G24: 3 | H24: yes
A25: Id24 | B25: 41.8 | C25: 7.89 | D25: yes | E25: No | F25: No | G25: 2 | H25: yes
A26: Id25 | B26: 35.09 | C26: 4.38 | D26: yes | E26: No | F26: No | G26: 2 | H26: yes
A27: Id26 | B27: 33.88 | C27: 7.01 | D27: No | E27: No | F27: No | G27: 3 | H27: yes
A28: Id27 | B28: 30.875 | C28: 11.88 | D28: No | E28: No | F28: No | G28: No major surgery | H28: yes
A29: Id28 | B29: 36.86 | C29: 5.19 | D29: yes | E29: No | F29: Yes | G29: 1 | H29: yes
A30: Id29 | B30: 35.86 | C30: 6.74 | D30: yes | E30: No | F30: No | G30: 2 | H30: yes
A31: Id30 | B31: 37.05 | C31: 8.44 | D31: No | E31: No | F31: No | G31: No major surgery | H31: yes
A32: Id31 | B32: 43.89 | C32: 8.71 | D32: No | E32: No | F32: No | G32: No major surgery | H32: yes
A33: Id32 | B33: 42.35 | C33: 5.08 | D33: yes | E33: No | F33: No | G33: No major surgery | H33: yes
A34: Id33 | B34: 31.35 | C34: 6.86 | D34: No | E34: No | F34: No | G34: No major surgery | H34: yes
A35: Id34 | B35: 47.6 | C35: 5.95 | D35: yes | E35: No | F35: No | G35: No major surgery | H35: yes
A36: Id35 | B36: 46.2 | C36: 6.09 | D36: No | E36: No | F36: Yes | G36: 1 | H36: yes
A37: Id36 | B37: 32.015 | C37: 11.75 | D37: No | E37: No | F37: No | G37: No major surgery | H37: yes
A38: Id37 | B38: 40.565 | C38: 7.37 | D38: No | E38: No | F38: No | G38: No major surgery | H38: yes
A39: Id38 | B39: 32.45 | C39: 11.91 | D39: No | E39: No | F39: No | G39: No major surgery | H39: yes
A40: Id39 | B40: 34.96 | C40: 6.52 | D40: No | E40: No | F40: No | G40: No major surgery | H40: yes
A41: Id40 | B41: 35.5 | C41: 5.14 | D41: No | E41: No | F41: Yes | G41: 1 | H41: yes
A42: Id41 | B42: 52.58 | C42: 4.19 | D42: No | E42: yes | F42: No | G42: 1 | H42: yes
A43: Id42 | B43: 35.2 | C43: 11.68 | D43: yes | E43: No | F43: No | G43: No major surgery | H43: yes
A44: Id43 | B44: 38.06 | C44: 6.98 | D44: No | E44: No | F44: No | G44: No major surgery | H44: yes
A45: Id44 | B45: 34.21 | C45: 8.34 | D45: No | E45: No | F45: No | G45: No major surgery | H45: yes
A46: Id45 | B46: 38.94 | C46: 8.49 | D46: yes | E46: No | F46: No | G46: 1 | H46: yes
A47: Id46 | B47: 30.21 | C47: 5.34 | D47: yes | E47: No | F47: No | G47: 1 | H47: yes
A48: Id47 | B48: 33.63 | C48: 4.43 | D48: yes | E48: No | F48: No | G48: 2 | H48: yes
A49: Id48 | B49: 40.37 | C49: 4.47 | D49: No | E49: No | F49: No | G49: No major surgery | H49: yes
A50: Id49 | B50: 53.09 | C50: 4.82 | D50: yes | E50: No | F50: No | G50: 2 | H50: yes
A51: Id50 | B51: 31.79 | C51: 5.51 | D51: yes | E51: No | F51: No | G51: 2 | H51: yes
A52: Id51 | B52: 41.895 | C52: 10.87 | D52: yes | E52: No | F52: No | G52: 1 | H52: yes
A53: Id52 | B53: 31.16 | C53: 9.34 | D53: No | E53: No | F53: No | G53: No major surgery | H53: yes
A54: Id53 | B54: 34.105 | C54: 5.03 | D54: yes | E54: No | F54: Yes | G54: 1 | H54: yes
A55: Id54 | B55: 51.93 | C55: 11.05 | D55: No | E55: No | F55: No | G55: No major surgery | H55: yes
A56: Id55 | B56: 38.95 | C56: 11.95 | D56: No | E56: No | F56: No | G56: No major surgery | H56: yes
A57: Id56 | B57: 36.63 | C57: 7.72 | D57: yes | E57: No | F57: No | G57: 1 | H57: yes
A58: Id57 | B58: 34.2 | C58: 5.75 | D58: No | E58: No | F58: No | G58: 2 | H58: yes
A59: Id58 | B59: 50.63 | C59: 11.89 | D59: No | E59: No | F59: No | G59: No major surgery | H59: yes
A60: Id59 | B60: 36.48 | C60: 6.2 | D60: No | E60: No | F60: No | G60: No major surgery | H60: yes
A61: Id60 | B61: 54.82 | C61: 10.61 | D61: No | E61: No | F61: No | G61: No major surgery | H61: yes
A62: Id61 | B62: 38.06 | C62: 6.04 | D62: No | E62: No | F62: Yes | G62: 1 | H62: yes
A63: Id62 | B63: 51.48 | C63: 9.33 | D63: yes | E63: No | F63: No | G63: No major surgery | H63: yes
A64: Id63 | B64: 52.06 | C64: 11.47 | D64: No | E64: No | F64: No | G64: No major surgery | H64: yes
A65: Id64 | B65: 30.685 | C65: 7.02 | D65: yes | E65: No | F65: No | G65: No major surgery | H65: yes
A66: Id65 | B66: 36.08 | C66: 8.8 | D66: yes | E66: No | F66: No | G66: 1 | H66: yes
A67: Id66 | B67: 54.99 | C67: 8.68 | D67: No | E67: No | F67: No | G67: 2 | H67: yes
A68: Id67 | B68: 35.97 | C68: 6.12 | D68: No | E68: No | F68: Yes | G68: 1 | H68: yes
A69: Id68 | B69: 45.54 | C69: 5.4 | D69: yes | E69: No | F69: Yes | G69: 1 | H69: yes
A70: Id69 | B70: 35.53 | C70: 4.36 | D70: yes | E70: No | F70: No | G70: No major surgery | H70: yes
A71: Id70 | B71: 30.8 | C71: 9.77 | D71: No | E71: No | F71: No | G71: No major surgery | H71: yes
A72: Id71 | B72: 38.39 | C72: 4.25 | D72: No | E72: No | F72: No | G72: 1 | H72: yes
A73: Id72 | B73: 32.3 | C73: 4.76 | D73: No | E73: No | F73: No | G73: 2 | H73: yes
A74: Id73 | B74: 48.8 | C74: 6.22 | D74: yes | E74: No | F74: No | G74: 2 | H74: yes
A75: Id74 | B75: 45.5 | C75: 7.96 | D75: No | E75: No | F75: No | G75: No major surgery | H75: yes
A76: Id75 | B76: 53.61 | C76: 10.92 | D76: yes | E76: No | F76: No | G76: 1 | H76: yes
A77: Id76 | B77: 36.19 | C77: 11.51 | D77: yes | E77: No | F77: No | G77: 1 | H77: yes
A78: Id77 | B78: 34.6 | C78: 5.99 | D78: yes | E78: No | F78: No | G78: No major surgery | H78: yes
A79: Id78 | B79: 54.12 | C79: 11.57 | D79: No | E79: No | F79: No | G79: No major surgery | H79: yes
A80: Id79 | B80: 48.82 | C80: 6.67 | D80: yes | E80: No | F80: No | G80: No major surgery | H80: yes
A81: Id80 | B81: 51.01 | C81: 9.2 | D81: No | E81: No | F81: No | G81: No major surgery | H81: yes
A82: Id81 | B82: 45.65 | C82: 5.11 | D82: yes | E82: No | F82: No | G82: 1 | H82: yes
A83: Id82 | B83: 52.9 | C83: 5.34 | D83: No | E83: No | F83: No | G83: No major surgery | H83: yes
A84: Id83 | B84: 45.41 | C84: 4.03 | D84: yes | E84: No | F84: No | G84: 1 | H84: yes
A85: Id84 | B85: 49.41 | C85: 4.23 | D85: yes | E85: No | F85: Yes | G85: 1 | H85: yes
A86: Id85 | B86: 31.825 | C86: 4.06 | D86: No | E86: No | F86: No | G86: 2 | H86: yes
A87: Id86 | B87: 51.28 | C87: 4.68 | D87: No | E87: No | F87: No | G87: 2 | H87: yes
A88: Id87 | B88: 34.96 | C88: 4.34 | D88: No | E88: No | F88: Yes | G88: 1 | H88: yes
A89: Id88 | B89: 33.11 | C89: 10.51 | D89: No | E89: No | F89: No | G89: No major surgery | H89: yes
A90: Id89 | B90: 54.74 | C90: 5.84 | D90: yes | E90: No | F90: Yes | G90: 1 | H90: yes
A91: Id90 | B91: 32.56 | C91: 5.41 | D91: No | E91: No | F91: Yes | G91: 1 | H91: yes
A92: Id91 | B92: 39.05 | C92: 6.06 | D92: No | E92: No | F92: No | G92: 1 | H92: yes
A93: Id92 | B93: 42.75 | C93: 4.22 | D93: No | E93: No | F93: No | G93: No major surgery | H93: yes
A94: Id93 | B94: 50.58 | C94: 5.12 | D94: No | E94: No | F94: No | G94: 2 | H94: yes
A95: Id94 | B95: 30.495 | C95: 4.57 | D95: yes | E95: No | F95: No | G95: No major surgery | H95: yes
A96: Id95 | B96: 48.31 | C96: 9.58 | D96: yes | E96: No | F96: No | G96: 2 | H96: yes
A97: Id96 | B97: 48.99 | C97: 9.78 | D97: yes | E97: No | F97: No | G97: 1 | H97: yes
A98: Id97 | B98: 38.39 | C98: 4.11 | D98: yes | E98: No | F98: No | G98: No major surgery | H98: yes
A99: Id98 | B99: 44.34 | C99: 4.02 | D99: yes | E99: No | F99: No | G99: 2 | H99: yes
A100: Id99 | B100: 41.51 | C100: 6.92 | D100: No | E100: No | F100: No | G100: No major surgery | H100: yes
...

Sheet Hospitalisation Details
A1: Customer ID | B1: year | C1: month | D1: date | E1: children | F1: charges | G1: Hospital tier | H1: City tier | I1: State ID
A2: Id2335 | B2: 1992 | C2: Jul | D2: 9 | E2: 0 | F2: 563.84 | G2: tier - 2 | H2: tier - 3 | I2: R1013
A3: Id2334 | B3: 1992 | C3: Nov | D3: 30 | E3: 0 | F3: 570.62 | G3: tier - 2 | H3: tier - 1 | I3: R1013
A4: Id2333 | B4: 1993 | C4: Jun | D4: 30 | E4: 0 | F4: 600 | G4: tier - 2 | H4: tier - 1 | I4: R1013
A5: Id2332 | B5: 1992 | C5: Sep | D5: 13 | E5: 0 | F5: 604.54 | G5: tier - 3 | H5: tier - 3 | I5: R1013
A6: Id2331 | B6: 1998 | C6: Jul | D6: 27 | E6: 0 | F6: 637.26 | G6: tier - 3 | H6: tier - 3 | I6: R1013
A7: Id2330 | B7: 2001 | C7: Nov | D7: 20 | E7: 0 | F7: 646.14 | G7: tier - 3 | H7: tier - 3 | I7: R1012
A8: Id2329 | B8: 1993 | C8: Jun | D8: 1 | E8: 0 | F8: 650 | G8: tier - 3 | H8: tier - 3 | I8: R1013
A9: Id2328 | B9: 1995 | C9: Jul | D9: 4 | E9: 0 | F9: 650 | G9: tier - 3 | H9: tier - 3 | I9: R1013
A10: Id2327 | B10: 2002 | C10: Nov | D10: 29 | E10: 0 | F10: 668 | G10: tier - 3 | H10: tier - 2 | I10: R1012
A11: Id2326 | B11: 1997 | C11: Nov | D11: 9 | E11: 0 | F11: 670 | G11: tier - 3 | H11: tier - 3 | I11: R1013
A12: Id2325 | B12: 2001 | C12: Sep | D12: 12 | E12: 0 | F12: 687.54 | G12: tier - 3 | H12: tier - 2 | I12: R1013
A13: Id2324 | B13: 1999 | C13: Dec | D13: 26 | E13: 0 | F13: 700 | G13: tier - 2 | H13: tier - 3 | I13: R1013
... A1050: Id1290 | B1050: 1977 | C1050: Jul | D1050: 26 | E1050: 2 | F1050: 8527.53 | G1050: tier - 2 | H1050: tier - 2 | I1050: R1013
A1051: Id1289 | B1051: ? | C1051: Jul | D1051: 24 | E1051: 0 | F1051: 8534.67 | G1051: tier - 2 | H1051: tier - 3 | I1051: R1024
A1052: Id1288 | B1052: 1981 | C1052: Dec | D1052: 27 | E1052: 3 | F1052: 8538.29 | G1052: tier - 2 | H1052: tier - 3 | I1052: R1024
A1053: Id1287 | B1053: 1975 | C1053: Nov | D1053: 6 | E1053: 1 | F1053: 8539.67 | G1053: tier - 2 | H1053: tier - 3 | I1053: R1011
A1054: Id1286 | B1054: ? | C1054: Dec | D1054: 12 | E1054: 1 | F1054: 8547.69 | G1054: tier - 2 | H1054: tier - 1 | I1054: R1013
A1055: Id1285 | B1055: 1975 | C1055: Aug | D1055: 6 | E1055: 1 | F1055: 8551.35 | G1055: tier - 2 | H1055: tier - 2 | I1055: R1011
A1056: Id1284 | B1056: 1975 | C1056: Aug | D1056: 21 | E1056: 1 | F1056: 8556.91 | G1056: tier - 2 | H1056: tier - 1 | I1056: R1011
A1057: Id1283 | B1057: 1988 | C1057: Sep | D1057: 21 | E1057: 3 | F1057: 8567.25 | G1057: tier - 2 | H1057: tier - 1 | I1057: R1012
A1058: Id1282 | B1058: 1975 | C1058: Sep | D1058: 26 | E1058: 1 | F1058: 8569.86 | G1058: tier - 2 | H1058: tier - 3 | I1058: R1013
A1059: Id1281 | B1059: 1982 | C1059: Dec | D1059: 6 | E1059: 3 | F1059: 8572.04 | G1059: tier - 2 | H1059: tier - 2 | I1059: R1021
A1060: Id1280 | B1060: 1987 | C1060: Nov | D1060: 11 | E1060: 3 | F1060: 8573.3 | G1060: tier - 2 | H1060: tier - 2 | I1060: R1021
A1061: Id1279 | B1061: 1983 | C1061: Dec | D1061: 30 | E1061: 5 | F1061: 8582.3 | G1061: tier - 2 | H1061: tier - 1 | I1061: R1013
A1062: Id1278 | B1062: 1983 | C1062: Jul | D1062: 25 | E1062: 5 | F1062: 8596.83 | G1062: tier - 2 | H1062: tier - 3 | I1062: R1013
A1063: Id1277 | B1063: 1973 | C1063: Jul | D1063: 11 | E1063: 0 | F1063: 8601.33 | G1063: tier - 2 | H1063: tier - 1 | I1063: R1013
A1064: Id1276 | B1064: 1977 | C1064: Sep | D1064: 24 | E1064: 2 | F1064: 8603.82 | G1064: tier - 2 | H1064: tier - 1 | I1064: R1019
A1065: Id1275 | B1065: 1977 | C1065: Nov | D1065: 12 | E1065: 2 | F1065: 8604.48 | G1065: tier - 3 | H1065: tier - 2 | I1065: R1016
A1066: Id1274 | B1066: 1977 | C1066: Oct | D1066: 15 | E1066: 3 | F1066: 8605.36 | G1066: tier - 2 | H1066: tier - 2 | I1066: R1013
... A2344: Id1 | B2344: 1968 | C2344: Oct | D2344: 12 | E2344: 0 | F2344: 63770.43 | G2344: tier - 1 | H2344: tier - 3 | I2344: R1013

Sheet Answers - Data Cleaning
A1: Data Cleaning
A2: 1. Missing Values | T2: 2. Fill in the missing values of month and Year | W2: Fill Missing Smoker, Hospital Tier, City Tier | AF2: Missing State ID
A3: Medical Examination Tab | J3: Hospitalisation Details | T3: Find & Replace | U3: Average year: | W3: Smoker List | Z3: Hospital tier | AC3: City tier
A4: Customer ID | B4: BMI | C4: HBA1C | D4: Heart Issues | E4: Any Transplants | F4: Cancer history | G4: NumberOfMajorSurgeries | H4: smoker | J4: Customer ID | K4: year | L4: month | M4: date | N4: children | O4: charges | P4: Hospital tier | Q4: City tier | R4: State ID | U4: =ROUND(AVERAGE('Hospitalisation Details'!B:B),0) -> 1983 | W4: Row Labels | X4: Count of smoker | Z4: Row Labels | AA4: Count of Hospital tier | AC4: Row Labels | AD4: Count of City tier | AF4: State ID | AG4: State ID
A5: =COUNTIF('Medical Examinations'!A:A,"?") -> 0 | B5: =COUNTIF('Medical Examinations'!B:B,"?") -> 0 | C5: =COUNTIF('Medical Examinations'!C:C,"?") -> 0 | D5: =COUNTIF('Medical Examinations'!D:D,"?") -> 0 | E5: =COUNTIF('Medical Examinations'!E:E,"?") -> 0 | F5: =COUNTIF('Medical Examinations'!F:F,"?") -> 0 | G5: =COUNTIF('Medical Examinations'!G:G,"?") -> 0 | H5: =COUNTIF('Medical Examinations'!H:H,"?") -> 0 | J5: =COUNTIF('Hospitalisation Details'!A:A,"?") -> 6 | K5: =COUNTIF('Hospitalisation Details'!B:B,"?") -> 2 | L5: =COUNTIF('Hospitalisation Details'!C:C,"?") -> 3 | M5: =COUNTIF('Hospitalisation Details'!D:D,"?") -> 0 | N5: =COUNTIF('Hospitalisation Details'!E:E,"?") -> 0 | O5: =COUNTIF('Hospitalisation Details'!F:F,"?") -> 0 | P5: =COUNTIF('Hospitalisation Details'!G:G,"?") -> 0 | Q5: =COUNTIF('Hospitalisation Details'!H:H,"?") -> 0 | R5: =COUNTIF('Hospitalisation Details'!I:I,"?") -> 2 | W5: No | X5: 1845 | Z5: tier - 1 | AA5: 309 | AC5: tier - 1 | AD5: 734 | AF5: R1013 | AG5: =IF(AF5="?","Unknown",AF5) -> R1013
T6: month | U6: year | W6: yes | X6: 490 | Z6: tier - 2 | AA6: 1340 | AC6: tier - 2 | AD6: 813 | AF6: R1013 | AG6: =IF(AF6="?","Unknown",AF6) -> R1013
T7: Jul | U7: 1992 | W7: (blank) | Z7: tier - 3 | AA7: 694 | AC7: tier - 3 | AD7: 796 | AF7: R1013 | AG7: =IF(AF7="?","Unknown",AF7) -> R1013
T8: Nov | U8: 1992 | W8: Grand Total | X8: 2335 | Z8: (blank) | AC8: (blank) | AF8: R1013 | AG8: =IF(AF8="?","Unknown",AF8) -> R1013
T9: Jun | U9: 1993 | Z9: Grand Total | AA9: 2343 | AC9: Grand Total | AD9: 2343 | AF9: R1013 | AG9: =IF(AF9="?","Unknown",AF9) -> R1013
T10: Sep | U10: 1992 | AF10: R1012 | AG10: =IF(AF10="?","Unknown",AF10) -> R1012
T11: Jul | U11: 1998 | AF11: R1013 | AG11: =IF(AF11="?","Unknown",AF11) -> R1013
T12: Nov | U12: 2001 | AF12: R1013 | AG12: =IF(AF12="?","Unknown",AF12) -> R1013
T13: Jun | U13: 1993 | AF13: R1012 | AG13: =IF(AF13="?","Unknown",AF13) -> R1012
T14: Jul | U14: 1995 | AF14: R1013 | AG14: =IF(AF14="?","Unknown",AF14) -> R1013
T15: Nov | U15: 2002 | AF15: R1013 | AG15: =IF(AF15="?","Unknown",AF15) -> R1013
T16: Nov | U16: 1997 | AF16: R1013 | AG16: =IF(AF16="?","Unknown",AF16) -> R1013
T17: Sep | U17: 2001 | AF17: R1013 | AG17: =IF(AF17="?","Unknown",AF17) -> R1013
T18: Dec | U18: 1999 | AF18: R1012 | AG18: =IF(AF18="?","Unknown",AF18) -> R1012
T19: Dec | U19: 1999 | AF19: R1013 | AG19: =IF(AF19="?","Unknown",AF19) -> R1013
T20: Sep | U20: 2002 | AF20: R1013 | AG20: =IF(AF20="?","Unknown",AF20) -> R1013
T21: Aug | U21: 1993 | AF21: R1013 | AG21: =IF(AF21="?","Unknown",AF21) -> R1013
... T2347: Sep | U2347: 1970 | AF2347: R1013 | AG2347: =IF(AF2347="?","Unknown",AF2347) -> R1013
T2348: Jun | U2348: 1977
T2349: Oct | U2349: 1968

Sheet Answers - Data Transformation  
A1: Data Transformation:
A3: Split the ‘names’ | F3: Convert Data | J3: Correcting inconsistencies | N3: Categorization | T3: Merger | Y3: Calucations | AA3: Formatting
A4: name | B4: Title | C4: First Name | D4: Last Name | F4: NumberOfMajorSurgeries | G4: Numeric Data | J4: Heart Issues | K4: smoker | N4: BMI | O4: Weight Status | Q4: HBA1C | R4: Diabetes Status | T4: year | U4: month | V4: date | W4: Date of Birth | Y4: Age | AA4: charges
A5: Hawks, Ms. Kelly | B5: =TRIM(MID(A5,FIND(",",A5)+1,FIND(".",A5)-FIND(",",A5)-1)) -> Ms | C5: =LEFT(A5,FIND(",",A5)-1) -> Hawks | D5: =RIGHT(A5,FIND(",",A5)-1) -> Kelly | F5: No major surgery | G5: =IF(F5="No major surgery",0,F5) -> 0 | H5: Here I gave "0" to No major Surgery . | J5: =PROPER('Medical Examinations'!D:D) -> No | K5: =PROPER('Medical Examinations'!H:H) -> Yes | L5: Here I updated data into proper case | N5: 47.41 | O5: =IF(N5<18.5,"Underweight", IF(N5<25,"Normal Weight", IF(N5<30,"Overweight", "Obesity"))) -> Obesity | Q5: 7.47 | R5: =IF(Q5<5.7,"Normal", IF(Q5<=6.4,"Prediabetes", "Diabetes")) -> Diabetes | T5: 1992 | U5: Jul | V5: 9 | W5: =DATE(T5,MONTH(1&U5),V5) -> 33794 | Y5: =DATEDIF(W5,DATE(2023,6,8),"Y") -> 30 | AA5: 563.84
A6: Lehner, Mr. Matthew D | B6: =TRIM(MID(A6,FIND(",",A6)+1,FIND(".",A6)-FIND(",",A6)-1)) -> Mr | C6: =LEFT(A6,FIND(",",A6)-1) -> Lehner | D6: =RIGHT(A6,FIND(",",A6)-1) -> thew D | F6: No major surgery | G6: =IF(F6="No major surgery",0,F6) -> 0 | J6: =PROPER('Medical Examinations'!D:D) -> No | K6: =PROPER('Medical Examinations'!H:H) -> Yes | N6: 30.36 | O6: =IF(N6<18.5,"Underweight", IF(N6<25,"Normal Weight", IF(N6<30,"Overweight", "Obesity"))) -> Obesity | Q6: 5.77 | R6: =IF(Q6<5.7,"Normal", IF(Q6<=6.4,"Prediabetes", "Diabetes")) -> Prediabetes | T6: 1992 | U6: Nov | V6: 30 | W6: =DATE(T6,MONTH(1&U6),V6) -> 33938 | Y6: =DATEDIF(W6,DATE(2023,6,8),"Y") -> 30 | AA6: 570.62
A7: Lu, Mr. Phil | B7: =TRIM(MID(A7,FIND(",",A7)+1,FIND(".",A7)-FIND(",",A7)-1)) -> Mr | C7: =LEFT(A7,FIND(",",A7)-1) -> Lu | D7: =RIGHT(A7,FIND(",",A7)-1) -> il | F7: 2 | G7: =IF(F7="No major surgery",0,F7) -> 2 | J7: =PROPER('Medical Examinations'!D:D) -> No | K7: =PROPER('Medical Examinations'!H:H) -> Yes | N7: 34.485 | O7: =IF(N7<18.5,"Underweight", IF(N7<25,"Normal Weight", IF(N7<30,"Overweight", "Obesity"))) -> Obesity | Q7: 11.87 | R7: =IF(Q7<5.7,"Normal", IF(Q7<=6.4,"Prediabetes", "Diabetes")) -> Diabetes | T7: 1993 | U7: Jun | V7: 30 | W7: =DATE(T7,MONTH(1&U7),V7) -> 34150 | Y7: =DATEDIF(W7,DATE(2023,6,8),"Y") -> 29 | AA7: 600
A8: Osborne, Ms. Kelsey | B8: =TRIM(MID(A8,FIND(",",A8)+1,FIND(".",A8)-FIND(",",A8)-1)) -> Ms | C8: =LEFT(A8,FIND(",",A8)-1) -> Osborne | D8: =RIGHT(A8,FIND(",",A8)-1) -> Kelsey | F8: No major surgery | G8: =IF(F8="No major surgery",0,F8) -> 0 | J8: =PROPER('Medical Examinations'!D:D) -> No | K8: =PROPER('Medical Examinations'!H:H) -> Yes | N8: 38.095 | O8: =IF(N8<18.5,"Underweight", IF(N8<25,"Normal Weight", IF(N8<30,"Overweight", "Obesity"))) -> Obesity | Q8: 6.05 | R8: =IF(Q8<5.7,"Normal", IF(Q8<=6.4,"Prediabetes", "Diabetes")) -> Prediabetes | T8: 1992 | U8: Sep | V8: 13 | W8: =DATE(T8,MONTH(1&U8),V8) -> 33860 | Y8: =DATEDIF(W8,DATE(2023,6,8),"Y") -> 30 | AA8: 604.54
A9: Kadala, Ms. Kristyn | B9: =TRIM(MID(A9,FIND(",",A9)+1,FIND(".",A9)-FIND(",",A9)-1)) -> Ms | C9: =LEFT(A9,FIND(",",A9)-1) -> Kadala | D9: =RIGHT(A9,FIND(",",A9)-1) -> ristyn | F9: No major surgery | G9: =IF(F9="No major surgery",0,F9) -> 0 | J9: =PROPER('Medical Examinations'!D:D) -> No | K9: =PROPER('Medical Examinations'!H:H) -> Yes | N9: 35.53 | O9: =IF(N9<18.5,"Underweight", IF(N9<25,"Normal Weight", IF(N9<30,"Overweight", "Obesity"))) -> Obesity | Q9: 5.45 | R9: =IF(Q9<5.7,"Normal", IF(Q9<=6.4,"Prediabetes", "Diabetes")) -> Normal | T9: 1998 | U9: Jul | V9: 27 | W9: =DATE(T9,MONTH(1&U9),V9) -> 36003 | Y9: =DATEDIF(W9,DATE(2023,6,8),"Y") -> 24 | AA9: 637.26
A10: Baker, Mr. Russell B. | B10: =TRIM(MID(A10,FIND(",",A10)+1,FIND(".",A10)-FIND(",",A10)-1)) -> Mr | C10: =LEFT(A10,FIND(",",A10)-1) -> Baker | D10: =RIGHT(A10,FIND(",",A10)-1) -> ll B. | F10: No major surgery | G10: =IF(F10="No major surgery",0,F10) -> 0 | J10: =PROPER('Medical Examinations'!D:D) -> Yes | K10: =PROPER('Medical Examinations'!H:H) -> Yes | N10: 32.8 | O10: =IF(N10<18.5,"Underweight", IF(N10<25,"Normal Weight", IF(N10<30,"Overweight", "Obesity"))) -> Obesity | Q10: 6.59 | R10: =IF(Q10<5.7,"Normal", IF(Q10<=6.4,"Prediabetes", "Diabetes")) -> Diabetes | T10: 2001 | U10: Nov | V10: 20 | W10: =DATE(T10,MONTH(1&U10),V10) -> 37215 | Y10: =DATEDIF(W10,DATE(2023,6,8),"Y") -> 21 | AA10: 646.14
A11: Macpherson, Mr. Scott | B11: =TRIM(MID(A11,FIND(",",A11)+1,FIND(".",A11)-FIND(",",A11)-1)) -> Mr | C11: =LEFT(A11,FIND(",",A11)-1) -> Macpherson | D11: =RIGHT(A11,FIND(",",A11)-1) -> Mr. Scott | F11: No major surgery | G11: =IF(F11="No major surgery",0,F11) -> 0 | J11: =PROPER('Medical Examinations'!D:D) -> No | K11: =PROPER('Medical Examinations'!H:H) -> Yes | N11: 36.4 | O11: =IF(N11<18.5,"Underweight", IF(N11<25,"Normal Weight", IF(N11<30,"Overweight", "Obesity"))) -> Obesity | Q11: 6.07 | R11: =IF(Q11<5.7,"Normal", IF(Q11<=6.4,"Prediabetes", "Diabetes")) -> Prediabetes | T11: 1993 | U11: Jun | V11: 1 | W11: =DATE(T11,MONTH(1&U11),V11) -> 34121 | Y11: =DATEDIF(W11,DATE(2023,6,8),"Y") -> 30 | AA11: 650
A12: Hallman, Mr. Stephen | B12: =TRIM(MID(A12,FIND(",",A12)+1,FIND(".",A12)-FIND(",",A12)-1)) -> Mr | C12: =LEFT(A12,FIND(",",A12)-1) -> Hallman | D12: =RIGHT(A12,FIND(",",A12)-1) -> Stephen | F12: 3 | G12: =IF(F12="No major surgery",0,F12) -> 3 | J12: =PROPER('Medical Examinations'!D:D) -> Yes | K12: =PROPER('Medical Examinations'!H:H) -> Yes | N12: 36.96 | O12: =IF(N12<18.5,"Underweight", IF(N12<25,"Normal Weight", IF(N12<30,"Overweight", "Obesity"))) -> Obesity | Q12: 7.93 | R12: =IF(Q12<5.7,"Normal", IF(Q12<=6.4,"Prediabetes", "Diabetes")) -> Diabetes | T12: 1995 | U12: Jul | V12: 4 | W12: =DATE(T12,MONTH(1&U12),V12) -> 34884 | Y12: =DATEDIF(W12,DATE(2023,6,8),"Y") -> 27 | AA12: 650
A13: Moran, Mr. Patrick R. | B13: =TRIM(MID(A13,FIND(",",A13)+1,FIND(".",A13)-FIND(",",A13)-1)) -> Mr | C13: =LEFT(A13,FIND(",",A13)-1) -> Moran | D13: =RIGHT(A13,FIND(",",A13)-1) -> ck R. | F13: 1 | G13: =IF(F13="No major surgery",0,F13) -> 1 | J13: =PROPER('Medical Examinations'!D:D) -> No | K13: =PROPER('Medical Examinations'!H:H) -> Yes | N13: 41.14 | O13: =IF(N13<18.5,"Underweight", IF(N13<25,"Normal Weight", IF(N13<30,"Overweight", "Obesity"))) -> Obesity | Q13: 9.58 | R13: =IF(Q13<5.7,"Normal", IF(Q13<=6.4,"Prediabetes", "Diabetes")) -> Diabetes | T13: 2002 | U13: Nov | V13: 29 | W13: =DATE(T13,MONTH(1&U13),V13) -> 37589 | Y13: =DATEDIF(W13,DATE(2023,6,8),"Y") -> 20 | AA13: 668
A14: Benner, Ms. Brooke N. | B14: =TRIM(MID(A14,FIND(",",A14)+1,FIND(".",A14)-FIND(",",A14)-1)) -> Ms | C14: =LEFT(A14,FIND(",",A14)-1) -> Benner | D14: =RIGHT(A14,FIND(",",A14)-1) -> oke N. | F14: No major surgery | G14: =IF(F14="No major surgery",0,F14) -> 0 | J14: =PROPER('Medical Examinations'!D:D) -> No | K14: =PROPER('Medical Examinations'!H:H) -> Yes | N14: 38.06 | O14: =IF(N14<18.5,"Underweight", IF(N14<25,"Normal Weight", IF(N14<30,"Overweight", "Obesity"))) -> Obesity | Q14: 10.79 | R14: =IF(Q14<5.7,"Normal", IF(Q14<=6.4,"Prediabetes", "Diabetes")) -> Diabetes | T14: 1997 | U14: Nov | V14: 9 | W14: =DATE(T14,MONTH(1&U14),V14) -> 35743 | Y14: =DATEDIF(W14,DATE(2023,6,8),"Y") -> 25 | AA14: 670
A15: Fierro Vargas, Ms. Paola Andrea | B15: =TRIM(MID(A15,FIND(",",A15)+1,FIND(".",A15)-FIND(",",A15)-1)) -> Ms | C15: =LEFT(A15,FIND(",",A15)-1) -> Fierro Vargas | D15: =RIGHT(A15,FIND(",",A15)-1) -> Paola Andrea | F15: 2 | G15: =IF(F15="No major surgery",0,F15) -> 2 | J15: =PROPER('Medical Examinations'!D:D) -> No | K15: =PROPER('Medical Examinations'!H:H) -> Yes | N15: 37.7 | O15: =IF(N15<18.5,"Underweight", IF(N15<25,"Normal Weight", IF(N15<30,"Overweight", "Obesity"))) -> Obesity | Q15: 5.96 | R15: =IF(Q15<5.7,"Normal", IF(Q15<=6.4,"Prediabetes", "Diabetes")) -> Prediabetes | T15: 2001 | U15: Sep | V15: 12 | W15: =DATE(T15,MONTH(1&U15),V15) -> 37146 | Y15: =DATEDIF(W15,DATE(2023,6,8),"Y") -> 21 | AA15: 687.54
A16: Franz, Mr. David | B16: =TRIM(MID(A16,FIND(",",A16)+1,FIND(".",A16)-FIND(",",A16)-1)) -> Mr | C16: =LEFT(A16,FIND(",",A16)-1) -> Franz | D16: =RIGHT(A16,FIND(",",A16)-1) -> David | F16: No major surgery | G16: =IF(F16="No major surgery",0,F16) -> 0 | J16: =PROPER('Medical Examinations'!D:D) -> Yes | K16: =PROPER('Medical Examinations'!H:H) -> Yes | N16: 42.13 | O16: =IF(N16<18.5,"Underweight", IF(N16<25,"Normal Weight", IF(N16<30,"Overweight", "Obesity"))) -> Obesity | Q16: 11.9 | R16: =IF(Q16<5.7,"Normal", IF(Q16<=6.4,"Prediabetes", "Diabetes")) -> Diabetes | T16: 1999 | U16: Dec | V16: 26 | W16: =DATE(T16,MONTH(1&U16),V16) -> 36520 | Y16: =DATEDIF(W16,DATE(2023,6,8),"Y") -> 23 | AA16: 700
A17: Foster, Mr. Wade | B17: =TRIM(MID(A17,FIND(",",A17)+1,FIND(".",A17)-FIND(",",A17)-1)) -> Mr | C17: =LEFT(A17,FIND(",",A17)-1) -> Foster | D17: =RIGHT(A17,FIND(",",A17)-1) -> Wade | F17: No major surgery | G17: =IF(F17="No major surgery",0,F17) -> 0 | J17: =PROPER('Medical Examinations'!D:D) -> No | K17: =PROPER('Medical Examinations'!H:H) -> Yes | N17: 40.92 | O17: =IF(N17<18.5,"Underweight", IF(N17<25,"Normal Weight", IF(N17<30,"Overweight", "Obesity"))) -> Obesity | Q17: 8.41 | R17: =IF(Q17<5.7,"Normal", IF(Q17<=6.4,"Prediabetes", "Diabetes")) -> Diabetes | T17: 1999 | U17: Dec | V17: 14 | W17: =DATE(T17,MONTH(1&U17),V17) -> 36508 | Y17: =DATEDIF(W17,DATE(2023,6,8),"Y") -> 23 | AA17: 722.99
A18: Tenorio, Mr. Franklin | B18: =TRIM(MID(A18,FIND(",",A18)+1,FIND(".",A18)-FIND(",",A18)-1)) -> Mr | C18: =LEFT(A18,FIND(",",A18)-1) -> Tenorio | D18: =RIGHT(A18,FIND(",",A18)-1) -> ranklin | F18: No major surgery | G18: =IF(F18="No major surgery",0,F18) -> 0 | J18: =PROPER('Medical Examinations'!D:D) -> No | K18: =PROPER('Medical Examinations'!H:H) -> Yes | N18: 40.565 | O18: =IF(N18<18.5,"Underweight", IF(N18<25,"Normal Weight", IF(N18<30,"Overweight", "Obesity"))) -> Obesity | Q18: 7.02 | R18: =IF(Q18<5.7,"Normal", IF(Q18<=6.4,"Prediabetes", "Diabetes")) -> Diabetes | T18: 2002 | U18: Sep | V18: 19 | W18: =DATE(T18,MONTH(1&U18),V18) -> 37518 | Y18: =DATEDIF(W18,DATE(2023,6,8),"Y") -> 20 | AA18: 750
A19: Rios, Ms. Leilani M. | B19: =TRIM(MID(A19,FIND(",",A19)+1,FIND(".",A19)-FIND(",",A19)-1)) -> Ms | C19: =LEFT(A19,FIND(",",A19)-1) -> Rios | D19: =RIGHT(A19,FIND(",",A19)-1) -> i M. | F19: 2 | G19: =IF(F19="No major surgery",0,F19) -> 2 | J19: =PROPER('Medical Examinations'!D:D) -> Yes | K19: =PROPER('Medical Examinations'!H:H) -> Yes | N19: 36.385 | O19: =IF(N19<18.5,"Underweight", IF(N19<25,"Normal Weight", IF(N19<30,"Overweight", "Obesity"))) -> Obesity | Q19: 7.59 | R19: =IF(Q19<5.7,"Normal", IF(Q19<=6.4,"Prediabetes", "Diabetes")) -> Diabetes | T19: 1993 | U19: Aug | V19: 9 | W19: =DATE(T19,MONTH(1&U19),V19) -> 34190 | Y19: =DATEDIF(W19,DATE(2023,6,8),"Y") -> 29 | AA19: 760
A20: Viau-Dupuis, Mr. Philippe | B20: =TRIM(MID(A20,FIND(",",A20)+1,FIND(".",A20)-FIND(",",A20)-1)) -> Mr | C20: =LEFT(A20,FIND(",",A20)-1) -> Viau-Dupuis | D20: =RIGHT(A20,FIND(",",A20)-1) -> . Philippe | F20: No major surgery | G20: =IF(F20="No major surgery",0,F20) -> 0 | J20: =PROPER('Medical Examinations'!D:D) -> Yes | K20: =PROPER('Medical Examinations'!H:H) -> Yes | N20: 39.9 | O20: =IF(N20<18.5,"Underweight", IF(N20<25,"Normal Weight", IF(N20<30,"Overweight", "Obesity"))) -> Obesity | Q20: 11.32 | R20: =IF(Q20<5.7,"Normal", IF(Q20<=6.4,"Prediabetes", "Diabetes")) -> Diabetes | T20: 1996 | U20: Oct | V20: 22 | W20: =DATE(T20,MONTH(1&U20),V20) -> 35360 | Y20: =DATEDIF(W20,DATE(2023,6,8),"Y") -> 26 | AA20: 760
A21: Cronin, Ms. Jennifer A. | B21: =TRIM(MID(A21,FIND(",",A21)+1,FIND(".",A21)-FIND(",",A21)-1)) -> Ms | C21: =LEFT(A21,FIND(",",A21)-1) -> Cronin | D21: =RIGHT(A21,FIND(",",A21)-1) -> fer A. | F21: 3 | G21: =IF(F21="No major surgery",0,F21) -> 3 | J21: =PROPER('Medical Examinations'!D:D) -> No | K21: =PROPER('Medical Examinations'!H:H) -> Yes | N21: 33.8 | O21: =IF(N21<18.5,"Underweight", IF(N21<25,"Normal Weight", IF(N21<30,"Overweight", "Obesity"))) -> Obesity | Q21: 7.67 | R21: =IF(Q21<5.7,"Normal", IF(Q21<=6.4,"Prediabetes", "Diabetes")) -> Diabetes | T21: 1993 | U21: Jun | V21: 28 | W21: =DATE(T21,MONTH(1&U21),V21) -> 34148 | Y21: =DATEDIF(W21,DATE(2023,6,8),"Y") -> 29 | AA21: 770
A22: Noordstar, Ms. Christina M. | B22: =TRIM(MID(A22,FIND(",",A22)+1,FIND(".",A22)-FIND(",",A22)-1)) -> Ms | C22: =LEFT(A22,FIND(",",A22)-1) -> Noordstar | D22: =RIGHT(A22,FIND(",",A22)-1) -> istina M. | F22: 1 | G22: =IF(F22="No major surgery",0,F22) -> 1 | J22: =PROPER('Medical Examinations'!D:D) -> Yes | K22: =PROPER('Medical Examinations'!H:H) -> Yes | N22: 36.765 | O22: =IF(N22<18.5,"Underweight", IF(N22<25,"Normal Weight", IF(N22<30,"Overweight", "Obesity"))) -> Obesity | Q22: 7.29 | R22: =IF(Q22<5.7,"Normal", IF(Q22<=6.4,"Prediabetes", "Diabetes")) -> Diabetes | T22: 1996 | U22: Sep | V22: 18 | W22: =DATE(T22,MONTH(1&U22),V22) -> 35326 | Y22: =DATEDIF(W22,DATE(2023,6,8),"Y") -> 26 | AA22: 770.38
A23: Boudalia, Mr. Said Sr. | B23: =TRIM(MID(A23,FIND(",",A23)+1,FIND(".",A23)-FIND(",",A23)-1)) -> Mr | C23: =LEFT(A23,FIND(",",A23)-1) -> Boudalia | D23: =RIGHT(A23,FIND(",",A23)-1) -> Said Sr. | F23: 1 | G23: =IF(F23="No major surgery",0,F23) -> 1 | J23: =PROPER('Medical Examinations'!D:D) -> Yes | K23: =PROPER('Medical Examinations'!H:H) -> Yes | N23: 36.955 | O23: =IF(N23<18.5,"Underweight", IF(N23<25,"Normal Weight", IF(N23<30,"Overweight", "Obesity"))) -> Obesity | Q23: 4.72 | R23: =IF(Q23<5.7,"Normal", IF(Q23<=6.4,"Prediabetes", "Diabetes")) -> Normal | T23: 1995 | U23: Dec | V23: 7 | W23: =DATE(T23,MONTH(1&U23),V23) -> 35040 | Y23: =DATEDIF(W23,DATE(2023,6,8),"Y") -> 27 | AA23: 773.54
A24: Flor, Mr. John | B24: =TRIM(MID(A24,FIND(",",A24)+1,FIND(".",A24)-FIND(",",A24)-1)) -> Mr | C24: =LEFT(A24,FIND(",",A24)-1) -> Flor | D24: =RIGHT(A24,FIND(",",A24)-1) -> John | F24: No major surgery | G24: =IF(F24="No major surgery",0,F24) -> 0 | J24: =PROPER('Medical Examinations'!D:D) -> No | K24: =PROPER('Medical Examinations'!H:H) -> Yes | N24: 42.9 | O24: =IF(N24<18.5,"Underweight", IF(N24<25,"Normal Weight", IF(N24<30,"Overweight", "Obesity"))) -> Obesity | Q24: 11.41 | R24: =IF(Q24<5.7,"Normal", IF(Q24<=6.4,"Prediabetes", "Diabetes")) -> Diabetes | T24: 2004 | U24: Oct | V24: 7 | W24: =DATE(T24,MONTH(1&U24),V24) -> 38267 | Y24: =DATEDIF(W24,DATE(2023,6,8),"Y") -> 18 | AA24: 830.52
A25: Fennon, Mr. Myles | B25: =TRIM(MID(A25,FIND(",",A25)+1,FIND(".",A25)-FIND(",",A25)-1)) -> Mr | C25: =LEFT(A25,FIND(",",A25)-1) -> Fennon | D25: =RIGHT(A25,FIND(",",A25)-1) -> Myles | F25: 2 | G25: =IF(F25="No major surgery",0,F25) -> 2 | J25: =PROPER('Medical Examinations'!D:D) -> Yes | K25: =PROPER('Medical Examinations'!H:H) -> Yes | N25: 36.3 | O25: =IF(N25<18.5,"Underweight", IF(N25<25,"Normal Weight", IF(N25<30,"Overweight", "Obesity"))) -> Obesity | Q25: 11.5 | R25: =IF(Q25<5.7,"Normal", IF(Q25<=6.4,"Prediabetes", "Diabetes")) -> Diabetes | T25: 2000 | U25: Nov | V25: 18 | W25: =DATE(T25,MONTH(1&U25),V25) -> 36848 | Y25: =DATEDIF(W25,DATE(2023,6,8),"Y") -> 22 | AA25: 865.41
A26: Hribar, Ms. Madelyn C | B26: =TRIM(MID(A26,FIND(",",A26)+1,FIND(".",A26)-FIND(",",A26)-1)) -> Ms | C26: =LEFT(A26,FIND(",",A26)-1) -> Hribar | D26: =RIGHT(A26,FIND(",",A26)-1) -> elyn C | F26: 2 | G26: =IF(F26="No major surgery",0,F26) -> 2 | J26: =PROPER('Medical Examinations'!D:D) -> Yes | K26: =PROPER('Medical Examinations'!H:H) -> Yes | N26: 32.2 | O26: =IF(N26<18.5,"Underweight", IF(N26<25,"Normal Weight", IF(N26<30,"Overweight", "Obesity"))) -> Obesity | Q26: 6.22 | R26: =IF(Q26<5.7,"Normal", IF(Q26<=6.4,"Prediabetes", "Diabetes")) -> Prediabetes | T26: 1993 | U26: Nov | V26: 27 | W26: =DATE(T26,MONTH(1&U26),V26) -> 34300 | Y26: =DATEDIF(W26,DATE(2023,6,8),"Y") -> 29 | AA26: 896.21
A27: Tassello, Ms. Nicole | B27: =TRIM(MID(A27,FIND(",",A27)+1,FIND(".",A27)-FIND(",",A27)-1)) -> Ms | C27: =LEFT(A27,FIND(",",A27)-1) -> Tassello | D27: =RIGHT(A27,FIND(",",A27)-1) -> Nicole | F27: 3 | G27: =IF(F27="No major surgery",0,F27) -> 3 | J27: =PROPER('Medical Examinations'!D:D) -> No | K27: =PROPER('Medical Examinations'!H:H) -> Yes | N27: 31.3 | O27: =IF(N27<18.5,"Underweight", IF(N27<25,"Normal Weight", IF(N27<30,"Overweight", "Obesity"))) -> Obesity | Q27: 11.38 | R27: =IF(Q27<5.7,"Normal", IF(Q27<=6.4,"Prediabetes", "Diabetes")) -> Diabetes | T27: 1994 | U27: Oct | V27: 30 | W27: =DATE(T27,MONTH(1&U27),V27) -> 34637 | Y27: =DATEDIF(W27,DATE(2023,6,8),"Y") -> 28 | AA27: 915.07
A28: Mauricette, Mr. Eric A. | B28: =TRIM(MID(A28,FIND(",",A28)+1,FIND(".",A28)-FIND(",",A28)-1)) -> Mr | C28: =LEFT(A28,FIND(",",A28)-1) -> Mauricette | D28: =RIGHT(A28,FIND(",",A28)-1) -> . Eric A. | F28: 2 | G28: =IF(F28="No major surgery",0,F28) -> 2 | J28: =PROPER('Medical Examinations'!D:D) -> No | K28: =PROPER('Medical Examinations'!H:H) -> Yes | N28: 41.8 | O28: =IF(N28<18.5,"Underweight", IF(N28<25,"Normal Weight", IF(N28<30,"Overweight", "Obesity"))) -> Obesity | Q28: 7.89 | R28: =IF(Q28<5.7,"Normal", IF(Q28<=6.4,"Prediabetes", "Diabetes")) -> Diabetes | T28: 1995 | U28: Oct | V28: 28 | W28: =DATE(T28,MONTH(1&U28),V28) -> 35000 | Y28: =DATEDIF(W28,DATE(2023,6,8),"Y") -> 27 | AA28: 928.59
A29: Garcia, Mr. Emiliano I. | B29: =TRIM(MID(A29,FIND(",",A29)+1,FIND(".",A29)-FIND(",",A29)-1)) -> Mr | C29: =LEFT(A29,FIND(",",A29)-1) -> Garcia | D29: =RIGHT(A29,FIND(",",A29)-1) -> ano I. | F29: 2 | G29: =IF(F29="No major surgery",0,F29) -> 2 | J29: =PROPER('Medical Examinations'!D:D) -> Yes | K29: =PROPER('Medical Examinations'!H:H) -> Yes | N29: 35.09 | O29: =IF(N29<18.5,"Underweight", IF(N29<25,"Normal Weight", IF(N29<30,"Overweight", "Obesity"))) -> Obesity | Q29: 4.38 | R29: =IF(Q29<5.7,"Normal", IF(Q29<=6.4,"Prediabetes", "Diabetes")) -> Normal | T29: 2001 | U29: Aug | V29: 19 | W29: =DATE(T29,MONTH(1&U29),V29) -> 37122 | Y29: =DATEDIF(W29,DATE(2023,6,8),"Y") -> 21 | AA29: 964.71
A30: Airoldi, Mr. Adam | B30: =TRIM(MID(A30,FIND(",",A30)+1,FIND(".",A30)-FIND(",",A30)-1)) -> Mr | C30: =LEFT(A30,FIND(",",A30)-1) -> Airoldi | D30: =RIGHT(A30,FIND(",",A30)-1) -> . Adam | F30: 3 | G30: =IF(F30="No major surgery",0,F30) -> 3 | J30: =PROPER('Medical Examinations'!D:D) -> Yes | K30: =PROPER('Medical Examinations'!H:H) -> Yes | N30: 33.88 | O30: =IF(N30<18.5,"Underweight", IF(N30<25,"Normal Weight", IF(N30<30,"Overweight", "Obesity"))) -> Obesity | Q30: 7.01 | R30: =IF(Q30<5.7,"Normal", IF(Q30<=6.4,"Prediabetes", "Diabetes")) -> Diabetes | T30: 1994 | U30: Nov | V30: 22 | W30: =DATE(T30,MONTH(1&U30),V30) -> 34660 | Y30: =DATEDIF(W30,DATE(2023,6,8),"Y") -> 28 | AA30: 1006.65
A31: Cater-Cyker, Mr. Zach | B31: =TRIM(MID(A31,FIND(",",A31)+1,FIND(".",A31)-FIND(",",A31)-1)) -> Mr | C31: =LEFT(A31,FIND(",",A31)-1) -> Cater-Cyker | D31: =RIGHT(A31,FIND(",",A31)-1) -> , Mr. Zach | F31: No major surgery | G31: =IF(F31="No major surgery",0,F31) -> 0 | J31: =PROPER('Medical Examinations'!D:D) -> No | K31: =PROPER('Medical Examinations'!H:H) -> Yes | N31: 30.875 | O31: =IF(N31<18.5,"Underweight", IF(N31<25,"Normal Weight", IF(N31<30,"Overweight", "Obesity"))) -> Obesity | Q31: 11.88 | R31: =IF(Q31<5.7,"Normal", IF(Q31<=6.4,"Prediabetes", "Diabetes")) -> Diabetes | T31: 2000 | U31: Oct | V31: 9 | W31: =DATE(T31,MONTH(1&U31),V31) -> 36808 | Y31: =DATEDIF(W31,DATE(2023,6,8),"Y") -> 22 | AA31: 1012
A32: Hamm, Ms. Stephanie W. | B32: =TRIM(MID(A32,FIND(",",A32)+1,FIND(".",A32)-FIND(",",A32)-1)) -> Ms | C32: =LEFT(A32,FIND(",",A32)-1) -> Hamm | D32: =RIGHT(A32,FIND(",",A32)-1) -> e W. | F32: 1 | G32: =IF(F32="No major surgery",0,F32) -> 1 | J32: =PROPER('Medical Examinations'!D:D) -> No | K32: =PROPER('Medical Examinations'!H:H) -> Yes | N32: 36.86 | O32: =IF(N32<18.5,"Underweight", IF(N32<25,"Normal Weight", IF(N32<30,"Overweight", "Obesity"))) -> Obesity | Q32: 5.19 | R32: =IF(Q32<5.7,"Normal", IF(Q32<=6.4,"Prediabetes", "Diabetes")) -> Normal | T32: 1999 | U32: Aug | V32: 5 | W32: =DATE(T32,MONTH(1&U32),V32) -> 36377 | Y32: =DATEDIF(W32,DATE(2023,6,8),"Y") -> 23 | AA32: 1019
A33: Cox, Mr. Stephen | B33: =TRIM(MID(A33,FIND(",",A33)+1,FIND(".",A33)-FIND(",",A33)-1)) -> Mr | C33: =LEFT(A33,FIND(",",A33)-1) -> Cox | D33: =RIGHT(A33,FIND(",",A33)-1) -> hen | F33: 2 | G33: =IF(F33="No major surgery",0,F33) -> 2 | J33: =PROPER('Medical Examinations'!D:D) -> Yes | K33: =PROPER('Medical Examinations'!H:H) -> Yes | N33: 35.86 | O33: =IF(N33<18.5,"Underweight", IF(N33<25,"Normal Weight", IF(N33<30,"Overweight", "Obesity"))) -> Obesity | Q33: 6.74 | R33: =IF(Q33<5.7,"Normal", IF(Q33<=6.4,"Prediabetes", "Diabetes")) -> Diabetes | T33: 1995 | U33: Oct | V33: 5 | W33: =DATE(T33,MONTH(1&U33),V33) -> 34977 | Y33: =DATEDIF(W33,DATE(2023,6,8),"Y") -> 27 | AA33: 1033.74
A34: Sachrajda, Ms. Natalie | B34: =TRIM(MID(A34,FIND(",",A34)+1,FIND(".",A34)-FIND(",",A34)-1)) -> Ms | C34: =LEFT(A34,FIND(",",A34)-1) -> Sachrajda | D34: =RIGHT(A34,FIND(",",A34)-1) -> Natalie | F34: No major surgery | G34: =IF(F34="No major surgery",0,F34) -> 0 | J34: =PROPER('Medical Examinations'!D:D) -> No | K34: =PROPER('Medical Examinations'!H:H) -> Yes | N34: 37.05 | O34: =IF(N34<18.5,"Underweight", IF(N34<25,"Normal Weight", IF(N34<30,"Overweight", "Obesity"))) -> Obesity | Q34: 8.44 | R34: =IF(Q34<5.7,"Normal", IF(Q34<=6.4,"Prediabetes", "Diabetes")) -> Diabetes | T34: 1994 | U34: Nov | V34: 17 | W34: =DATE(T34,MONTH(1&U34),V34) -> 34655 | Y34: =DATEDIF(W34,DATE(2023,6,8),"Y") -> 28 | AA34: 1044
A35: Gareri, Ms. Nicole J. | B35: =TRIM(MID(A35,FIND(",",A35)+1,FIND(".",A35)-FIND(",",A35)-1)) -> Ms | C35: =LEFT(A35,FIND(",",A35)-1) -> Gareri | D35: =RIGHT(A35,FIND(",",A35)-1) -> ole J. | F35: No major surgery | G35: =IF(F35="No major surgery",0,F35) -> 0 | J35: =PROPER('Medical Examinations'!D:D) -> Yes | K35: =PROPER('Medical Examinations'!H:H) -> Yes | N35: 43.89 | O35: =IF(N35<18.5,"Underweight", IF(N35<25,"Normal Weight", IF(N35<30,"Overweight", "Obesity"))) -> Obesity | Q35: 8.71 | R35: =IF(Q35<5.7,"Normal", IF(Q35<=6.4,"Prediabetes", "Diabetes")) -> Diabetes | T35: 2002 | U35: Jul | V35: 20 | W35: =DATE(T35,MONTH(1&U35),V35) -> 37457 | Y35: =DATEDIF(W35,DATE(2023,6,8),"Y") -> 20 | AA35: 1047
A36: Welch, Mr. Jefferson D | B36: =TRIM(MID(A36,FIND(",",A36)+1,FIND(".",A36)-FIND(",",A36)-1)) -> Mr | C36: =LEFT(A36,FIND(",",A36)-1) -> Welch | D36: =RIGHT(A36,FIND(",",A36)-1) -> son D | F36: No major surgery | G36: =IF(F36="No major surgery",0,F36) -> 0 | J36: =PROPER('Medical Examinations'!D:D) -> No | K36: =PROPER('Medical Examinations'!H:H) -> Yes | N36: 42.35 | O36: =IF(N36<18.5,"Underweight", IF(N36<25,"Normal Weight", IF(N36<30,"Overweight", "Obesity"))) -> Obesity | Q36: 5.08 | R36: =IF(Q36<5.7,"Normal", IF(Q36<=6.4,"Prediabetes", "Diabetes")) -> Normal | T36: 2002 | U36: Jul | V36: 1 | W36: =DATE(T36,MONTH(1&U36),V36) -> 37438 | Y36: =DATEDIF(W36,DATE(2023,6,8),"Y") -> 20 | AA36: 1049
A37: Prindiville, Mr. Brendan D. | B37: =TRIM(MID(A37,FIND(",",A37)+1,FIND(".",A37)-FIND(",",A37)-1)) -> Mr | C37: =LEFT(A37,FIND(",",A37)-1) -> Prindiville | D37: =RIGHT(A37,FIND(",",A37)-1) -> Brendan D. | F37: No major surgery | G37: =IF(F37="No major surgery",0,F37) -> 0 | J37: =PROPER('Medical Examinations'!D:D) -> No | K37: =PROPER('Medical Examinations'!H:H) -> Yes | N37: 31.35 | O37: =IF(N37<18.5,"Underweight", IF(N37<25,"Normal Weight", IF(N37<30,"Overweight", "Obesity"))) -> Obesity | Q37: 6.86 | R37: =IF(Q37<5.7,"Normal", IF(Q37<=6.4,"Prediabetes", "Diabetes")) -> Diabetes | T37: 1995 | U37: Jun | V37: 1 | W37: =DATE(T37,MONTH(1&U37),V37) -> 34851 | Y37: =DATEDIF(W37,DATE(2023,6,8),"Y") -> 28 | AA37: 1056
A38: Kincaid, Ms. Courtney | B38: =TRIM(MID(A38,FIND(",",A38)+1,FIND(".",A38)-FIND(",",A38)-1)) -> Ms | C38: =LEFT(A38,FIND(",",A38)-1) -> Kincaid | D38: =RIGHT(A38,FIND(",",A38)-1) -> ourtney | F38: No major surgery | G38: =IF(F38="No major surgery",0,F38) -> 0 | J38: =PROPER('Medical Examinations'!D:D) -> No | K38: =PROPER('Medical Examinations'!H:H) -> Yes | N38: 47.6 | O38: =IF(N38<18.5,"Underweight", IF(N38<25,"Normal Weight", IF(N38<30,"Overweight", "Obesity"))) -> Obesity | Q38: 5.95 | R38: =IF(Q38<5.7,"Normal", IF(Q38<=6.4,"Prediabetes", "Diabetes")) -> Prediabetes | T38: 1993 | U38: Sep | V38: 28 | W38: =DATE(T38,MONTH(1&U38),V38) -> 34240 | Y38: =DATEDIF(W38,DATE(2023,6,8),"Y") -> 29 | AA38: 1068
A39: Bruestle, Ms. Sydney L. | B39: =TRIM(MID(A39,FIND(",",A39)+1,FIND(".",A39)-FIND(",",A39)-1)) -> Ms | C39: =LEFT(A39,FIND(",",A39)-1) -> Bruestle | D39: =RIGHT(A39,FIND(",",A39)-1) -> ydney L. | F39: 1 | G39: =IF(F39="No major surgery",0,F39) -> 1 | J39: =PROPER('Medical Examinations'!D:D) -> No | K39: =PROPER('Medical Examinations'!H:H) -> Yes | N39: 46.2 | O39: =IF(N39<18.5,"Underweight", IF(N39<25,"Normal Weight", IF(N39<30,"Overweight", "Obesity"))) -> Obesity | Q39: 6.09 | R39: =IF(Q39<5.7,"Normal", IF(Q39<=6.4,"Prediabetes", "Diabetes")) -> Prediabetes | T39: 2004 | U39: Aug | V39: 24 | W39: =DATE(T39,MONTH(1&U39),V39) -> 38223 | Y39: =DATEDIF(W39,DATE(2023,6,8),"Y") -> 18 | AA39: 1070
A40: Lachance, Mr. Julien | B40: =TRIM(MID(A40,FIND(",",A40)+1,FIND(".",A40)-FIND(",",A40)-1)) -> Mr | C40: =LEFT(A40,FIND(",",A40)-1) -> Lachance | D40: =RIGHT(A40,FIND(",",A40)-1) -> Julien | F40: No major surgery | G40: =IF(F40="No major surgery",0,F40) -> 0 | J40: =PROPER('Medical Examinations'!D:D) -> No | K40: =PROPER('Medical Examinations'!H:H) -> Yes | N40: 32.015 | O40: =IF(N40<18.5,"Underweight", IF(N40<25,"Normal Weight", IF(N40<30,"Overweight", "Obesity"))) -> Obesity | Q40: 11.75 | R40: =IF(Q40<5.7,"Normal", IF(Q40<=6.4,"Prediabetes", "Diabetes")) -> Diabetes | T40: 1997 | U40: Aug | V40: 13 | W40: =DATE(T40,MONTH(1&U40),V40) -> 35655 | Y40: =DATEDIF(W40,DATE(2023,6,8),"Y") -> 25 | AA40: 1071
A41: Eason, Mr. Ryan M | B41: =TRIM(MID(A41,FIND(",",A41)+1,FIND(".",A41)-FIND(",",A41)-1)) -> Mr | C41: =LEFT(A41,FIND(",",A41)-1) -> Eason | D41: =RIGHT(A41,FIND(",",A41)-1) -> yan M | F41: No major surgery | G41: =IF(F41="No major surgery",0,F41) -> 0 | J41: =PROPER('Medical Examinations'!D:D) -> No | K41: =PROPER('Medical Examinations'!H:H) -> Yes | N41: 40.565 | O41: =IF(N41<18.5,"Underweight", IF(N41<25,"Normal Weight", IF(N41<30,"Overweight", "Obesity"))) -> Obesity | Q41: 7.37 | R41: =IF(Q41<5.7,"Normal", IF(Q41<=6.4,"Prediabetes", "Diabetes")) -> Diabetes | T41: 1998 | U41: Dec | V41: 26 | W41: =DATE(T41,MONTH(1&U41),V41) -> 36155 | Y41: =DATEDIF(W41,DATE(2023,6,8),"Y") -> 24 | AA41: 1082
A42: Grummon, Ms. Anna H. | B42: =TRIM(MID(A42,FIND(",",A42)+1,FIND(".",A42)-FIND(",",A42)-1)) -> Ms | C42: =LEFT(A42,FIND(",",A42)-1) -> Grummon | D42: =RIGHT(A42,FIND(",",A42)-1) -> Anna H. | F42: No major surgery | G42: =IF(F42="No major surgery",0,F42) -> 0 | J42: =PROPER('Medical Examinations'!D:D) -> No | K42: =PROPER('Medical Examinations'!H:H) -> Yes | N42: 32.45 | O42: =IF(N42<18.5,"Underweight", IF(N42<25,"Normal Weight", IF(N42<30,"Overweight", "Obesity"))) -> Obesity | Q42: 11.91 | R42: =IF(Q42<5.7,"Normal", IF(Q42<=6.4,"Prediabetes", "Diabetes")) -> Diabetes | T42: 2002 | U42: Aug | V42: 13 | W42: =DATE(T42,MONTH(1&U42),V42) -> 37481 | Y42: =DATEDIF(W42,DATE(2023,6,8),"Y") -> 20 | AA42: 1086
A43: Vanwechel, Ms. Samantha | B43: =TRIM(MID(A43,FIND(",",A43)+1,FIND(".",A43)-FIND(",",A43)-1)) -> Ms | C43: =LEFT(A43,FIND(",",A43)-1) -> Vanwechel | D43: =RIGHT(A43,FIND(",",A43)-1) -> Samantha | F43: No major surgery | G43: =IF(F43="No major surgery",0,F43) -> 0 | J43: =PROPER('Medical Examinations'!D:D) -> Yes | K43: =PROPER('Medical Examinations'!H:H) -> Yes | N43: 34.96 | O43: =IF(N43<18.5,"Underweight", IF(N43<25,"Normal Weight", IF(N43<30,"Overweight", "Obesity"))) -> Obesity | Q43: 6.52 | R43: =IF(Q43<5.7,"Normal", IF(Q43<=6.4,"Prediabetes", "Diabetes")) -> Diabetes | T43: 2004 | U43: Nov | V43: 12 | W43: =DATE(T43,MONTH(1&U43),V43) -> 38303 | Y43: =DATEDIF(W43,DATE(2023,6,8),"Y") -> 18 | AA43: 1121.87
A44: Fisher, Mr. Robert | B44: =TRIM(MID(A44,FIND(",",A44)+1,FIND(".",A44)-FIND(",",A44)-1)) -> Mr | C44: =LEFT(A44,FIND(",",A44)-1) -> Fisher | D44: =RIGHT(A44,FIND(",",A44)-1) -> Robert | F44: 1 | G44: =IF(F44="No major surgery",0,F44) -> 1 | J44: =PROPER('Medical Examinations'!D:D) -> No | K44: =PROPER('Medical Examinations'!H:H) -> Yes | N44: 35.5 | O44: =IF(N44<18.5,"Underweight", IF(N44<25,"Normal Weight", IF(N44<30,"Overweight", "Obesity"))) -> Obesity | Q44: 5.14 | R44: =IF(Q44<5.7,"Normal", IF(Q44<=6.4,"Prediabetes", "Diabetes")) -> Normal | T44: 2004 | U44: Jun | V44: 14 | W44: =DATE(T44,MONTH(1&U44),V44) -> 38152 | Y44: =DATEDIF(W44,DATE(2023,6,8),"Y") -> 18 | AA44: 1131.51
A45: Jenkins, Mr. James R. | B45: =TRIM(MID(A45,FIND(",",A45)+1,FIND(".",A45)-FIND(",",A45)-1)) -> Mr | C45: =LEFT(A45,FIND(",",A45)-1) -> Jenkins | D45: =RIGHT(A45,FIND(",",A45)-1) -> ames R. | F45: 1 | G45: =IF(F45="No major surgery",0,F45) -> 1 | J45: =PROPER('Medical Examinations'!D:D) -> No | K45: =PROPER('Medical Examinations'!H:H) -> Yes | N45: 52.58 | O45: =IF(N45<18.5,"Underweight", IF(N45<25,"Normal Weight", IF(N45<30,"Overweight", "Obesity"))) -> Obesity | Q45: 4.19 | R45: =IF(Q45<5.7,"Normal", IF(Q45<=6.4,"Prediabetes", "Diabetes")) -> Normal | T45: 2002 | U45: Jul | V45: 19 | W45: =DATE(T45,MONTH(1&U45),V45) -> 37456 | Y45: =DATEDIF(W45,DATE(2023,6,8),"Y") -> 20 | AA45: 1132
A46: Peters, Ms. Roseann | B46: =TRIM(MID(A46,FIND(",",A46)+1,FIND(".",A46)-FIND(",",A46)-1)) -> Ms | C46: =LEFT(A46,FIND(",",A46)-1) -> Peters | D46: =RIGHT(A46,FIND(",",A46)-1) -> oseann | F46: No major surgery | G46: =IF(F46="No major surgery",0,F46) -> 0 | J46: =PROPER('Medical Examinations'!D:D) -> Yes | K46: =PROPER('Medical Examinations'!H:H) -> Yes | N46: 35.2 | O46: =IF(N46<18.5,"Underweight", IF(N46<25,"Normal Weight", IF(N46<30,"Overweight", "Obesity"))) -> Obesity | Q46: 11.68 | R46: =IF(Q46<5.7,"Normal", IF(Q46<=6.4,"Prediabetes", "Diabetes")) -> Diabetes | T46: 2004 | U46: Oct | V46: 6 | W46: =DATE(T46,MONTH(1&U46),V46) -> 38266 | Y46: =DATEDIF(W46,DATE(2023,6,8),"Y") -> 18 | AA46: 1135
A47: Aha, Ms. Nicole | B47: =TRIM(MID(A47,FIND(",",A47)+1,FIND(".",A47)-FIND(",",A47)-1)) -> Ms | C47: =LEFT(A47,FIND(",",A47)-1) -> Aha | D47: =RIGHT(A47,FIND(",",A47)-1) -> ole | F47: No major surgery | G47: =IF(F47="No major surgery",0,F47) -> 0 | J47: =PROPER('Medical Examinations'!D:D) -> Yes | K47: =PROPER('Medical Examinations'!H:H) -> Yes | N47: 38.06 | O47: =IF(N47<18.5,"Underweight", IF(N47<25,"Normal Weight", IF(N47<30,"Overweight", "Obesity"))) -> Obesity | Q47: 6.98 | R47: =IF(Q47<5.7,"Normal", IF(Q47<=6.4,"Prediabetes", "Diabetes")) -> Diabetes | T47: 2004 | U47: Jun | V47: 11 | W47: =DATE(T47,MONTH(1&U47),V47) -> 38149 | Y47: =DATEDIF(W47,DATE(2023,6,8),"Y") -> 18 | AA47: 1135.94
A48: McElwain, Mr. Spencer | B48: =TRIM(MID(A48,FIND(",",A48)+1,FIND(".",A48)-FIND(",",A48)-1)) -> Mr | C48: =LEFT(A48,FIND(",",A48)-1) -> McElwain | D48: =RIGHT(A48,FIND(",",A48)-1) -> Spencer | F48: No major surgery | G48: =IF(F48="No major surgery",0,F48) -> 0 | J48: =PROPER('Medical Examinations'!D:D) -> Yes | K48: =PROPER('Medical Examinations'!H:H) -> Yes | N48: 34.21 | O48: =IF(N48<18.5,"Underweight", IF(N48<25,"Normal Weight", IF(N48<30,"Overweight", "Obesity"))) -> Obesity | Q48: 8.34 | R48: =IF(Q48<5.7,"Normal", IF(Q48<=6.4,"Prediabetes", "Diabetes")) -> Diabetes | T48: 2004 | U48: Nov | V48: 28 | W48: =DATE(T48,MONTH(1&U48),V48) -> 38319 | Y48: =DATEDIF(W48,DATE(2023,6,8),"Y") -> 18 | AA48: 1136.4
A49: Januszewski, Mr. Eric W | B49: =TRIM(MID(A49,FIND(",",A49)+1,FIND(".",A49)-FIND(",",A49)-1)) -> Mr | C49: =LEFT(A49,FIND(",",A49)-1) -> Januszewski | D49: =RIGHT(A49,FIND(",",A49)-1) -> Mr. Eric W | F49: 1 | G49: =IF(F49="No major surgery",0,F49) -> 1 | J49: =PROPER('Medical Examinations'!D:D) -> No | K49: =PROPER('Medical Examinations'!H:H) -> Yes | N49: 38.94 | O49: =IF(N49<18.5,"Underweight", IF(N49<25,"Normal Weight", IF(N49<30,"Overweight", "Obesity"))) -> Obesity | Q49: 8.49 | R49: =IF(Q49<5.7,"Normal", IF(Q49<=6.4,"Prediabetes", "Diabetes")) -> Diabetes | T49: 2002 | U49: Aug | V49: 11 | W49: =DATE(T49,MONTH(1&U49),V49) -> 37479 | Y49: =DATEDIF(W49,DATE(2023,6,8),"Y") -> 20 | AA49: 1137
A50: Rohne, Ms. Brianna L | B50: =TRIM(MID(A50,FIND(",",A50)+1,FIND(".",A50)-FIND(",",A50)-1)) -> Ms | C50: =LEFT(A50,FIND(",",A50)-1) -> Rohne | D50: =RIGHT(A50,FIND(",",A50)-1) -> nna L | F50: 1 | G50: =IF(F50="No major surgery",0,F50) -> 1 | J50: =PROPER('Medical Examinations'!D:D) -> Yes | K50: =PROPER('Medical Examinations'!H:H) -> Yes | N50: 30.21 | O50: =IF(N50<18.5,"Underweight", IF(N50<25,"Normal Weight", IF(N50<30,"Overweight", "Obesity"))) -> Obesity | Q50: 5.34 | R50: =IF(Q50<5.7,"Normal", IF(Q50<=6.4,"Prediabetes", "Diabetes")) -> Normal | T50: 2004 | U50: Nov | V50: 6 | W50: =DATE(T50,MONTH(1&U50),V50) -> 38297 | Y50: =DATEDIF(W50,DATE(2023,6,8),"Y") -> 18 | AA50: 1137.01
A51: O'Grady, Mr. Thomas J. | B51: =TRIM(MID(A51,FIND(",",A51)+1,FIND(".",A51)-FIND(",",A51)-1)) -> Mr | C51: =LEFT(A51,FIND(",",A51)-1) -> O'Grady | D51: =RIGHT(A51,FIND(",",A51)-1) -> omas J. | F51: 2 | G51: =IF(F51="No major surgery",0,F51) -> 2 | J51: =PROPER('Medical Examinations'!D:D) -> Yes | K51: =PROPER('Medical Examinations'!H:H) -> Yes | N51: 33.63 | O51: =IF(N51<18.5,"Underweight", IF(N51<25,"Normal Weight", IF(N51<30,"Overweight", "Obesity"))) -> Obesity | Q51: 4.43 | R51: =IF(Q51<5.7,"Normal", IF(Q51<=6.4,"Prediabetes", "Diabetes")) -> Normal | T51: 2004 | U51: Oct | V51: 15 | W51: =DATE(T51,MONTH(1&U51),V51) -> 38275 | Y51: =DATEDIF(W51,DATE(2023,6,8),"Y") -> 18 | AA51: 1137.01
A52: Peters, Ms. Melissa L | B52: =TRIM(MID(A52,FIND(",",A52)+1,FIND(".",A52)-FIND(",",A52)-1)) -> Ms | C52: =LEFT(A52,FIND(",",A52)-1) -> Peters | D52: =RIGHT(A52,FIND(",",A52)-1) -> issa L | F52: No major surgery | G52: =IF(F52="No major surgery",0,F52) -> 0 | J52: =PROPER('Medical Examinations'!D:D) -> Yes | K52: =PROPER('Medical Examinations'!H:H) -> Yes | N52: 40.37 | O52: =IF(N52<18.5,"Underweight", IF(N52<25,"Normal Weight", IF(N52<30,"Overweight", "Obesity"))) -> Obesity | Q52: 4.47 | R52: =IF(Q52<5.7,"Normal", IF(Q52<=6.4,"Prediabetes", "Diabetes")) -> Normal | T52: 2004 | U52: Nov | V52: 27 | W52: =DATE(T52,MONTH(1&U52),V52) -> 38318 | Y52: =DATEDIF(W52,DATE(2023,6,8),"Y") -> 18 | AA52: 1137.47
A53: De Simone, Mr. Flavio | B53: =TRIM(MID(A53,FIND(",",A53)+1,FIND(".",A53)-FIND(",",A53)-1)) -> Mr | C53: =LEFT(A53,FIND(",",A53)-1) -> De Simone | D53: =RIGHT(A53,FIND(",",A53)-1) -> . Flavio | F53: 2 | G53: =IF(F53="No major surgery",0,F53) -> 2 | J53: =PROPER('Medical Examinations'!D:D) -> No | K53: =PROPER('Medical Examinations'!H:H) -> Yes | N53: 53.09 | O53: =IF(N53<18.5,"Underweight", IF(N53<25,"Normal Weight", IF(N53<30,"Overweight", "Obesity"))) -> Obesity | Q53: 4.82 | R53: =IF(Q53<5.7,"Normal", IF(Q53<=6.4,"Prediabetes", "Diabetes")) -> Normal | T53: 2001 | U53: Oct | V53: 25 | W53: =DATE(T53,MONTH(1&U53),V53) -> 37189 | Y53: =DATEDIF(W53,DATE(2023,6,8),"Y") -> 21 | AA53: 1141
A54: Beckett, Mr. Ryan | B54: =TRIM(MID(A54,FIND(",",A54)+1,FIND(".",A54)-FIND(",",A54)-1)) -> Mr | C54: =LEFT(A54,FIND(",",A54)-1) -> Beckett | D54: =RIGHT(A54,FIND(",",A54)-1) -> . Ryan | F54: 2 | G54: =IF(F54="No major surgery",0,F54) -> 2 | J54: =PROPER('Medical Examinations'!D:D) -> Yes | K54: =PROPER('Medical Examinations'!H:H) -> Yes | N54: 31.79 | O54: =IF(N54<18.5,"Underweight", IF(N54<25,"Normal Weight", IF(N54<30,"Overweight", "Obesity"))) -> Obesity | Q54: 5.51 | R54: =IF(Q54<5.7,"Normal", IF(Q54<=6.4,"Prediabetes", "Diabetes")) -> Normal | T54: 2004 | U54: Sep | V54: 12 | W54: =DATE(T54,MONTH(1&U54),V54) -> 38242 | Y54: =DATEDIF(W54,DATE(2023,6,8),"Y") -> 18 | AA54: 1141.45
A55: Sobrilsky, Mr. Anthony J. | B55: =TRIM(MID(A55,FIND(",",A55)+1,FIND(".",A55)-FIND(",",A55)-1)) -> Mr | C55: =LEFT(A55,FIND(",",A55)-1) -> Sobrilsky | D55: =RIGHT(A55,FIND(",",A55)-1) -> nthony J. | F55: 1 | G55: =IF(F55="No major surgery",0,F55) -> 1 | J55: =PROPER('Medical Examinations'!D:D) -> No | K55: =PROPER('Medical Examinations'!H:H) -> Yes | N55: 41.895 | O55: =IF(N55<18.5,"Underweight", IF(N55<25,"Normal Weight", IF(N55<30,"Overweight", "Obesity"))) -> Obesity | Q55: 10.87 | R55: =IF(Q55<5.7,"Normal", IF(Q55<=6.4,"Prediabetes", "Diabetes")) -> Diabetes | T55: 2002 | U55: Oct | V55: 1 | W55: =DATE(T55,MONTH(1&U55),V55) -> 37530 | Y55: =DATEDIF(W55,DATE(2023,6,8),"Y") -> 20 | AA55: 1142
A56: Wang, Ms. Alex | B56: =TRIM(MID(A56,FIND(",",A56)+1,FIND(".",A56)-FIND(",",A56)-1)) -> Ms | C56: =LEFT(A56,FIND(",",A56)-1) -> Wang | D56: =RIGHT(A56,FIND(",",A56)-1) -> Alex | F56: No major surgery | G56: =IF(F56="No major surgery",0,F56) -> 0 | J56: =PROPER('Medical Examinations'!D:D) -> No | K56: =PROPER('Medical Examinations'!H:H) -> Yes | N56: 31.16 | O56: =IF(N56<18.5,"Underweight", IF(N56<25,"Normal Weight", IF(N56<30,"Overweight", "Obesity"))) -> Obesity | Q56: 9.34 | R56: =IF(Q56<5.7,"Normal", IF(Q56<=6.4,"Prediabetes", "Diabetes")) -> Diabetes | T56: 2004 | U56: Jun | V56: 10 | W56: =DATE(T56,MONTH(1&U56),V56) -> 38148 | Y56: =DATEDIF(W56,DATE(2023,6,8),"Y") -> 18 | AA56: 1146.8
A57: Campa, Mr. David | B57: =TRIM(MID(A57,FIND(",",A57)+1,FIND(".",A57)-FIND(",",A57)-1)) -> Mr | C57: =LEFT(A57,FIND(",",A57)-1) -> Campa | D57: =RIGHT(A57,FIND(",",A57)-1) -> David | F57: 1 | G57: =IF(F57="No major surgery",0,F57) -> 1 | J57: =PROPER('Medical Examinations'!D:D) -> Yes | K57: =PROPER('Medical Examinations'!H:H) -> Yes | N57: 34.105 | O57: =IF(N57<18.5,"Underweight", IF(N57<25,"Normal Weight", IF(N57<30,"Overweight", "Obesity"))) -> Obesity | Q57: 5.03 | R57: =IF(Q57<5.7,"Normal", IF(Q57<=6.4,"Prediabetes", "Diabetes")) -> Normal | T57: 2003 | U57: Jun | V57: 12 | W57: =DATE(T57,MONTH(1&U57),V57) -> 37784 | Y57: =DATEDIF(W57,DATE(2023,6,8),"Y") -> 19 | AA57: 1149
A58: Clifford, Mr. Andrew B | B58: =TRIM(MID(A58,FIND(",",A58)+1,FIND(".",A58)-FIND(",",A58)-1)) -> Mr | C58: =LEFT(A58,FIND(",",A58)-1) -> Clifford | D58: =RIGHT(A58,FIND(",",A58)-1) -> Andrew B | F58: No major surgery | G58: =IF(F58="No major surgery",0,F58) -> 0 | J58: =PROPER('Medical Examinations'!D:D) -> No | K58: =PROPER('Medical Examinations'!H:H) -> Yes | N58: 51.93 | O58: =IF(N58<18.5,"Underweight", IF(N58<25,"Normal Weight", IF(N58<30,"Overweight", "Obesity"))) -> Obesity | Q58: 11.05 | R58: =IF(Q58<5.7,"Normal", IF(Q58<=6.4,"Prediabetes", "Diabetes")) -> Diabetes | T58: 2004 | U58: Jul | V58: 18 | W58: =DATE(T58,MONTH(1&U58),V58) -> 38186 | Y58: =DATEDIF(W58,DATE(2023,6,8),"Y") -> 18 | AA58: 1149.4
A59: Dalmata, Ms. Dara E | B59: =TRIM(MID(A59,FIND(",",A59)+1,FIND(".",A59)-FIND(",",A59)-1)) -> Ms | C59: =LEFT(A59,FIND(",",A59)-1) -> Dalmata | D59: =RIGHT(A59,FIND(",",A59)-1) -> Dara E | F59: No major surgery | G59: =IF(F59="No major surgery",0,F59) -> 0 | J59: =PROPER('Medical Examinations'!D:D) -> No | K59: =PROPER('Medical Examinations'!H:H) -> Yes | N59: 38.95 | O59: =IF(N59<18.5,"Underweight", IF(N59<25,"Normal Weight", IF(N59<30,"Overweight", "Obesity"))) -> Obesity | Q59: 11.95 | R59: =IF(Q59<5.7,"Normal", IF(Q59<=6.4,"Prediabetes", "Diabetes")) -> Diabetes | T59: 1994 | U59: Jul | V59: 26 | W59: =DATE(T59,MONTH(1&U59),V59) -> 34541 | Y59: =DATEDIF(W59,DATE(2023,6,8),"Y") -> 28 | AA59: 1158.32
A60: Vishik, Ms. Inna | B60: =TRIM(MID(A60,FIND(",",A60)+1,FIND(".",A60)-FIND(",",A60)-1)) -> Ms | C60: =LEFT(A60,FIND(",",A60)-1) -> Vishik | D60: =RIGHT(A60,FIND(",",A60)-1) -> Inna | F60: 1 | G60: =IF(F60="No major surgery",0,F60) -> 1 | J60: =PROPER('Medical Examinations'!D:D) -> No | K60: =PROPER('Medical Examinations'!H:H) -> Yes | N60: 36.63 | O60: =IF(N60<18.5,"Underweight", IF(N60<25,"Normal Weight", IF(N60<30,"Overweight", "Obesity"))) -> Obesity | Q60: 7.72 | R60: =IF(Q60<5.7,"Normal", IF(Q60<=6.4,"Prediabetes", "Diabetes")) -> Diabetes | T60: 2004 | U60: Nov | V60: 11 | W60: =DATE(T60,MONTH(1&U60),V60) -> 38302 | Y60: =DATEDIF(W60,DATE(2023,6,8),"Y") -> 18 | AA60: 1163.46
A61: Schorr, Mr. Ari | B61: =TRIM(MID(A61,FIND(",",A61)+1,FIND(".",A61)-FIND(",",A61)-1)) -> Mr | C61: =LEFT(A61,FIND(",",A61)-1) -> Schorr | D61: =RIGHT(A61,FIND(",",A61)-1) -> . Ari | F61: 2 | G61: =IF(F61="No major surgery",0,F61) -> 2 | J61: =PROPER('Medical Examinations'!D:D) -> No | K61: =PROPER('Medical Examinations'!H:H) -> Yes | N61: 34.2 | O61: =IF(N61<18.5,"Underweight", IF(N61<25,"Normal Weight", IF(N61<30,"Overweight", "Obesity"))) -> Obesity | Q61: 5.75 | R61: =IF(Q61<5.7,"Normal", IF(Q61<=6.4,"Prediabetes", "Diabetes")) -> Prediabetes | T61: 2002 | U61: Jun | V61: 11 | W61: =DATE(T61,MONTH(1&U61),V61) -> 37418 | Y61: =DATEDIF(W61,DATE(2023,6,8),"Y") -> 20 | AA61: 1165
A62: Lusardi, Ms. Lindsey | B62: =TRIM(MID(A62,FIND(",",A62)+1,FIND(".",A62)-FIND(",",A62)-1)) -> Ms | C62: =LEFT(A62,FIND(",",A62)-1) -> Lusardi | D62: =RIGHT(A62,FIND(",",A62)-1) -> Lindsey | F62: No major surgery | G62: =IF(F62="No major surgery",0,F62) -> 0 | J62: =PROPER('Medical Examinations'!D:D) -> No | K62: =PROPER('Medical Examinations'!H:H) -> Yes | N62: 50.63 | O62: =IF(N62<18.5,"Underweight", IF(N62<25,"Normal Weight", IF(N62<30,"Overweight", "Obesity"))) -> Obesity | Q62: 11.89 | R62: =IF(Q62<5.7,"Normal", IF(Q62<=6.4,"Prediabetes", "Diabetes")) -> Diabetes | T62: 2001 | U62: Nov | V62: 12 | W62: =DATE(T62,MONTH(1&U62),V62) -> 37207 | Y62: =DATEDIF(W62,DATE(2023,6,8),"Y") -> 21 | AA62: 1167
A63: Rayner, Mr. Kenny | B63: =TRIM(MID(A63,FIND(",",A63)+1,FIND(".",A63)-FIND(",",A63)-1)) -> Mr | C63: =LEFT(A63,FIND(",",A63)-1) -> Rayner | D63: =RIGHT(A63,FIND(",",A63)-1) -> Kenny | F63: No major surgery | G63: =IF(F63="No major surgery",0,F63) -> 0 | J63: =PROPER('Medical Examinations'!D:D) -> Yes | K63: =PROPER('Medical Examinations'!H:H) -> Yes | N63: 36.48 | O63: =IF(N63<18.5,"Underweight", IF(N63<25,"Normal Weight", IF(N63<30,"Overweight", "Obesity"))) -> Obesity | Q63: 6.2 | R63: =IF(Q63<5.7,"Normal", IF(Q63<=6.4,"Prediabetes", "Diabetes")) -> Prediabetes | T63: 1996 | U63: Aug | V63: 11 | W63: =DATE(T63,MONTH(1&U63),V63) -> 35288 | Y63: =DATEDIF(W63,DATE(2023,6,8),"Y") -> 26 | AA63: 1178
A64: Voghel, Ms. Louise | B64: =TRIM(MID(A64,FIND(",",A64)+1,FIND(".",A64)-FIND(",",A64)-1)) -> Ms | C64: =LEFT(A64,FIND(",",A64)-1) -> Voghel | D64: =RIGHT(A64,FIND(",",A64)-1) -> Louise | F64: No major surgery | G64: =IF(F64="No major surgery",0,F64) -> 0 | J64: =PROPER('Medical Examinations'!D:D) -> No | K64: =PROPER('Medical Examinations'!H:H) -> Yes | N64: 54.82 | O64: =IF(N64<18.5,"Underweight", IF(N64<25,"Normal Weight", IF(N64<30,"Overweight", "Obesity"))) -> Obesity | Q64: 10.61 | R64: =IF(Q64<5.7,"Normal", IF(Q64<=6.4,"Prediabetes", "Diabetes")) -> Diabetes | T64: 1997 | U64: Jun | V64: 28 | W64: =DATE(T64,MONTH(1&U64),V64) -> 35609 | Y64: =DATEDIF(W64,DATE(2023,6,8),"Y") -> 25 | AA64: 1178.07
A65: Rieth, Mr. Cameron | B65: =TRIM(MID(A65,FIND(",",A65)+1,FIND(".",A65)-FIND(",",A65)-1)) -> Mr | C65: =LEFT(A65,FIND(",",A65)-1) -> Rieth | D65: =RIGHT(A65,FIND(",",A65)-1) -> meron | F65: 1 | G65: =IF(F65="No major surgery",0,F65) -> 1 | J65: =PROPER('Medical Examinations'!D:D) -> Yes | K65: =PROPER('Medical Examinations'!H:H) -> Yes | N65: 38.06 | O65: =IF(N65<18.5,"Underweight", IF(N65<25,"Normal Weight", IF(N65<30,"Overweight", "Obesity"))) -> Obesity | Q65: 6.04 | R65: =IF(Q65<5.7,"Normal", IF(Q65<=6.4,"Prediabetes", "Diabetes")) -> Prediabetes | T65: 2002 | U65: Aug | V65: 26 | W65: =DATE(T65,MONTH(1&U65),V65) -> 37494 | Y65: =DATEDIF(W65,DATE(2023,6,8),"Y") -> 20 | AA65: 1191
A66: Gollotto, Ms. Katie T. | B66: =TRIM(MID(A66,FIND(",",A66)+1,FIND(".",A66)-FIND(",",A66)-1)) -> Ms | C66: =LEFT(A66,FIND(",",A66)-1) -> Gollotto | D66: =RIGHT(A66,FIND(",",A66)-1) -> Katie T. | F66: No major surgery | G66: =IF(F66="No major surgery",0,F66) -> 0 | J66: =PROPER('Medical Examinations'!D:D) -> Yes | K66: =PROPER('Medical Examinations'!H:H) -> Yes | N66: 51.48 | O66: =IF(N66<18.5,"Underweight", IF(N66<25,"Normal Weight", IF(N66<30,"Overweight", "Obesity"))) -> Obesity | Q66: 9.33 | R66: =IF(Q66<5.7,"Normal", IF(Q66<=6.4,"Prediabetes", "Diabetes")) -> Diabetes | T66: 1999 | U66: Jun | V66: 28 | W66: =DATE(T66,MONTH(1&U66),V66) -> 36339 | Y66: =DATEDIF(W66,DATE(2023,6,8),"Y") -> 23 | AA66: 1200
A67: Dunn, Ms. Casey | B67: =TRIM(MID(A67,FIND(",",A67)+1,FIND(".",A67)-FIND(",",A67)-1)) -> Ms | C67: =LEFT(A67,FIND(",",A67)-1) -> Dunn | D67: =RIGHT(A67,FIND(",",A67)-1) -> asey | F67: No major surgery | G67: =IF(F67="No major surgery",0,F67) -> 0 | J67: =PROPER('Medical Examinations'!D:D) -> No | K67: =PROPER('Medical Examinations'!H:H) -> Yes | N67: 52.06 | O67: =IF(N67<18.5,"Underweight", IF(N67<25,"Normal Weight", IF(N67<30,"Overweight", "Obesity"))) -> Obesity | Q67: 11.47 | R67: =IF(Q67<5.7,"Normal", IF(Q67<=6.4,"Prediabetes", "Diabetes")) -> Diabetes | T67: 1992 | U67: Oct | V67: 6 | W67: =DATE(T67,MONTH(1&U67),V67) -> 33883 | Y67: =DATEDIF(W67,DATE(2023,6,8),"Y") -> 30 | AA67: 1200.55
A68: Blitzer, Mr. David | B68: =TRIM(MID(A68,FIND(",",A68)+1,FIND(".",A68)-FIND(",",A68)-1)) -> Mr | C68: =LEFT(A68,FIND(",",A68)-1) -> Blitzer | D68: =RIGHT(A68,FIND(",",A68)-1) -> David | F68: No major surgery | G68: =IF(F68="No major surgery",0,F68) -> 0 | J68: =PROPER('Medical Examinations'!D:D) -> No | K68: =PROPER('Medical Examinations'!H:H) -> Yes | N68: 30.685 | O68: =IF(N68<18.5,"Underweight", IF(N68<25,"Normal Weight", IF(N68<30,"Overweight", "Obesity"))) -> Obesity | Q68: 7.02 | R68: =IF(Q68<5.7,"Normal", IF(Q68<=6.4,"Prediabetes", "Diabetes")) -> Diabetes | T68: 2004 | U68: Jun | V68: 2 | W68: =DATE(T68,MONTH(1&U68),V68) -> 38140 | Y68: =DATEDIF(W68,DATE(2023,6,8),"Y") -> 19 | AA68: 1210
A69: Smith, Mr. Bryson C. | B69: =TRIM(MID(A69,FIND(",",A69)+1,FIND(".",A69)-FIND(",",A69)-1)) -> Mr | C69: =LEFT(A69,FIND(",",A69)-1) -> Smith | D69: =RIGHT(A69,FIND(",",A69)-1) -> on C. | F69: 1 | G69: =IF(F69="No major surgery",0,F69) -> 1 | J69: =PROPER('Medical Examinations'!D:D) -> Yes | K69: =PROPER('Medical Examinations'!H:H) -> Yes | N69: 36.08 | O69: =IF(N69<18.5,"Underweight", IF(N69<25,"Normal Weight", IF(N69<30,"Overweight", "Obesity"))) -> Obesity | Q69: 8.8 | R69: =IF(Q69<5.7,"Normal", IF(Q69<=6.4,"Prediabetes", "Diabetes")) -> Diabetes | T69: 1996 | U69: Nov | V69: 4 | W69: =DATE(T69,MONTH(1&U69),V69) -> 35373 | Y69: =DATEDIF(W69,DATE(2023,6,8),"Y") -> 26 | AA69: 1220
A70: Hyland, Ms. Megan | B70: =TRIM(MID(A70,FIND(",",A70)+1,FIND(".",A70)-FIND(",",A70)-1)) -> Ms | C70: =LEFT(A70,FIND(",",A70)-1) -> Hyland | D70: =RIGHT(A70,FIND(",",A70)-1) -> Megan | F70: 2 | G70: =IF(F70="No major surgery",0,F70) -> 2 | J70: =PROPER('Medical Examinations'!D:D) -> Yes | K70: =PROPER('Medical Examinations'!H:H) -> Yes | N70: 54.99 | O70: =IF(N70<18.5,"Underweight", IF(N70<25,"Normal Weight", IF(N70<30,"Overweight", "Obesity"))) -> Obesity | Q70: 8.68 | R70: =IF(Q70<5.7,"Normal", IF(Q70<=6.4,"Prediabetes", "Diabetes")) -> Diabetes | T70: 2004 | U70: Jul | V70: 9 | W70: =DATE(T70,MONTH(1&U70),V70) -> 38177 | Y70: =DATEDIF(W70,DATE(2023,6,8),"Y") -> 18 | AA70: 1224
A71: Ducharme, Mr. Daniel | B71: =TRIM(MID(A71,FIND(",",A71)+1,FIND(".",A71)-FIND(",",A71)-1)) -> Mr | C71: =LEFT(A71,FIND(",",A71)-1) -> Ducharme | D71: =RIGHT(A71,FIND(",",A71)-1) -> Daniel | F71: 1 | G71: =IF(F71="No major surgery",0,F71) -> 1 | J71: =PROPER('Medical Examinations'!D:D) -> No | K71: =PROPER('Medical Examinations'!H:H) -> Yes | N71: 35.97 | O71: =IF(N71<18.5,"Underweight", IF(N71<25,"Normal Weight", IF(N71<30,"Overweight", "Obesity"))) -> Obesity | Q71: 6.12 | R71: =IF(Q71<5.7,"Normal", IF(Q71<=6.4,"Prediabetes", "Diabetes")) -> Prediabetes | T71: 2004 | U71: Oct | V71: 16 | W71: =DATE(T71,MONTH(1&U71),V71) -> 38276 | Y71: =DATEDIF(W71,DATE(2023,6,8),"Y") -> 18 | AA71: 1228
A72: Johnson, Mr. Steven M. | B72: =TRIM(MID(A72,FIND(",",A72)+1,FIND(".",A72)-FIND(",",A72)-1)) -> Mr | C72: =LEFT(A72,FIND(",",A72)-1) -> Johnson | D72: =RIGHT(A72,FIND(",",A72)-1) -> even M. | F72: 1 | G72: =IF(F72="No major surgery",0,F72) -> 1 | J72: =PROPER('Medical Examinations'!D:D) -> No | K72: =PROPER('Medical Examinations'!H:H) -> Yes | N72: 45.54 | O72: =IF(N72<18.5,"Underweight", IF(N72<25,"Normal Weight", IF(N72<30,"Overweight", "Obesity"))) -> Obesity | Q72: 5.4 | R72: =IF(Q72<5.7,"Normal", IF(Q72<=6.4,"Prediabetes", "Diabetes")) -> Normal | T72: 1998 | U72: Jul | V72: 13 | W72: =DATE(T72,MONTH(1&U72),V72) -> 35989 | Y72: =DATEDIF(W72,DATE(2023,6,8),"Y") -> 24 | AA72: 1234
A73: Mutz, Ms. Jenna L. | B73: =TRIM(MID(A73,FIND(",",A73)+1,FIND(".",A73)-FIND(",",A73)-1)) -> Ms | C73: =LEFT(A73,FIND(",",A73)-1) -> Mutz | D73: =RIGHT(A73,FIND(",",A73)-1) -> a L. | F73: No major surgery | G73: =IF(F73="No major surgery",0,F73) -> 0 | J73: =PROPER('Medical Examinations'!D:D) -> No | K73: =PROPER('Medical Examinations'!H:H) -> Yes | N73: 35.53 | O73: =IF(N73<18.5,"Underweight", IF(N73<25,"Normal Weight", IF(N73<30,"Overweight", "Obesity"))) -> Obesity | Q73: 4.36 | R73: =IF(Q73<5.7,"Normal", IF(Q73<=6.4,"Prediabetes", "Diabetes")) -> Normal | T73: 2002 | U73: Dec | V73: 12 | W73: =DATE(T73,MONTH(1&U73),V73) -> 37602 | Y73: =DATEDIF(W73,DATE(2023,6,8),"Y") -> 20 | AA73: 1237
A74: Lee, Mr. Freeman | B74: =TRIM(MID(A74,FIND(",",A74)+1,FIND(".",A74)-FIND(",",A74)-1)) -> Mr | C74: =LEFT(A74,FIND(",",A74)-1) -> Lee | D74: =RIGHT(A74,FIND(",",A74)-1) -> man | F74: No major surgery | G74: =IF(F74="No major surgery",0,F74) -> 0 | J74: =PROPER('Medical Examinations'!D:D) -> Yes | K74: =PROPER('Medical Examinations'!H:H) -> Yes | N74: 30.8 | O74: =IF(N74<18.5,"Underweight", IF(N74<25,"Normal Weight", IF(N74<30,"Overweight", "Obesity"))) -> Obesity | Q74: 9.77 | R74: =IF(Q74<5.7,"Normal", IF(Q74<=6.4,"Prediabetes", "Diabetes")) -> Diabetes | T74: 1998 | U74: Oct | V74: 11 | W74: =DATE(T74,MONTH(1&U74),V74) -> 36079 | Y74: =DATEDIF(W74,DATE(2023,6,8),"Y") -> 24 | AA74: 1240
A75: Turner, Mr. Jeff | B75: =TRIM(MID(A75,FIND(",",A75)+1,FIND(".",A75)-FIND(",",A75)-1)) -> Mr | C75: =LEFT(A75,FIND(",",A75)-1) -> Turner | D75: =RIGHT(A75,FIND(",",A75)-1) -> Jeff | F75: 1 | G75: =IF(F75="No major surgery",0,F75) -> 1 | J75: =PROPER('Medical Examinations'!D:D) -> No | K75: =PROPER('Medical Examinations'!H:H) -> Yes | N75: 38.39 | O75: =IF(N75<18.5,"Underweight", IF(N75<25,"Normal Weight", IF(N75<30,"Overweight", "Obesity"))) -> Obesity | Q75: 4.25 | R75: =IF(Q75<5.7,"Normal", IF(Q75<=6.4,"Prediabetes", "Diabetes")) -> Normal | T75: 2002 | U75: Jul | V75: 1 | W75: =DATE(T75,MONTH(1&U75),V75) -> 37438 | Y75: =DATEDIF(W75,DATE(2023,6,8),"Y") -> 20 | AA75: 1241
A76: Rangel, Mr. Elenilton V. Sr. | B76: =TRIM(MID(A76,FIND(",",A76)+1,FIND(".",A76)-FIND(",",A76)-1)) -> Mr | C76: =LEFT(A76,FIND(",",A76)-1) -> Rangel | D76: =RIGHT(A76,FIND(",",A76)-1) -> V. Sr. | F76: 2 | G76: =IF(F76="No major surgery",0,F76) -> 2 | J76: =PROPER('Medical Examinations'!D:D) -> Yes | K76: =PROPER('Medical Examinations'!H:H) -> Yes | N76: 32.3 | O76: =IF(N76<18.5,"Underweight", IF(N76<25,"Normal Weight", IF(N76<30,"Overweight", "Obesity"))) -> Obesity | Q76: 4.76 | R76: =IF(Q76<5.7,"Normal", IF(Q76<=6.4,"Prediabetes", "Diabetes")) -> Normal | T76: 2003 | U76: Aug | V76: 2 | W76: =DATE(T76,MONTH(1&U76),V76) -> 37835 | Y76: =DATEDIF(W76,DATE(2023,6,8),"Y") -> 19 | AA76: 1241.57
A77: Lacey, Ms. Maurya | B77: =TRIM(MID(A77,FIND(",",A77)+1,FIND(".",A77)-FIND(",",A77)-1)) -> Ms | C77: =LEFT(A77,FIND(",",A77)-1) -> Lacey | D77: =RIGHT(A77,FIND(",",A77)-1) -> aurya | F77: 2 | G77: =IF(F77="No major surgery",0,F77) -> 2 | J77: =PROPER('Medical Examinations'!D:D) -> Yes | K77: =PROPER('Medical Examinations'!H:H) -> Yes | N77: 48.8 | O77: =IF(N77<18.5,"Underweight", IF(N77<25,"Normal Weight", IF(N77<30,"Overweight", "Obesity"))) -> Obesity | Q77: 6.22 | R77: =IF(Q77<5.7,"Normal", IF(Q77<=6.4,"Prediabetes", "Diabetes")) -> Prediabetes | T77: 2003 | U77: Sep | V77: 15 | W77: =DATE(T77,MONTH(1&U77),V77) -> 37879 | Y77: =DATEDIF(W77,DATE(2023,6,8),"Y") -> 19 | AA77: 1242.26
A78: Stiger, Ms. Samantha C | B78: =TRIM(MID(A78,FIND(",",A78)+1,FIND(".",A78)-FIND(",",A78)-1)) -> Ms | C78: =LEFT(A78,FIND(",",A78)-1) -> Stiger | D78: =RIGHT(A78,FIND(",",A78)-1) -> ntha C | F78: No major surgery | G78: =IF(F78="No major surgery",0,F78) -> 0 | J78: =PROPER('Medical Examinations'!D:D) -> Yes | K78: =PROPER('Medical Examinations'!H:H) -> Yes | N78: 45.5 | O78: =IF(N78<18.5,"Underweight", IF(N78<25,"Normal Weight", IF(N78<30,"Overweight", "Obesity"))) -> Obesity | Q78: 7.96 | R78: =IF(Q78<5.7,"Normal", IF(Q78<=6.4,"Prediabetes", "Diabetes")) -> Diabetes | T78: 2003 | U78: Sep | V78: 8 | W78: =DATE(T78,MONTH(1&U78),V78) -> 37872 | Y78: =DATEDIF(W78,DATE(2023,6,8),"Y") -> 19 | AA78: 1242.82
A79: Caldwell, Ms. Bethany A | B79: =TRIM(MID(A79,FIND(",",A79)+1,FIND(".",A79)-FIND(",",A79)-1)) -> Ms | C79: =LEFT(A79,FIND(",",A79)-1) -> Caldwell | D79: =RIGHT(A79,FIND(",",A79)-1) -> ethany A | F79: 1 | G79: =IF(F79="No major surgery",0,F79) -> 1 | J79: =PROPER('Medical Examinations'!D:D) -> No | K79: =PROPER('Medical Examinations'!H:H) -> Yes | N79: 53.61 | O79: =IF(N79<18.5,"Underweight", IF(N79<25,"Normal Weight", IF(N79<30,"Overweight", "Obesity"))) -> Obesity | Q79: 10.92 | R79: =IF(Q79<5.7,"Normal", IF(Q79<=6.4,"Prediabetes", "Diabetes")) -> Diabetes | T79: 2003 | U79: Sep | V79: 15 | W79: =DATE(T79,MONTH(1&U79),V79) -> 37879 | Y79: =DATEDIF(W79,DATE(2023,6,8),"Y") -> 19 | AA79: 1252.41
A80: Marmillod, Mr. Yves | B80: =TRIM(MID(A80,FIND(",",A80)+1,FIND(".",A80)-FIND(",",A80)-1)) -> Mr | C80: =LEFT(A80,FIND(",",A80)-1) -> Marmillod | D80: =RIGHT(A80,FIND(",",A80)-1) -> Mr. Yves | F80: 1 | G80: =IF(F80="No major surgery",0,F80) -> 1 | J80: =PROPER('Medical Examinations'!D:D) -> Yes | K80: =PROPER('Medical Examinations'!H:H) -> Yes | N80: 36.19 | O80: =IF(N80<18.5,"Underweight", IF(N80<25,"Normal Weight", IF(N80<30,"Overweight", "Obesity"))) -> Obesity | Q80: 11.51 | R80: =IF(Q80<5.7,"Normal", IF(Q80<=6.4,"Prediabetes", "Diabetes")) -> Diabetes | T80: 1997 | U80: Nov | V80: 4 | W80: =DATE(T80,MONTH(1&U80),V80) -> 35738 | Y80: =DATEDIF(W80,DATE(2023,6,8),"Y") -> 25 | AA80: 1253
A81: Cloutier-Simons, Ms. Danielle | B81: =TRIM(MID(A81,FIND(",",A81)+1,FIND(".",A81)-FIND(",",A81)-1)) -> Ms | C81: =LEFT(A81,FIND(",",A81)-1) -> Cloutier-Simons | D81: =RIGHT(A81,FIND(",",A81)-1) -> , Ms. Danielle | F81: No major surgery | G81: =IF(F81="No major surgery",0,F81) -> 0 | J81: =PROPER('Medical Examinations'!D:D) -> No | K81: =PROPER('Medical Examinations'!H:H) -> Yes | N81: 34.6 | O81: =IF(N81<18.5,"Underweight", IF(N81<25,"Normal Weight", IF(N81<30,"Overweight", "Obesity"))) -> Obesity | Q81: 5.99 | R81: =IF(Q81<5.7,"Normal", IF(Q81<=6.4,"Prediabetes", "Diabetes")) -> Prediabetes | T81: 2003 | U81: Dec | V81: 10 | W81: =DATE(T81,MONTH(1&U81),V81) -> 37965 | Y81: =DATEDIF(W81,DATE(2023,6,8),"Y") -> 19 | AA81: 1253.94
A82: Vegas, Ms. Julia | B82: =TRIM(MID(A82,FIND(",",A82)+1,FIND(".",A82)-FIND(",",A82)-1)) -> Ms | C82: =LEFT(A82,FIND(",",A82)-1) -> Vegas | D82: =RIGHT(A82,FIND(",",A82)-1) -> Julia | F82: No major surgery | G82: =IF(F82="No major surgery",0,F82) -> 0 | J82: =PROPER('Medical Examinations'!D:D) -> Yes | K82: =PROPER('Medical Examinations'!H:H) -> Yes | N82: 54.12 | O82: =IF(N82<18.5,"Underweight", IF(N82<25,"Normal Weight", IF(N82<30,"Overweight", "Obesity"))) -> Obesity | Q82: 11.57 | R82: =IF(Q82<5.7,"Normal", IF(Q82<=6.4,"Prediabetes", "Diabetes")) -> Diabetes | T82: 2003 | U82: Oct | V82: 13 | W82: =DATE(T82,MONTH(1&U82),V82) -> 37907 | Y82: =DATEDIF(W82,DATE(2023,6,8),"Y") -> 19 | AA82: 1256.3
A83: Cochran, Mr. Joshua | B83: =TRIM(MID(A83,FIND(",",A83)+1,FIND(".",A83)-FIND(",",A83)-1)) -> Mr | C83: =LEFT(A83,FIND(",",A83)-1) -> Cochran | D83: =RIGHT(A83,FIND(",",A83)-1) -> Joshua | F83: No major surgery | G83: =IF(F83="No major surgery",0,F83) -> 0 | J83: =PROPER('Medical Examinations'!D:D) -> No | K83: =PROPER('Medical Examinations'!H:H) -> Yes | N83: 48.82 | O83: =IF(N83<18.5,"Underweight", IF(N83<25,"Normal Weight", IF(N83<30,"Overweight", "Obesity"))) -> Obesity | Q83: 6.67 | R83: =IF(Q83<5.7,"Normal", IF(Q83<=6.4,"Prediabetes", "Diabetes")) -> Diabetes | T83: 2003 | U83: Oct | V83: 30 | W83: =DATE(T83,MONTH(1&U83),V83) -> 37924 | Y83: =DATEDIF(W83,DATE(2023,6,8),"Y") -> 19 | AA83: 1261.44
A84: Holtzapple, Ms. Jennifer | B84: =TRIM(MID(A84,FIND(",",A84)+1,FIND(".",A84)-FIND(",",A84)-1)) -> Ms | C84: =LEFT(A84,FIND(",",A84)-1) -> Holtzapple | D84: =RIGHT(A84,FIND(",",A84)-1) -> Jennifer | F84: No major surgery | G84: =IF(F84="No major surgery",0,F84) -> 0 | J84: =PROPER('Medical Examinations'!D:D) -> Yes | K84: =PROPER('Medical Examinations'!H:H) -> Yes | N84: 51.01 | O84: =IF(N84<18.5,"Underweight", IF(N84<25,"Normal Weight", IF(N84<30,"Overweight", "Obesity"))) -> Obesity | Q84: 9.2 | R84: =IF(Q84<5.7,"Normal", IF(Q84<=6.4,"Prediabetes", "Diabetes")) -> Diabetes | T84: 2003 | U84: Aug | V84: 15 | W84: =DATE(T84,MONTH(1&U84),V84) -> 37848 | Y84: =DATEDIF(W84,DATE(2023,6,8),"Y") -> 19 | AA84: 1261.86
A85: Meyer, Ms. Gwen M. | B85: =TRIM(MID(A85,FIND(",",A85)+1,FIND(".",A85)-FIND(",",A85)-1)) -> Ms | C85: =LEFT(A85,FIND(",",A85)-1) -> Meyer | D85: =RIGHT(A85,FIND(",",A85)-1) -> en M. | F85: 1 | G85: =IF(F85="No major surgery",0,F85) -> 1 | J85: =PROPER('Medical Examinations'!D:D) -> Yes | K85: =PROPER('Medical Examinations'!H:H) -> Yes | N85: 45.65 | O85: =IF(N85<18.5,"Underweight", IF(N85<25,"Normal Weight", IF(N85<30,"Overweight", "Obesity"))) -> Obesity | Q85: 5.11 | R85: =IF(Q85<5.7,"Normal", IF(Q85<=6.4,"Prediabetes", "Diabetes")) -> Normal | T85: 2003 | U85: Nov | V85: 21 | W85: =DATE(T85,MONTH(1&U85),V85) -> 37946 | Y85: =DATEDIF(W85,DATE(2023,6,8),"Y") -> 19 | AA85: 1263.25
A86: Brickley, Mr. Patrick | B86: =TRIM(MID(A86,FIND(",",A86)+1,FIND(".",A86)-FIND(",",A86)-1)) -> Mr | C86: =LEFT(A86,FIND(",",A86)-1) -> Brickley | D86: =RIGHT(A86,FIND(",",A86)-1) -> Patrick | F86: No major surgery | G86: =IF(F86="No major surgery",0,F86) -> 0 | J86: =PROPER('Medical Examinations'!D:D) -> No | K86: =PROPER('Medical Examinations'!H:H) -> Yes | N86: 52.9 | O86: =IF(N86<18.5,"Underweight", IF(N86<25,"Normal Weight", IF(N86<30,"Overweight", "Obesity"))) -> Obesity | Q86: 5.34 | R86: =IF(Q86<5.7,"Normal", IF(Q86<=6.4,"Prediabetes", "Diabetes")) -> Normal | T86: 2002 | U86: Dec | V86: 4 | W86: =DATE(T86,MONTH(1&U86),V86) -> 37594 | Y86: =DATEDIF(W86,DATE(2023,6,8),"Y") -> 20 | AA86: 1267
A87: Magee, Ms. Kate | B87: =TRIM(MID(A87,FIND(",",A87)+1,FIND(".",A87)-FIND(",",A87)-1)) -> Ms | C87: =LEFT(A87,FIND(",",A87)-1) -> Magee | D87: =RIGHT(A87,FIND(",",A87)-1) -> Kate | F87: 1 | G87: =IF(F87="No major surgery",0,F87) -> 1 | J87: =PROPER('Medical Examinations'!D:D) -> No | K87: =PROPER('Medical Examinations'!H:H) -> Yes | N87: 45.41 | O87: =IF(N87<18.5,"Underweight", IF(N87<25,"Normal Weight", IF(N87<30,"Overweight", "Obesity"))) -> Obesity | Q87: 4.03 | R87: =IF(Q87<5.7,"Normal", IF(Q87<=6.4,"Prediabetes", "Diabetes")) -> Normal | T87: 1997 | U87: Oct | V87: 26 | W87: =DATE(T87,MONTH(1&U87),V87) -> 35729 | Y87: =DATEDIF(W87,DATE(2023,6,8),"Y") -> 25 | AA87: 1276
A88: Thoma, Mr. Kevin | B88: =TRIM(MID(A88,FIND(",",A88)+1,FIND(".",A88)-FIND(",",A88)-1)) -> Mr | C88: =LEFT(A88,FIND(",",A88)-1) -> Thoma | D88: =RIGHT(A88,FIND(",",A88)-1) -> Kevin | F88: 1 | G88: =IF(F88="No major surgery",0,F88) -> 1 | J88: =PROPER('Medical Examinations'!D:D) -> No | K88: =PROPER('Medical Examinations'!H:H) -> Yes | N88: 49.41 | O88: =IF(N88<18.5,"Underweight", IF(N88<25,"Normal Weight", IF(N88<30,"Overweight", "Obesity"))) -> Obesity | Q88: 4.23 | R88: =IF(Q88<5.7,"Normal", IF(Q88<=6.4,"Prediabetes", "Diabetes")) -> Normal | T88: 2004 | U88: Sep | V88: 30 | W88: =DATE(T88,MONTH(1&U88),V88) -> 38260 | Y88: =DATEDIF(W88,DATE(2023,6,8),"Y") -> 18 | AA88: 1283
A89: Heagy, Mr. Stephen II | B89: =TRIM(MID(A89,FIND(",",A89)+1,FIND(".",A89)-FIND(",",A89)-1)) -> Mr | C89: =LEFT(A89,FIND(",",A89)-1) -> Heagy | D89: =RIGHT(A89,FIND(",",A89)-1) -> en II | F89: 2 | G89: =IF(F89="No major surgery",0,F89) -> 2 | J89: =PROPER('Medical Examinations'!D:D) -> No | K89: =PROPER('Medical Examinations'!H:H) -> Yes | N89: 31.825 | O89: =IF(N89<18.5,"Underweight", IF(N89<25,"Normal Weight", IF(N89<30,"Overweight", "Obesity"))) -> Obesity | Q89: 4.06 | R89: =IF(Q89<5.7,"Normal", IF(Q89<=6.4,"Prediabetes", "Diabetes")) -> Normal | T89: 2004 | U89: Jul | V89: 28 | W89: =DATE(T89,MONTH(1&U89),V89) -> 38196 | Y89: =DATEDIF(W89,DATE(2023,6,8),"Y") -> 18 | AA89: 1285
A90: Regnier, Mr. Philip | B90: =TRIM(MID(A90,FIND(",",A90)+1,FIND(".",A90)-FIND(",",A90)-1)) -> Mr | C90: =LEFT(A90,FIND(",",A90)-1) -> Regnier | D90: =RIGHT(A90,FIND(",",A90)-1) -> Philip | F90: 2 | G90: =IF(F90="No major surgery",0,F90) -> 2 | J90: =PROPER('Medical Examinations'!D:D) -> Yes | K90: =PROPER('Medical Examinations'!H:H) -> Yes | N90: 51.28 | O90: =IF(N90<18.5,"Underweight", IF(N90<25,"Normal Weight", IF(N90<30,"Overweight", "Obesity"))) -> Obesity | Q90: 4.68 | R90: =IF(Q90<5.7,"Normal", IF(Q90<=6.4,"Prediabetes", "Diabetes")) -> Normal | T90: 2000 | U90: Jun | V90: 26 | W90: =DATE(T90,MONTH(1&U90),V90) -> 36703 | Y90: =DATEDIF(W90,DATE(2023,6,8),"Y") -> 22 | AA90: 1286
A91: Parendo, Mr. Brett A | B91: =TRIM(MID(A91,FIND(",",A91)+1,FIND(".",A91)-FIND(",",A91)-1)) -> Mr | C91: =LEFT(A91,FIND(",",A91)-1) -> Parendo | D91: =RIGHT(A91,FIND(",",A91)-1) -> Brett A | F91: 1 | G91: =IF(F91="No major surgery",0,F91) -> 1 | J91: =PROPER('Medical Examinations'!D:D) -> No | K91: =PROPER('Medical Examinations'!H:H) -> Yes | N91: 34.96 | O91: =IF(N91<18.5,"Underweight", IF(N91<25,"Normal Weight", IF(N91<30,"Overweight", "Obesity"))) -> Obesity | Q91: 4.34 | R91: =IF(Q91<5.7,"Normal", IF(Q91<=6.4,"Prediabetes", "Diabetes")) -> Normal | T91: 1998 | U91: Jun | V91: 4 | W91: =DATE(T91,MONTH(1&U91),V91) -> 35950 | Y91: =DATEDIF(W91,DATE(2023,6,8),"Y") -> 25 | AA91: 1290.93
A92: Schell, Ms. Rebecca | B92: =TRIM(MID(A92,FIND(",",A92)+1,FIND(".",A92)-FIND(",",A92)-1)) -> Ms | C92: =LEFT(A92,FIND(",",A92)-1) -> Schell | D92: =RIGHT(A92,FIND(",",A92)-1) -> ebecca | F92: No major surgery | G92: =IF(F92="No major surgery",0,F92) -> 0 | J92: =PROPER('Medical Examinations'!D:D) -> No | K92: =PROPER('Medical Examinations'!H:H) -> Yes | N92: 33.11 | O92: =IF(N92<18.5,"Underweight", IF(N92<25,"Normal Weight", IF(N92<30,"Overweight", "Obesity"))) -> Obesity | Q92: 10.51 | R92: =IF(Q92<5.7,"Normal", IF(Q92<=6.4,"Prediabetes", "Diabetes")) -> Diabetes | T92: 2001 | U92: Nov | V92: 29 | W92: =DATE(T92,MONTH(1&U92),V92) -> 37224 | Y92: =DATEDIF(W92,DATE(2023,6,8),"Y") -> 21 | AA92: 1293
A93: Driscoll, Ms. Kelley | B93: =TRIM(MID(A93,FIND(",",A93)+1,FIND(".",A93)-FIND(",",A93)-1)) -> Ms | C93: =LEFT(A93,FIND(",",A93)-1) -> Driscoll | D93: =RIGHT(A93,FIND(",",A93)-1) -> Kelley | F93: 1 | G93: =IF(F93="No major surgery",0,F93) -> 1 | J93: =PROPER('Medical Examinations'!D:D) -> No | K93: =PROPER('Medical Examinations'!H:H) -> Yes | N93: 54.74 | O93: =IF(N93<18.5,"Underweight", IF(N93<25,"Normal Weight", IF(N93<30,"Overweight", "Obesity"))) -> Obesity | Q93: 5.84 | R93: =IF(Q93<5.7,"Normal", IF(Q93<=6.4,"Prediabetes", "Diabetes")) -> Prediabetes | T93: 2002 | U93: Dec | V93: 10 | W93: =DATE(T93,MONTH(1&U93),V93) -> 37600 | Y93: =DATEDIF(W93,DATE(2023,6,8),"Y") -> 20 | AA93: 1304
A94: Mitchell, Ms. Abigail K | B94: =TRIM(MID(A94,FIND(",",A94)+1,FIND(".",A94)-FIND(",",A94)-1)) -> Ms | C94: =LEFT(A94,FIND(",",A94)-1) -> Mitchell | D94: =RIGHT(A94,FIND(",",A94)-1) -> bigail K | F94: 1 | G94: =IF(F94="No major surgery",0,F94) -> 1 | J94: =PROPER('Medical Examinations'!D:D) -> No | K94: =PROPER('Medical Examinations'!H:H) -> Yes | N94: 32.56 | O94: =IF(N94<18.5,"Underweight", IF(N94<25,"Normal Weight", IF(N94<30,"Overweight", "Obesity"))) -> Obesity | Q94: 5.41 | R94: =IF(Q94<5.7,"Normal", IF(Q94<=6.4,"Prediabetes", "Diabetes")) -> Normal | T94: 1999 | U94: Dec | V94: 2 | W94: =DATE(T94,MONTH(1&U94),V94) -> 36496 | Y94: =DATEDIF(W94,DATE(2023,6,8),"Y") -> 23 | AA94: 1304
A95: Cutler, Ms. Hope | B95: =TRIM(MID(A95,FIND(",",A95)+1,FIND(".",A95)-FIND(",",A95)-1)) -> Ms | C95: =LEFT(A95,FIND(",",A95)-1) -> Cutler | D95: =RIGHT(A95,FIND(",",A95)-1) -> Hope | F95: 1 | G95: =IF(F95="No major surgery",0,F95) -> 1 | J95: =PROPER('Medical Examinations'!D:D) -> Yes | K95: =PROPER('Medical Examinations'!H:H) -> Yes | N95: 39.05 | O95: =IF(N95<18.5,"Underweight", IF(N95<25,"Normal Weight", IF(N95<30,"Overweight", "Obesity"))) -> Obesity | Q95: 6.06 | R95: =IF(Q95<5.7,"Normal", IF(Q95<=6.4,"Prediabetes", "Diabetes")) -> Prediabetes | T95: 2002 | U95: Oct | V95: 13 | W95: =DATE(T95,MONTH(1&U95),V95) -> 37542 | Y95: =DATEDIF(W95,DATE(2023,6,8),"Y") -> 20 | AA95: 1315
A96: Derian, Ms. Elyse M. | B96: =TRIM(MID(A96,FIND(",",A96)+1,FIND(".",A96)-FIND(",",A96)-1)) -> Ms | C96: =LEFT(A96,FIND(",",A96)-1) -> Derian | D96: =RIGHT(A96,FIND(",",A96)-1) -> yse M. | F96: No major surgery | G96: =IF(F96="No major surgery",0,F96) -> 0 | J96: =PROPER('Medical Examinations'!D:D) -> Yes | K96: =PROPER('Medical Examinations'!H:H) -> Yes | N96: 42.75 | O96: =IF(N96<18.5,"Underweight", IF(N96<25,"Normal Weight", IF(N96<30,"Overweight", "Obesity"))) -> Obesity | Q96: 4.22 | R96: =IF(Q96<5.7,"Normal", IF(Q96<=6.4,"Prediabetes", "Diabetes")) -> Normal | T96: 1999 | U96: Oct | V96: 14 | W96: =DATE(T96,MONTH(1&U96),V96) -> 36447 | Y96: =DATEDIF(W96,DATE(2023,6,8),"Y") -> 23 | AA96: 1329.17
A97: Farina, Mr. Nicholas | B97: =TRIM(MID(A97,FIND(",",A97)+1,FIND(".",A97)-FIND(",",A97)-1)) -> Mr | C97: =LEFT(A97,FIND(",",A97)-1) -> Farina | D97: =RIGHT(A97,FIND(",",A97)-1) -> cholas | F97: 2 | G97: =IF(F97="No major surgery",0,F97) -> 2 | J97: =PROPER('Medical Examinations'!D:D) -> Yes | K97: =PROPER('Medical Examinations'!H:H) -> Yes | N97: 50.58 | O97: =IF(N97<18.5,"Underweight", IF(N97<25,"Normal Weight", IF(N97<30,"Overweight", "Obesity"))) -> Obesity | Q97: 5.12 | R97: =IF(Q97<5.7,"Normal", IF(Q97<=6.4,"Prediabetes", "Diabetes")) -> Normal | T97: 1998 | U97: Jul | V97: 12 | W97: =DATE(T97,MONTH(1&U97),V97) -> 35988 | Y97: =DATEDIF(W97,DATE(2023,6,8),"Y") -> 24 | AA97: 1332.61
A98: Saunders, Mr. David | B98: =TRIM(MID(A98,FIND(",",A98)+1,FIND(".",A98)-FIND(",",A98)-1)) -> Mr | C98: =LEFT(A98,FIND(",",A98)-1) -> Saunders | D98: =RIGHT(A98,FIND(",",A98)-1) -> . David | F98: No major surgery | G98: =IF(F98="No major surgery",0,F98) -> 0 | J98: =PROPER('Medical Examinations'!D:D) -> Yes | K98: =PROPER('Medical Examinations'!H:H) -> Yes | N98: 30.495 | O98: =IF(N98<18.5,"Underweight", IF(N98<25,"Normal Weight", IF(N98<30,"Overweight", "Obesity"))) -> Obesity | Q98: 4.57 | R98: =IF(Q98<5.7,"Normal", IF(Q98<=6.4,"Prediabetes", "Diabetes")) -> Normal | T98: 1995 | U98: Jul | V98: 30 | W98: =DATE(T98,MONTH(1&U98),V98) -> 34910 | Y98: =DATEDIF(W98,DATE(2023,6,8),"Y") -> 27 | AA98: 1338
A99: Kratz, Ms. Natalie | B99: =TRIM(MID(A99,FIND(",",A99)+1,FIND(".",A99)-FIND(",",A99)-1)) -> Ms | C99: =LEFT(A99,FIND(",",A99)-1) -> Kratz | D99: =RIGHT(A99,FIND(",",A99)-1) -> talie | F99: 2 | G99: =IF(F99="No major surgery",0,F99) -> 2 | J99: =PROPER('Medical Examinations'!D:D) -> Yes | K99: =PROPER('Medical Examinations'!H:H) -> Yes | N99: 48.31 | O99: =IF(N99<18.5,"Underweight", IF(N99<25,"Normal Weight", IF(N99<30,"Overweight", "Obesity"))) -> Obesity | Q99: 9.58 | R99: =IF(Q99<5.7,"Normal", IF(Q99<=6.4,"Prediabetes", "Diabetes")) -> Diabetes | T99: 1997 | U99: Nov | V99: 7 | W99: =DATE(T99,MONTH(1&U99),V99) -> 35741 | Y99: =DATEDIF(W99,DATE(2023,6,8),"Y") -> 25 | AA99: 1341.16
A100: Boland, Mr. Thomas | B100: =TRIM(MID(A100,FIND(",",A100)+1,FIND(".",A100)-FIND(",",A100)-1)) -> Mr | C100: =LEFT(A100,FIND(",",A100)-1) -> Boland | D100: =RIGHT(A100,FIND(",",A100)-1) -> Thomas | F100: 1 | G100: =IF(F100="No major surgery",0,F100) -> 1 | J100: =PROPER('Medical Examinations'!D:D) -> No | K100: =PROPER('Medical Examinations'!H:H) -> Yes | N100: 48.99 | O100: =IF(N100<18.5,"Underweight", IF(N100<25,"Normal Weight", IF(N100<30,"Overweight", "Obesity"))) -> Obesity | Q100: 9.78 | R100: =IF(Q100<5.7,"Normal", IF(Q100<=6.4,"Prediabetes", "Diabetes")) -> Diabetes | T100: 1998 | U100: Dec | V100: 3 | W100: =DATE(T100,MONTH(1&U100),V100) -> 36132 | Y100: =DATEDIF(W100,DATE(2023,6,8),"Y") -> 24 | AA100: 1359
A101: Van Hout, Ms. Pamela J. | B101: =TRIM(MID(A101,FIND(",",A101)+1,FIND(".",A101)-FIND(",",A101)-1)) -> Ms | C101: =LEFT(A101,FIND(",",A101)-1) -> Van Hout | D101: =RIGHT(A101,FIND(",",A101)-1) -> amela J. | F101: No major surgery | G101: =IF(F101="No major surgery",0,F101) -> 0 | J101: =PROPER('Medical Examinations'!D:D) -> No | K101: =PROPER('Medical Examinations'!H:H) -> Yes | N101: 38.39 | O101: =IF(N101<18.5,"Underweight", IF(N101<25,"Normal Weight", IF(N101<30,"Overweight", "Obesity"))) -> Obesity | Q101: 4.11 | R101: =IF(Q101<5.7,"Normal", IF(Q101<=6.4,"Prediabetes", "Diabetes")) -> Normal | T101: 2002 | U101: Aug | V101: 15 | W101: =DATE(T101,MONTH(1&U101),V101) -> 37483 | Y101: =DATEDIF(W101,DATE(2023,6,8),"Y") -> 20 | AA101: 1382
...

Sheet Healthcare
A1: Customer ID | B1: Name | C1: BMI | D1: HBA1C | E1: Heart Issues | F1: Any Transplants | G1: Cancer history | H1: NumberOfMajorSurgeries | I1: smoker | J1: year | K1: month | L1: date | M1: children | N1: charges | O1: Hospital tier | P1: City tier | Q1: State ID
A2: Id1 | B2: =VLOOKUP(A2,'Customer Names'!A:B,2,0) -> Hawks, Ms. Kelly | C2: =VLOOKUP(A2,'Medical Examinations'!A:H,2,0) -> 47.41 | D2: =VLOOKUP(A2,'Medical Examinations'!A:C,3,0) -> 7.47 | E2: =VLOOKUP(A2,'Medical Examinations'!A:E,4) -> No | F2: =VLOOKUP(A2,'Medical Examinations'!A:E,5) -> No | G2: =VLOOKUP(A2,'Medical Examinations'!A:F,6,0) -> No | H2: =VLOOKUP(A2,'Medical Examinations'!A:G,7) -> No major surgery | I2: =VLOOKUP(A2,'Medical Examinations'!A:H,8,0) -> yes | J2: =VLOOKUP(A2,'Hospitalisation Details'!A:B,2,0) -> 1968 | K2: =VLOOKUP(A2,'Hospitalisation Details'!A:C,3,0) -> Oct | L2: =VLOOKUP(A2,'Hospitalisation Details'!A:D,4,0) -> 12 | M2: =VLOOKUP(A2,'Hospitalisation Details'!A:E,5,0) -> 0 | N2: =VLOOKUP(A2,'Hospitalisation Details'!A:F,6,0) -> 63770.43 | O2: =VLOOKUP(A2,'Hospitalisation Details'!A:G,7,0) -> tier - 1 | P2: =VLOOKUP(A2,'Hospitalisation Details'!A:I,8,0) -> tier - 3 | Q2: =VLOOKUP(A2,'Hospitalisation Details'!A:I,9,0) -> R1013
A3: Id2 | B3: =VLOOKUP(A3,'Customer Names'!A:B,2,0) -> Lehner, Mr. Matthew D | C3: =VLOOKUP(A3,'Medical Examinations'!A:H,2,0) -> 30.36 | D3: =VLOOKUP(A3,'Medical Examinations'!A:C,3,0) -> 5.77 | E3: =VLOOKUP(A3,'Medical Examinations'!A:E,4) -> yes | F3: =VLOOKUP(A3,'Medical Examinations'!A:E,5) -> No | G3: =VLOOKUP(A3,'Medical Examinations'!A:F,6,0) -> No | H3: =VLOOKUP(A3,'Medical Examinations'!A:G,7) -> No major surgery | I3: =VLOOKUP(A3,'Medical Examinations'!A:H,8,0) -> yes | J3: =VLOOKUP(A3,'Hospitalisation Details'!A:B,2,0) -> 1977 | K3: =VLOOKUP(A3,'Hospitalisation Details'!A:C,3,0) -> Jun | L3: =VLOOKUP(A3,'Hospitalisation Details'!A:D,4,0) -> 8 | M3: =VLOOKUP(A3,'Hospitalisation Details'!A:E,5,0) -> 0 | N3: =VLOOKUP(A3,'Hospitalisation Details'!A:F,6,0) -> 62592.87 | O3: =VLOOKUP(A3,'Hospitalisation Details'!A:G,7,0) -> tier - 2 | P3: =VLOOKUP(A3,'Hospitalisation Details'!A:I,8,0) -> tier - 3 | Q3: =VLOOKUP(A3,'Hospitalisation Details'!A:I,9,0) -> R1013
A4: Id3 | B4: =VLOOKUP(A4,'Customer Names'!A:B,2,0) -> Lu, Mr. Phil | C4: =VLOOKUP(A4,'Medical Examinations'!A:H,2,0) -> 34.485 | D4: =VLOOKUP(A4,'Medical Examinations'!A:C,3,0) -> 11.87 | E4: =VLOOKUP(A4,'Medical Examinations'!A:E,4) -> No | F4: =VLOOKUP(A4,'Medical Examinations'!A:E,5) -> No | G4: =VLOOKUP(A4,'Medical Examinations'!A:F,6,0) -> No | H4: =VLOOKUP(A4,'Medical Examinations'!A:G,7) -> 1 | I4: =VLOOKUP(A4,'Medical Examinations'!A:H,8,0) -> yes | J4: =VLOOKUP(A4,'Hospitalisation Details'!A:B,2,0) -> 1970 | K4: Sep | L4: =VLOOKUP(A4,'Hospitalisation Details'!A:D,4,0) -> 11 | M4: =VLOOKUP(A4,'Hospitalisation Details'!A:E,5,0) -> 3 | N4: =VLOOKUP(A4,'Hospitalisation Details'!A:F,6,0) -> 60021.4 | O4: =VLOOKUP(A4,'Hospitalisation Details'!A:G,7,0) -> tier - 1 | P4: =VLOOKUP(A4,'Hospitalisation Details'!A:I,8,0) -> tier - 1 | Q4: =VLOOKUP(A4,'Hospitalisation Details'!A:I,9,0) -> R1012
A5: Id4 | B5: =VLOOKUP(A5,'Customer Names'!A:B,2,0) -> Osborne, Ms. Kelsey | C5: =VLOOKUP(A5,'Medical Examinations'!A:H,2,0) -> 38.095 | D5: =VLOOKUP(A5,'Medical Examinations'!A:C,3,0) -> 6.05 | E5: =VLOOKUP(A5,'Medical Examinations'!A:E,4) -> No | F5: =VLOOKUP(A5,'Medical Examinations'!A:E,5) -> No | G5: =VLOOKUP(A5,'Medical Examinations'!A:F,6,0) -> No | H5: =VLOOKUP(A5,'Medical Examinations'!A:G,7) -> 1 | I5: =VLOOKUP(A5,'Medical Examinations'!A:H,8,0) -> yes | J5: =VLOOKUP(A5,'Hospitalisation Details'!A:B,2,0) -> 1991 | K5: =VLOOKUP(A5,'Hospitalisation Details'!A:C,3,0) -> Jun | L5: =VLOOKUP(A5,'Hospitalisation Details'!A:D,4,0) -> 6 | M5: =VLOOKUP(A5,'Hospitalisation Details'!A:E,5,0) -> 1 | N5: =VLOOKUP(A5,'Hospitalisation Details'!A:F,6,0) -> 58571.07 | O5: =VLOOKUP(A5,'Hospitalisation Details'!A:G,7,0) -> tier - 1 | P5: =VLOOKUP(A5,'Hospitalisation Details'!A:I,8,0) -> tier - 3 | Q5: =VLOOKUP(A5,'Hospitalisation Details'!A:I,9,0) -> R1024
A6: Id5 | B6: =VLOOKUP(A6,'Customer Names'!A:B,2,0) -> Kadala, Ms. Kristyn | C6: =VLOOKUP(A6,'Medical Examinations'!A:H,2,0) -> 35.53 | D6: =VLOOKUP(A6,'Medical Examinations'!A:C,3,0) -> 5.45 | E6: =VLOOKUP(A6,'Medical Examinations'!A:E,4) -> No | F6: =VLOOKUP(A6,'Medical Examinations'!A:E,5) -> No | G6: =VLOOKUP(A6,'Medical Examinations'!A:F,6,0) -> No | H6: =VLOOKUP(A6,'Medical Examinations'!A:G,7) -> 1 | I6: =VLOOKUP(A6,'Medical Examinations'!A:H,8,0) -> yes | J6: =VLOOKUP(A6,'Hospitalisation Details'!A:B,2,0) -> 1989 | K6: =VLOOKUP(A6,'Hospitalisation Details'!A:C,3,0) -> Jun | L6: =VLOOKUP(A6,'Hospitalisation Details'!A:D,4,0) -> 19 | M6: =VLOOKUP(A6,'Hospitalisation Details'!A:E,5,0) -> 0 | N6: =VLOOKUP(A6,'Hospitalisation Details'!A:F,6,0) -> 55135.4 | O6: =VLOOKUP(A6,'Hospitalisation Details'!A:G,7,0) -> tier - 1 | P6: =VLOOKUP(A6,'Hospitalisation Details'!A:I,8,0) -> tier - 2 | Q6: =VLOOKUP(A6,'Hospitalisation Details'!A:I,9,0) -> R1012
A7: Id6 | B7: =VLOOKUP(A7,'Customer Names'!A:B,2,0) -> Baker, Mr. Russell B. | C7: =VLOOKUP(A7,'Medical Examinations'!A:H,2,0) -> 32.8 | D7: =VLOOKUP(A7,'Medical Examinations'!A:C,3,0) -> 6.59 | E7: =VLOOKUP(A7,'Medical Examinations'!A:E,4) -> No | F7: =VLOOKUP(A7,'Medical Examinations'!A:E,5) -> No | G7: =VLOOKUP(A7,'Medical Examinations'!A:F,6,0) -> No | H7: =VLOOKUP(A7,'Medical Examinations'!A:G,7) -> 1 | I7: =VLOOKUP(A7,'Medical Examinations'!A:H,8,0) -> yes | J7: =VLOOKUP(A7,'Hospitalisation Details'!A:B,2,0) -> 1962 | K7: =VLOOKUP(A7,'Hospitalisation Details'!A:C,3,0) -> Aug | L7: =VLOOKUP(A7,'Hospitalisation Details'!A:D,4,0) -> 4 | M7: =VLOOKUP(A7,'Hospitalisation Details'!A:E,5,0) -> 0 | N7: =VLOOKUP(A7,'Hospitalisation Details'!A:F,6,0) -> 52590.83 | O7: =VLOOKUP(A7,'Hospitalisation Details'!A:G,7,0) -> tier - 1 | P7: =VLOOKUP(A7,'Hospitalisation Details'!A:I,8,0) -> tier - 3 | Q7: =VLOOKUP(A7,'Hospitalisation Details'!A:I,9,0) -> R1011
A8: Id7 | B8: =VLOOKUP(A8,'Customer Names'!A:B,2,0) -> Macpherson, Mr. Scott | C8: =VLOOKUP(A8,'Medical Examinations'!A:H,2,0) -> 36.4 | D8: =VLOOKUP(A8,'Medical Examinations'!A:C,3,0) -> 6.07 | E8: =VLOOKUP(A8,'Medical Examinations'!A:E,4) -> No | F8: =VLOOKUP(A8,'Medical Examinations'!A:E,5) -> No | G8: =VLOOKUP(A8,'Medical Examinations'!A:F,6,0) -> No | H8: =VLOOKUP(A8,'Medical Examinations'!A:G,7) -> 1 | I8: =VLOOKUP(A8,'Medical Examinations'!A:H,8,0) -> yes | J8: =VLOOKUP(A8,'Hospitalisation Details'!A:B,2,0) -> 1994 | K8: =VLOOKUP(A8,'Hospitalisation Details'!A:C,3,0) -> Oct | L8: =VLOOKUP(A8,'Hospitalisation Details'!A:D,4,0) -> 27 | M8: =VLOOKUP(A8,'Hospitalisation Details'!A:E,5,0) -> 1 | N8: =VLOOKUP(A8,'Hospitalisation Details'!A:F,6,0) -> 51194.56 | O8: =VLOOKUP(A8,'Hospitalisation Details'!A:G,7,0) -> tier - 1 | P8: =VLOOKUP(A8,'Hospitalisation Details'!A:I,8,0) -> tier - 3 | Q8: =VLOOKUP(A8,'Hospitalisation Details'!A:I,9,0) -> R1011
A9: Id8 | B9: =VLOOKUP(A9,'Customer Names'!A:B,2,0) -> Hallman, Mr. Stephen | C9: =VLOOKUP(A9,'Medical Examinations'!A:H,2,0) -> 36.96 | D9: =VLOOKUP(A9,'Medical Examinations'!A:C,3,0) -> 7.93 | E9: =VLOOKUP(A9,'Medical Examinations'!A:E,4) -> No | F9: =VLOOKUP(A9,'Medical Examinations'!A:E,5) -> No | G9: =VLOOKUP(A9,'Medical Examinations'!A:F,6,0) -> No | H9: =VLOOKUP(A9,'Medical Examinations'!A:G,7) -> 1 | I9: =VLOOKUP(A9,'Medical Examinations'!A:H,8,0) -> yes | J9: =VLOOKUP(A9,'Hospitalisation Details'!A:B,2,0) -> 1958 | K9: =VLOOKUP(A9,'Hospitalisation Details'!A:C,3,0) -> Jun | L9: =VLOOKUP(A9,'Hospitalisation Details'!A:D,4,0) -> 27 | M9: =VLOOKUP(A9,'Hospitalisation Details'!A:E,5,0) -> 2 | N9: =VLOOKUP(A9,'Hospitalisation Details'!A:F,6,0) -> 49577.66 | O9: =VLOOKUP(A9,'Hospitalisation Details'!A:G,7,0) -> tier - 2 | P9: =VLOOKUP(A9,'Hospitalisation Details'!A:I,8,0) -> tier - 2 | Q9: =VLOOKUP(A9,'Hospitalisation Details'!A:I,9,0) -> R1013
A10: Id9 | B10: =VLOOKUP(A10,'Customer Names'!A:B,2,0) -> Moran, Mr. Patrick R. | C10: =VLOOKUP(A10,'Medical Examinations'!A:H,2,0) -> 41.14 | D10: =VLOOKUP(A10,'Medical Examinations'!A:C,3,0) -> 9.58 | E10: =VLOOKUP(A10,'Medical Examinations'!A:E,4) -> No | F10: =VLOOKUP(A10,'Medical Examinations'!A:E,5) -> No | G10: =VLOOKUP(A10,'Medical Examinations'!A:F,6,0) -> Yes | H10: =VLOOKUP(A10,'Medical Examinations'!A:G,7) -> 1 | I10: =VLOOKUP(A10,'Medical Examinations'!A:H,8,0) -> yes | J10: =VLOOKUP(A10,'Hospitalisation Details'!A:B,2,0) -> 1963 | K10: =VLOOKUP(A10,'Hospitalisation Details'!A:C,3,0) -> Sep | L10: =VLOOKUP(A10,'Hospitalisation Details'!A:D,4,0) -> 4 | M10: =VLOOKUP(A10,'Hospitalisation Details'!A:E,5,0) -> 1 | N10: =VLOOKUP(A10,'Hospitalisation Details'!A:F,6,0) -> 48970.25 | O10: =VLOOKUP(A10,'Hospitalisation Details'!A:G,7,0) -> tier - 1 | P10: =VLOOKUP(A10,'Hospitalisation Details'!A:I,8,0) -> tier - 2 | Q10: =VLOOKUP(A10,'Hospitalisation Details'!A:I,9,0) -> R1013
A11: Id10 | B11: =VLOOKUP(A11,'Customer Names'!A:B,2,0) -> Benner, Ms. Brooke N. | C11: =VLOOKUP(A11,'Medical Examinations'!A:H,2,0) -> 38.06 | D11: =VLOOKUP(A11,'Medical Examinations'!A:C,3,0) -> 10.79 | E11: =VLOOKUP(A11,'Medical Examinations'!A:E,4) -> No | F11: =VLOOKUP(A11,'Medical Examinations'!A:E,5) -> No | G11: =VLOOKUP(A11,'Medical Examinations'!A:F,6,0) -> No | H11: =VLOOKUP(A11,'Medical Examinations'!A:G,7) -> No major surgery | I11: =VLOOKUP(A11,'Medical Examinations'!A:H,8,0) -> yes | J11: =VLOOKUP(A11,'Hospitalisation Details'!A:B,2,0) -> 1978 | K11: =VLOOKUP(A11,'Hospitalisation Details'!A:C,3,0) -> Dec | L11: =VLOOKUP(A11,'Hospitalisation Details'!A:D,4,0) -> 29 | M11: =VLOOKUP(A11,'Hospitalisation Details'!A:E,5,0) -> 0 | N11: =VLOOKUP(A11,'Hospitalisation Details'!A:F,6,0) -> 48885.14 | O11: =VLOOKUP(A11,'Hospitalisation Details'!A:G,7,0) -> tier - 1 | P11: =VLOOKUP(A11,'Hospitalisation Details'!A:I,8,0) -> tier - 2 | Q11: =VLOOKUP(A11,'Hospitalisation Details'!A:I,9,0) -> R1013
A12: Id11 | B12: =VLOOKUP(A12,'Customer Names'!A:B,2,0) -> Fierro Vargas, Ms. Paola Andrea | C12: =VLOOKUP(A12,'Medical Examinations'!A:H,2,0) -> 37.7 | D12: =VLOOKUP(A12,'Medical Examinations'!A:C,3,0) -> 5.96 | E12: =VLOOKUP(A12,'Medical Examinations'!A:E,4) -> yes | F12: =VLOOKUP(A12,'Medical Examinations'!A:E,5) -> No | G12: =VLOOKUP(A12,'Medical Examinations'!A:F,6,0) -> No | H12: =VLOOKUP(A12,'Medical Examinations'!A:G,7) -> 1 | I12: =VLOOKUP(A12,'Medical Examinations'!A:H,8,0) -> yes | J12: =VLOOKUP(A12,'Hospitalisation Details'!A:B,2,0) -> 1959 | K12: =VLOOKUP(A12,'Hospitalisation Details'!A:C,3,0) -> Jul | L12: =VLOOKUP(A12,'Hospitalisation Details'!A:D,4,0) -> 22 | M12: =VLOOKUP(A12,'Hospitalisation Details'!A:E,5,0) -> 0 | N12: =VLOOKUP(A12,'Hospitalisation Details'!A:F,6,0) -> 48824.45 | O12: =VLOOKUP(A12,'Hospitalisation Details'!A:G,7,0) -> tier - 2 | P12: =VLOOKUP(A12,'Hospitalisation Details'!A:I,8,0) -> tier - 1 | Q12: =VLOOKUP(A12,'Hospitalisation Details'!A:I,9,0) -> R1011
A13: Id12 | B13: =VLOOKUP(A13,'Customer Names'!A:B,2,0) -> Franz, Mr. David | C13: =VLOOKUP(A13,'Medical Examinations'!A:H,2,0) -> 42.13 | D13: =VLOOKUP(A13,'Medical Examinations'!A:C,3,0) -> 11.9 | E13: =VLOOKUP(A13,'Medical Examinations'!A:E,4) -> No | F13: =VLOOKUP(A13,'Medical Examinations'!A:E,5) -> No | G13: =VLOOKUP(A13,'Medical Examinations'!A:F,6,0) -> No | H13: =VLOOKUP(A13,'Medical Examinations'!A:G,7) -> No major surgery | I13: =VLOOKUP(A13,'Medical Examinations'!A:H,8,0) -> yes | J13: =VLOOKUP(A13,'Hospitalisation Details'!A:B,2,0) -> 1965 | K13: =VLOOKUP(A13,'Hospitalisation Details'!A:C,3,0) -> Oct | L13: =VLOOKUP(A13,'Hospitalisation Details'!A:D,4,0) -> 27 | M13: =VLOOKUP(A13,'Hospitalisation Details'!A:E,5,0) -> 1 | N13: =VLOOKUP(A13,'Hospitalisation Details'!A:F,6,0) -> 48675.52 | O13: =VLOOKUP(A13,'Hospitalisation Details'!A:G,7,0) -> tier - 1 | P13: =VLOOKUP(A13,'Hospitalisation Details'!A:I,8,0) -> tier - 2 | Q13: =VLOOKUP(A13,'Hospitalisation Details'!A:I,9,0) -> R1013
A14: Id13 | B14: =VLOOKUP(A14,'Customer Names'!A:B,2,0) -> Foster, Mr. Wade | C14: =VLOOKUP(A14,'Medical Examinations'!A:H,2,0) -> 40.92 | D14: =VLOOKUP(A14,'Medical Examinations'!A:C,3,0) -> 8.41 | E14: =VLOOKUP(A14,'Medical Examinations'!A:E,4) -> yes | F14: =VLOOKUP(A14,'Medical Examinations'!A:E,5) -> No | G14: =VLOOKUP(A14,'Medical Examinations'!A:F,6,0) -> No | H14: =VLOOKUP(A14,'Medical Examinations'!A:G,7) -> 2 | I14: =VLOOKUP(A14,'Medical Examinations'!A:H,8,0) -> yes | J14: =VLOOKUP(A14,'Hospitalisation Details'!A:B,2,0) -> 1962 | K14: =VLOOKUP(A14,'Hospitalisation Details'!A:C,3,0) -> Oct | L14: =VLOOKUP(A14,'Hospitalisation Details'!A:D,4,0) -> 11 | M14: =VLOOKUP(A14,'Hospitalisation Details'!A:E,5,0) -> 0 | N14: =VLOOKUP(A14,'Hospitalisation Details'!A:F,6,0) -> 48673.56 | O14: =VLOOKUP(A14,'Hospitalisation Details'!A:G,7,0) -> tier - 1 | P14: =VLOOKUP(A14,'Hospitalisation Details'!A:I,8,0) -> tier - 2 | Q14: =VLOOKUP(A14,'Hospitalisation Details'!A:I,9,0) -> R1013
A15: Id14 | B15: =VLOOKUP(A15,'Customer Names'!A:B,2,0) -> Tenorio, Mr. Franklin | C15: =VLOOKUP(A15,'Medical Examinations'!A:H,2,0) -> 40.565 | D15: =VLOOKUP(A15,'Medical Examinations'!A:C,3,0) -> 7.02 | E15: =VLOOKUP(A15,'Medical Examinations'!A:E,4) -> No | F15: =VLOOKUP(A15,'Medical Examinations'!A:E,5) -> No | G15: =VLOOKUP(A15,'Medical Examinations'!A:F,6,0) -> No | H15: =VLOOKUP(A15,'Medical Examinations'!A:G,7) -> No major surgery | I15: =VLOOKUP(A15,'Medical Examinations'!A:H,8,0) -> yes | J15: =VLOOKUP(A15,'Hospitalisation Details'!A:B,2,0) -> 1968 | K15: =VLOOKUP(A15,'Hospitalisation Details'!A:C,3,0) -> Dec | L15: =VLOOKUP(A15,'Hospitalisation Details'!A:D,4,0) -> 1 | M15: =VLOOKUP(A15,'Hospitalisation Details'!A:E,5,0) -> 3 | N15: =VLOOKUP(A15,'Hospitalisation Details'!A:F,6,0) -> 48549.18 | O15: =VLOOKUP(A15,'Hospitalisation Details'!A:G,7,0) -> tier - 1 | P15: =VLOOKUP(A15,'Hospitalisation Details'!A:I,8,0) -> tier - 3 | Q15: =VLOOKUP(A15,'Hospitalisation Details'!A:I,9,0) -> R1016
A16: Id15 | B16: =VLOOKUP(A16,'Customer Names'!A:B,2,0) -> Rios, Ms. Leilani M. | C16: =VLOOKUP(A16,'Medical Examinations'!A:H,2,0) -> 36.385 | D16: =VLOOKUP(A16,'Medical Examinations'!A:C,3,0) -> 7.59 | E16: =VLOOKUP(A16,'Medical Examinations'!A:E,4) -> No | F16: =VLOOKUP(A16,'Medical Examinations'!A:E,5) -> No | G16: =VLOOKUP(A16,'Medical Examinations'!A:F,6,0) -> No | H16: =VLOOKUP(A16,'Medical Examinations'!A:G,7) -> No major surgery | I16: =VLOOKUP(A16,'Medical Examinations'!A:H,8,0) -> yes | J16: =VLOOKUP(A16,'Hospitalisation Details'!A:B,2,0) -> 1961 | K16: =VLOOKUP(A16,'Hospitalisation Details'!A:C,3,0) -> Dec | L16: =VLOOKUP(A16,'Hospitalisation Details'!A:D,4,0) -> 21 | M16: =VLOOKUP(A16,'Hospitalisation Details'!A:E,5,0) -> 1 | N16: =VLOOKUP(A16,'Hospitalisation Details'!A:F,6,0) -> 48517.56 | O16: =VLOOKUP(A16,'Hospitalisation Details'!A:G,7,0) -> tier - 1 | P16: =VLOOKUP(A16,'Hospitalisation Details'!A:I,8,0) -> tier - 3 | Q16: =VLOOKUP(A16,'Hospitalisation Details'!A:I,9,0) -> R1024
... A2318: Id2317 | B2318: =VLOOKUP(A2318,'Customer Names'!A:B,2,0) -> Murakami, Mr. Koji | C2318: =VLOOKUP(A2318,'Medical Examinations'!A:H,2,0) -> 20.47 | D2318: =VLOOKUP(A2318,'Medical Examinations'!A:C,3,0) -> 5.81 | E2318: =VLOOKUP(A2318,'Medical Examinations'!A:E,4) -> yes | F2318: =VLOOKUP(A2318,'Medical Examinations'!A:E,5) -> No | G2318: =VLOOKUP(A2318,'Medical Examinations'!A:F,6,0) -> No | H2318: =VLOOKUP(A2318,'Medical Examinations'!A:G,7) -> 1 | I2318: =VLOOKUP(A2318,'Medical Examinations'!A:H,8,0) -> No | J2318: =VLOOKUP(A2318,'Hospitalisation Details'!A:B,2,0) -> 1995 | K2318: =VLOOKUP(A2318,'Hospitalisation Details'!A:C,3,0) -> Dec | L2318: =VLOOKUP(A2318,'Hospitalisation Details'!A:D,4,0) -> 7 | M2318: =VLOOKUP(A2318,'Hospitalisation Details'!A:E,5,0) -> 0 | N2318: =VLOOKUP(A2318,'Hospitalisation Details'!A:F,6,0) -> 773.54 | O2318: =VLOOKUP(A2318,'Hospitalisation Details'!A:G,7,0) -> tier - 3 | P2318: =VLOOKUP(A2318,'Hospitalisation Details'!A:I,8,0) -> tier - 2 | Q2318: =VLOOKUP(A2318,'Hospitalisation Details'!A:I,9,0) -> R1013
A2319: Id2318 | B2319: =VLOOKUP(A2319,'Customer Names'!A:B,2,0) -> Gagnon, Ms. Candice M | C2319: =VLOOKUP(A2319,'Medical Examinations'!A:H,2,0) -> 18.82 | D2319: =VLOOKUP(A2319,'Medical Examinations'!A:C,3,0) -> 5.51 | E2319: =VLOOKUP(A2319,'Medical Examinations'!A:E,4) -> yes | F2319: =VLOOKUP(A2319,'Medical Examinations'!A:E,5) -> No | G2319: =VLOOKUP(A2319,'Medical Examinations'!A:F,6,0) -> No | H2319: =VLOOKUP(A2319,'Medical Examinations'!A:G,7) -> No major surgery | I2319: =VLOOKUP(A2319,'Medical Examinations'!A:H,8,0) -> No | J2319: =VLOOKUP(A2319,'Hospitalisation Details'!A:B,2,0) -> 1996 | K2319: Sep | L2319: =VLOOKUP(A2319,'Hospitalisation Details'!A:D,4,0) -> 18 | M2319: =VLOOKUP(A2319,'Hospitalisation Details'!A:E,5,0) -> 0 | N2319: =VLOOKUP(A2319,'Hospitalisation Details'!A:F,6,0) -> 770.38 | O2319: =VLOOKUP(A2319,'Hospitalisation Details'!A:G,7,0) -> tier - 3 | P2319: =VLOOKUP(A2319,'Hospitalisation Details'!A:I,8,0) -> tier - 2 | Q2319: =VLOOKUP(A2319,'Hospitalisation Details'!A:I,9,0) -> R1012
A2320: Id2319 | B2320: =VLOOKUP(A2320,'Customer Names'!A:B,2,0) -> Petermann, Mr. Theodore A. | C2320: =VLOOKUP(A2320,'Medical Examinations'!A:H,2,0) -> 17.08 | D2320: =VLOOKUP(A2320,'Medical Examinations'!A:C,3,0) -> 5.73 | E2320: =VLOOKUP(A2320,'Medical Examinations'!A:E,4) -> No | F2320: =VLOOKUP(A2320,'Medical Examinations'!A:E,5) -> No | G2320: =VLOOKUP(A2320,'Medical Examinations'!A:F,6,0) -> Yes | H2320: =VLOOKUP(A2320,'Medical Examinations'!A:G,7) -> 1 | I2320: =VLOOKUP(A2320,'Medical Examinations'!A:H,8,0) -> No | J2320: =VLOOKUP(A2320,'Hospitalisation Details'!A:B,2,0) -> 1993 | K2320: =VLOOKUP(A2320,'Hospitalisation Details'!A:C,3,0) -> Jun | L2320: =VLOOKUP(A2320,'Hospitalisation Details'!A:D,4,0) -> 28 | M2320: =VLOOKUP(A2320,'Hospitalisation Details'!A:E,5,0) -> 0 | N2320: =VLOOKUP(A2320,'Hospitalisation Details'!A:F,6,0) -> 770 | O2320: =VLOOKUP(A2320,'Hospitalisation Details'!A:G,7,0) -> tier - 3 | P2320: =VLOOKUP(A2320,'Hospitalisation Details'!A:I,8,0) -> tier - 3 | Q2320: =VLOOKUP(A2320,'Hospitalisation Details'!A:I,9,0) -> R1013
A2321: Id2320 | B2321: =VLOOKUP(A2321,'Customer Names'!A:B,2,0) -> Graves - Rostro, Ms. Lindy | C2321: =VLOOKUP(A2321,'Medical Examinations'!A:H,2,0) -> 19.21 | D2321: =VLOOKUP(A2321,'Medical Examinations'!A:C,3,0) -> 5.53 | E2321: =VLOOKUP(A2321,'Medical Examinations'!A:E,4) -> yes | F2321: =VLOOKUP(A2321,'Medical Examinations'!A:E,5) -> No | G2321: =VLOOKUP(A2321,'Medical Examinations'!A:F,6,0) -> No | H2321: =VLOOKUP(A2321,'Medical Examinations'!A:G,7) -> No major surgery | I2321: =VLOOKUP(A2321,'Medical Examinations'!A:H,8,0) -> No | J2321: =VLOOKUP(A2321,'Hospitalisation Details'!A:B,2,0) -> 1996 | K2321: =VLOOKUP(A2321,'Hospitalisation Details'!A:C,3,0) -> Oct | L2321: =VLOOKUP(A2321,'Hospitalisation Details'!A:D,4,0) -> 22 | M2321: =VLOOKUP(A2321,'Hospitalisation Details'!A:E,5,0) -> 0 | N2321: =VLOOKUP(A2321,'Hospitalisation Details'!A:F,6,0) -> 760 | O2321: =VLOOKUP(A2321,'Hospitalisation Details'!A:G,7,0) -> tier - 3 | P2321: =VLOOKUP(A2321,'Hospitalisation Details'!A:I,8,0) -> tier - 3 | Q2321: =VLOOKUP(A2321,'Hospitalisation Details'!A:I,9,0) -> R1013
A2322: Id2321 | B2322: =VLOOKUP(A2322,'Customer Names'!A:B,2,0) -> Danielson, Mr. Thomas | C2322: =VLOOKUP(A2322,'Medical Examinations'!A:H,2,0) -> 17.86 | D2322: =VLOOKUP(A2322,'Medical Examinations'!A:C,3,0) -> 5.43 | E2322: =VLOOKUP(A2322,'Medical Examinations'!A:E,4) -> No | F2322: =VLOOKUP(A2322,'Medical Examinations'!A:E,5) -> No | G2322: =VLOOKUP(A2322,'Medical Examinations'!A:F,6,0) -> Yes | H2322: =VLOOKUP(A2322,'Medical Examinations'!A:G,7) -> 1 | I2322: =VLOOKUP(A2322,'Medical Examinations'!A:H,8,0) -> No | J2322: =VLOOKUP(A2322,'Hospitalisation Details'!A:B,2,0) -> 1993 | K2322: =VLOOKUP(A2322,'Hospitalisation Details'!A:C,3,0) -> Aug | L2322: =VLOOKUP(A2322,'Hospitalisation Details'!A:D,4,0) -> 9 | M2322: =VLOOKUP(A2322,'Hospitalisation Details'!A:E,5,0) -> 0 | N2322: =VLOOKUP(A2322,'Hospitalisation Details'!A:F,6,0) -> 760 | O2322: =VLOOKUP(A2322,'Hospitalisation Details'!A:G,7,0) -> tier - 3 | P2322: =VLOOKUP(A2322,'Hospitalisation Details'!A:I,8,0) -> tier - 1 | Q2322: =VLOOKUP(A2322,'Hospitalisation Details'!A:I,9,0) -> R1013
A2323: Id2322 | B2323: =VLOOKUP(A2323,'Customer Names'!A:B,2,0) -> Street, Ms. Holly | C2323: =VLOOKUP(A2323,'Medical Examinations'!A:H,2,0) -> 21.38 | D2323: =VLOOKUP(A2323,'Medical Examinations'!A:C,3,0) -> 8.01 | E2323: =VLOOKUP(A2323,'Medical Examinations'!A:E,4) -> No | F2323: =VLOOKUP(A2323,'Medical Examinations'!A:E,5) -> No | G2323: =VLOOKUP(A2323,'Medical Examinations'!A:F,6,0) -> No | H2323: =VLOOKUP(A2323,'Medical Examinations'!A:G,7) -> No major surgery | I2323: =VLOOKUP(A2323,'Medical Examinations'!A:H,8,0) -> No | J2323: =VLOOKUP(A2323,'Hospitalisation Details'!A:B,2,0) -> 2002 | K2323: Sep | L2323: =VLOOKUP(A2323,'Hospitalisation Details'!A:D,4,0) -> 19 | M2323: =VLOOKUP(A2323,'Hospitalisation Details'!A:E,5,0) -> 0 | N2323: =VLOOKUP(A2323,'Hospitalisation Details'!A:F,6,0) -> 750 | O2323: =VLOOKUP(A2323,'Hospitalisation Details'!A:G,7,0) -> tier - 3 | P2323: =VLOOKUP(A2323,'Hospitalisation Details'!A:I,8,0) -> tier - 1 | Q2323: =VLOOKUP(A2323,'Hospitalisation Details'!A:I,9,0) -> R1012
A2324: Id2323 | B2324: =VLOOKUP(A2324,'Customer Names'!A:B,2,0) -> Buss, Mr. Matthew | C2324: =VLOOKUP(A2324,'Medical Examinations'!A:H,2,0) -> 23.35 | D2324: =VLOOKUP(A2324,'Medical Examinations'!A:C,3,0) -> 5.94 | E2324: =VLOOKUP(A2324,'Medical Examinations'!A:E,4) -> No | F2324: =VLOOKUP(A2324,'Medical Examinations'!A:E,5) -> No | G2324: =VLOOKUP(A2324,'Medical Examinations'!A:F,6,0) -> No | H2324: =VLOOKUP(A2324,'Medical Examinations'!A:G,7) -> No major surgery | I2324: =VLOOKUP(A2324,'Medical Examinations'!A:H,8,0) -> No | J2324: =VLOOKUP(A2324,'Hospitalisation Details'!A:B,2,0) -> 1999 | K2324: =VLOOKUP(A2324,'Hospitalisation Details'!A:C,3,0) -> Dec | L2324: =VLOOKUP(A2324,'Hospitalisation Details'!A:D,4,0) -> 14 | M2324: =VLOOKUP(A2324,'Hospitalisation Details'!A:E,5,0) -> 0 | N2324: =VLOOKUP(A2324,'Hospitalisation Details'!A:F,6,0) -> 722.99 | O2324: =VLOOKUP(A2324,'Hospitalisation Details'!A:G,7,0) -> tier - 3 | P2324: =VLOOKUP(A2324,'Hospitalisation Details'!A:I,8,0) -> tier - 1 | Q2324: =VLOOKUP(A2324,'Hospitalisation Details'!A:I,9,0) -> R1013
A2325: Id2324 | B2325: =VLOOKUP(A2325,'Customer Names'!A:B,2,0) -> Duffy, Ms. Meghan K | C2325: =VLOOKUP(A2325,'Medical Examinations'!A:H,2,0) -> 22.24 | D2325: =VLOOKUP(A2325,'Medical Examinations'!A:C,3,0) -> 5.04 | E2325: =VLOOKUP(A2325,'Medical Examinations'!A:E,4) -> No | F2325: =VLOOKUP(A2325,'Medical Examinations'!A:E,5) -> No | G2325: =VLOOKUP(A2325,'Medical Examinations'!A:F,6,0) -> No | H2325: =VLOOKUP(A2325,'Medical Examinations'!A:G,7) -> No major surgery | I2325: =VLOOKUP(A2325,'Medical Examinations'!A:H,8,0) -> No | J2325: =VLOOKUP(A2325,'Hospitalisation Details'!A:B,2,0) -> 1999 | K2325: =VLOOKUP(A2325,'Hospitalisation Details'!A:C,3,0) -> Dec | L2325: =VLOOKUP(A2325,'Hospitalisation Details'!A:D,4,0) -> 26 | M2325: =VLOOKUP(A2325,'Hospitalisation Details'!A:E,5,0) -> 0 | N2325: =VLOOKUP(A2325,'Hospitalisation Details'!A:F,6,0) -> 700 | O2325: =VLOOKUP(A2325,'Hospitalisation Details'!A:G,7,0) -> tier - 2 | P2325: =VLOOKUP(A2325,'Hospitalisation Details'!A:I,8,0) -> tier - 3 | Q2325: =VLOOKUP(A2325,'Hospitalisation Details'!A:I,9,0) -> R1013
A2326: Id2325 | B2326: =VLOOKUP(A2326,'Customer Names'!A:B,2,0) -> Hines, Mr. Fred | C2326: =VLOOKUP(A2326,'Medical Examinations'!A:H,2,0) -> 24.76 | D2326: =VLOOKUP(A2326,'Medical Examinations'!A:C,3,0) -> 4.54 | E2326: =VLOOKUP(A2326,'Medical Examinations'!A:E,4) -> yes | F2326: =VLOOKUP(A2326,'Medical Examinations'!A:E,5) -> No | G2326: =VLOOKUP(A2326,'Medical Examinations'!A:F,6,0) -> No | H2326: =VLOOKUP(A2326,'Medical Examinations'!A:G,7) -> No major surgery | I2326: =VLOOKUP(A2326,'Medical Examinations'!A:H,8,0) -> No | J2326: =VLOOKUP(A2326,'Hospitalisation Details'!A:B,2,0) -> 2001 | K2326: =VLOOKUP(A2326,'Hospitalisation Details'!A:C,3,0) -> Sep | L2326: =VLOOKUP(A2326,'Hospitalisation Details'!A:D,4,0) -> 12 | M2326: =VLOOKUP(A2326,'Hospitalisation Details'!A:E,5,0) -> 0 | N2326: =VLOOKUP(A2326,'Hospitalisation Details'!A:F,6,0) -> 687.54 | O2326: =VLOOKUP(A2326,'Hospitalisation Details'!A:G,7,0) -> tier - 3 | P2326: =VLOOKUP(A2326,'Hospitalisation Details'!A:I,8,0) -> tier - 2 | Q2326: =VLOOKUP(A2326,'Hospitalisation Details'!A:I,9,0) -> R1013
A2327: Id2326 | B2327: =VLOOKUP(A2327,'Customer Names'!A:B,2,0) -> Castro, Mr. Sebastian | C2327: =VLOOKUP(A2327,'Medical Examinations'!A:H,2,0) -> 20.1 | D2327: =VLOOKUP(A2327,'Medical Examinations'!A:C,3,0) -> 5.6 | E2327: =VLOOKUP(A2327,'Medical Examinations'!A:E,4) -> yes | F2327: =VLOOKUP(A2327,'Medical Examinations'!A:E,5) -> No | G2327: =VLOOKUP(A2327,'Medical Examinations'!A:F,6,0) -> Yes | H2327: =VLOOKUP(A2327,'Medical Examinations'!A:G,7) -> 1 | I2327: =VLOOKUP(A2327,'Medical Examinations'!A:H,8,0) -> No | J2327: =VLOOKUP(A2327,'Hospitalisation Details'!A:B,2,0) -> 1997 | K2327: =VLOOKUP(A2327,'Hospitalisation Details'!A:C,3,0) -> Nov | L2327: =VLOOKUP(A2327,'Hospitalisation Details'!A:D,4,0) -> 9 | M2327: =VLOOKUP(A2327,'Hospitalisation Details'!A:E,5,0) -> 0 | N2327: =VLOOKUP(A2327,'Hospitalisation Details'!A:F,6,0) -> 670 | O2327: =VLOOKUP(A2327,'Hospitalisation Details'!A:G,7,0) -> tier - 3 | P2327: =VLOOKUP(A2327,'Hospitalisation Details'!A:I,8,0) -> tier - 3 | Q2327: =VLOOKUP(A2327,'Hospitalisation Details'!A:I,9,0) -> R1013
A2328: Id2327 | B2328: =VLOOKUP(A2328,'Customer Names'!A:B,2,0) -> Howell, Ms. Laura | C2328: =VLOOKUP(A2328,'Medical Examinations'!A:H,2,0) -> 21.77 | D2328: =VLOOKUP(A2328,'Medical Examinations'!A:C,3,0) -> 10.67 | E2328: =VLOOKUP(A2328,'Medical Examinations'!A:E,4) -> No | F2328: =VLOOKUP(A2328,'Medical Examinations'!A:E,5) -> No | G2328: =VLOOKUP(A2328,'Medical Examinations'!A:F,6,0) -> No | H2328: =VLOOKUP(A2328,'Medical Examinations'!A:G,7) -> No major surgery | I2328: =VLOOKUP(A2328,'Medical Examinations'!A:H,8,0) -> No | J2328: =VLOOKUP(A2328,'Hospitalisation Details'!A:B,2,0) -> 2002 | K2328: =VLOOKUP(A2328,'Hospitalisation Details'!A:C,3,0) -> Nov | L2328: =VLOOKUP(A2328,'Hospitalisation Details'!A:D,4,0) -> 29 | M2328: =VLOOKUP(A2328,'Hospitalisation Details'!A:E,5,0) -> 0 | N2328: =VLOOKUP(A2328,'Hospitalisation Details'!A:F,6,0) -> 668 | O2328: =VLOOKUP(A2328,'Hospitalisation Details'!A:G,7,0) -> tier - 3 | P2328: =VLOOKUP(A2328,'Hospitalisation Details'!A:I,8,0) -> tier - 2 | Q2328: =VLOOKUP(A2328,'Hospitalisation Details'!A:I,9,0) -> R1012
A2329: Id2328 | B2329: =VLOOKUP(A2329,'Customer Names'!A:B,2,0) -> Avery, Ms. Nicole | C2329: =VLOOKUP(A2329,'Medical Examinations'!A:H,2,0) -> 17.82 | D2329: =VLOOKUP(A2329,'Medical Examinations'!A:C,3,0) -> 5.26 | E2329: =VLOOKUP(A2329,'Medical Examinations'!A:E,4) -> yes | F2329: =VLOOKUP(A2329,'Medical Examinations'!A:E,5) -> No | G2329: =VLOOKUP(A2329,'Medical Examinations'!A:F,6,0) -> No | H2329: =VLOOKUP(A2329,'Medical Examinations'!A:G,7) -> 1 | I2329: =VLOOKUP(A2329,'Medical Examinations'!A:H,8,0) -> No | J2329: =VLOOKUP(A2329,'Hospitalisation Details'!A:B,2,0) -> 1995 | K2329: =VLOOKUP(A2329,'Hospitalisation Details'!A:C,3,0) -> Jul | L2329: =VLOOKUP(A2329,'Hospitalisation Details'!A:D,4,0) -> 4 | M2329: =VLOOKUP(A2329,'Hospitalisation Details'!A:E,5,0) -> 0 | N2329: =VLOOKUP(A2329,'Hospitalisation Details'!A:F,6,0) -> 650 | O2329: =VLOOKUP(A2329,'Hospitalisation Details'!A:G,7,0) -> tier - 3 | P2329: =VLOOKUP(A2329,'Hospitalisation Details'!A:I,8,0) -> tier - 3 | Q2329: =VLOOKUP(A2329,'Hospitalisation Details'!A:I,9,0) -> R1013
A2330: Id2329 | B2330: =VLOOKUP(A2330,'Customer Names'!A:B,2,0) -> Bohinski, Ms. Susan E | C2330: =VLOOKUP(A2330,'Medical Examinations'!A:H,2,0) -> 17.07 | D2330: =VLOOKUP(A2330,'Medical Examinations'!A:C,3,0) -> 5.22 | E2330: =VLOOKUP(A2330,'Medical Examinations'!A:E,4) -> No | F2330: =VLOOKUP(A2330,'Medical Examinations'!A:E,5) -> No | G2330: =VLOOKUP(A2330,'Medical Examinations'!A:F,6,0) -> Yes | H2330: =VLOOKUP(A2330,'Medical Examinations'!A:G,7) -> 1 | I2330: =VLOOKUP(A2330,'Medical Examinations'!A:H,8,0) -> No | J2330: =VLOOKUP(A2330,'Hospitalisation Details'!A:B,2,0) -> 1993 | K2330: =VLOOKUP(A2330,'Hospitalisation Details'!A:C,3,0) -> Jun | L2330: =VLOOKUP(A2330,'Hospitalisation Details'!A:D,4,0) -> 1 | M2330: =VLOOKUP(A2330,'Hospitalisation Details'!A:E,5,0) -> 0 | N2330: =VLOOKUP(A2330,'Hospitalisation Details'!A:F,6,0) -> 650 | O2330: =VLOOKUP(A2330,'Hospitalisation Details'!A:G,7,0) -> tier - 3 | P2330: =VLOOKUP(A2330,'Hospitalisation Details'!A:I,8,0) -> tier - 3 | Q2330: =VLOOKUP(A2330,'Hospitalisation Details'!A:I,9,0) -> R1013
A2331: Id2330 | B2331: =VLOOKUP(A2331,'Customer Names'!A:B,2,0) -> Kohls, Ms. Katy | C2331: =VLOOKUP(A2331,'Medical Examinations'!A:H,2,0) -> 22.24 | D2331: =VLOOKUP(A2331,'Medical Examinations'!A:C,3,0) -> 4.29 | E2331: =VLOOKUP(A2331,'Medical Examinations'!A:E,4) -> yes | F2331: =VLOOKUP(A2331,'Medical Examinations'!A:E,5) -> No | G2331: =VLOOKUP(A2331,'Medical Examinations'!A:F,6,0) -> No | H2331: =VLOOKUP(A2331,'Medical Examinations'!A:G,7) -> No major surgery | I2331: =VLOOKUP(A2331,'Medical Examinations'!A:H,8,0) -> No | J2331: =VLOOKUP(A2331,'Hospitalisation Details'!A:B,2,0) -> 2001 | K2331: =VLOOKUP(A2331,'Hospitalisation Details'!A:C,3,0) -> Nov | L2331: =VLOOKUP(A2331,'Hospitalisation Details'!A:D,4,0) -> 20 | M2331: =VLOOKUP(A2331,'Hospitalisation Details'!A:E,5,0) -> 0 | N2331: =VLOOKUP(A2331,'Hospitalisation Details'!A:F,6,0) -> 646.14 | O2331: =VLOOKUP(A2331,'Hospitalisation Details'!A:G,7,0) -> tier - 3 | P2331: =VLOOKUP(A2331,'Hospitalisation Details'!A:I,8,0) -> tier - 3 | Q2331: =VLOOKUP(A2331,'Hospitalisation Details'!A:I,9,0) -> R1012
A2332: Id2331 | B2332: =VLOOKUP(A2332,'Customer Names'!A:B,2,0) -> Brietzke, Mr. Jordan | C2332: =VLOOKUP(A2332,'Medical Examinations'!A:H,2,0) -> 22.34 | D2332: =VLOOKUP(A2332,'Medical Examinations'!A:C,3,0) -> 5.57 | E2332: =VLOOKUP(A2332,'Medical Examinations'!A:E,4) -> No | F2332: =VLOOKUP(A2332,'Medical Examinations'!A:E,5) -> No | G2332: =VLOOKUP(A2332,'Medical Examinations'!A:F,6,0) -> No | H2332: =VLOOKUP(A2332,'Medical Examinations'!A:G,7) -> 1 | I2332: =VLOOKUP(A2332,'Medical Examinations'!A:H,8,0) -> No | J2332: =VLOOKUP(A2332,'Hospitalisation Details'!A:B,2,0) -> 1998 | K2332: =VLOOKUP(A2332,'Hospitalisation Details'!A:C,3,0) -> Jul | L2332: =VLOOKUP(A2332,'Hospitalisation Details'!A:D,4,0) -> 27 | M2332: =VLOOKUP(A2332,'Hospitalisation Details'!A:E,5,0) -> 0 | N2332: =VLOOKUP(A2332,'Hospitalisation Details'!A:F,6,0) -> 637.26 | O2332: =VLOOKUP(A2332,'Hospitalisation Details'!A:G,7,0) -> tier - 3 | P2332: =VLOOKUP(A2332,'Hospitalisation Details'!A:I,8,0) -> tier - 3 | Q2332: =VLOOKUP(A2332,'Hospitalisation Details'!A:I,9,0) -> R1013
A2333: Id2332 | B2333: =VLOOKUP(A2333,'Customer Names'!A:B,2,0) -> Riveros Gonzalez, Mr. Juan D. Sr. | C2333: =VLOOKUP(A2333,'Medical Examinations'!A:H,2,0) -> 17.7 | D2333: =VLOOKUP(A2333,'Medical Examinations'!A:C,3,0) -> 6.28 | E2333: =VLOOKUP(A2333,'Medical Examinations'!A:E,4) -> No | F2333: =VLOOKUP(A2333,'Medical Examinations'!A:E,5) -> No | G2333: =VLOOKUP(A2333,'Medical Examinations'!A:F,6,0) -> No | H2333: =VLOOKUP(A2333,'Medical Examinations'!A:G,7) -> 1 | I2333: =VLOOKUP(A2333,'Medical Examinations'!A:H,8,0) -> No | J2333: =VLOOKUP(A2333,'Hospitalisation Details'!A:B,2,0) -> 1992 | K2333: =VLOOKUP(A2333,'Hospitalisation Details'!A:C,3,0) -> Sep | L2333: =VLOOKUP(A2333,'Hospitalisation Details'!A:D,4,0) -> 13 | M2333: =VLOOKUP(A2333,'Hospitalisation Details'!A:E,5,0) -> 0 | N2333: =VLOOKUP(A2333,'Hospitalisation Details'!A:F,6,0) -> 604.54 | O2333: =VLOOKUP(A2333,'Hospitalisation Details'!A:G,7,0) -> tier - 3 | P2333: =VLOOKUP(A2333,'Hospitalisation Details'!A:I,8,0) -> tier - 3 | Q2333: =VLOOKUP(A2333,'Hospitalisation Details'!A:I,9,0) -> R1013
A2334: Id2333 | B2334: =VLOOKUP(A2334,'Customer Names'!A:B,2,0) -> Albano, Ms. Julie | C2334: =VLOOKUP(A2334,'Medical Examinations'!A:H,2,0) -> 16.47 | D2334: =VLOOKUP(A2334,'Medical Examinations'!A:C,3,0) -> 6.35 | E2334: =VLOOKUP(A2334,'Medical Examinations'!A:E,4) -> No | F2334: =VLOOKUP(A2334,'Medical Examinations'!A:E,5) -> No | G2334: =VLOOKUP(A2334,'Medical Examinations'!A:F,6,0) -> Yes | H2334: =VLOOKUP(A2334,'Medical Examinations'!A:G,7) -> 1 | I2334: =VLOOKUP(A2334,'Medical Examinations'!A:H,8,0) -> No | J2334: =VLOOKUP(A2334,'Hospitalisation Details'!A:B,2,0) -> 1993 | K2334: =VLOOKUP(A2334,'Hospitalisation Details'!A:C,3,0) -> Jun | L2334: =VLOOKUP(A2334,'Hospitalisation Details'!A:D,4,0) -> 30 | M2334: =VLOOKUP(A2334,'Hospitalisation Details'!A:E,5,0) -> 0 | N2334: =VLOOKUP(A2334,'Hospitalisation Details'!A:F,6,0) -> 600 | O2334: =VLOOKUP(A2334,'Hospitalisation Details'!A:G,7,0) -> tier - 2 | P2334: =VLOOKUP(A2334,'Hospitalisation Details'!A:I,8,0) -> tier - 1 | Q2334: =VLOOKUP(A2334,'Hospitalisation Details'!A:I,9,0) -> R1013
A2335: Id2334 | B2335: =VLOOKUP(A2335,'Customer Names'!A:B,2,0) -> Rosendahl, Mr. Evan P | C2335: =VLOOKUP(A2335,'Medical Examinations'!A:H,2,0) -> 17.6 | D2335: =VLOOKUP(A2335,'Medical Examinations'!A:C,3,0) -> 4.39 | E2335: =VLOOKUP(A2335,'Medical Examinations'!A:E,4) -> No | F2335: =VLOOKUP(A2335,'Medical Examinations'!A:E,5) -> No | G2335: =VLOOKUP(A2335,'Medical Examinations'!A:F,6,0) -> No | H2335: =VLOOKUP(A2335,'Medical Examinations'!A:G,7) -> 1 | I2335: =VLOOKUP(A2335,'Medical Examinations'!A:H,8,0) -> No | J2335: =VLOOKUP(A2335,'Hospitalisation Details'!A:B,2,0) -> 1992 | K2335: =VLOOKUP(A2335,'Hospitalisation Details'!A:C,3,0) -> Nov | L2335: =VLOOKUP(A2335,'Hospitalisation Details'!A:D,4,0) -> 30 | M2335: =VLOOKUP(A2335,'Hospitalisation Details'!A:E,5,0) -> 0 | N2335: =VLOOKUP(A2335,'Hospitalisation Details'!A:F,6,0) -> 570.62 | O2335: =VLOOKUP(A2335,'Hospitalisation Details'!A:G,7,0) -> tier - 2 | P2335: =VLOOKUP(A2335,'Hospitalisation Details'!A:I,8,0) -> tier - 1 | Q2335: =VLOOKUP(A2335,'Hospitalisation Details'!A:I,9,0) -> R1013
A2336: Id2335 | B2336: =VLOOKUP(A2336,'Customer Names'!A:B,2,0) -> German, Mr. Aaron K | C2336: =VLOOKUP(A2336,'Medical Examinations'!A:H,2,0) -> 17.58 | D2336: =VLOOKUP(A2336,'Medical Examinations'!A:C,3,0) -> 4.51 | E2336: =VLOOKUP(A2336,'Medical Examinations'!A:E,4) -> No | F2336: =VLOOKUP(A2336,'Medical Examinations'!A:E,5) -> No | G2336: =VLOOKUP(A2336,'Medical Examinations'!A:F,6,0) -> No | H2336: =VLOOKUP(A2336,'Medical Examinations'!A:G,7) -> 1 | I2336: =VLOOKUP(A2336,'Medical Examinations'!A:H,8,0) -> No | J2336: =VLOOKUP(A2336,'Hospitalisation Details'!A:B,2,0) -> 1992 | K2336: =VLOOKUP(A2336,'Hospitalisation Details'!A:C,3,0) -> Jul | L2336: =VLOOKUP(A2336,'Hospitalisation Details'!A:D,4,0) -> 9 | M2336: =VLOOKUP(A2336,'Hospitalisation Details'!A:E,5,0) -> 0 | N2336: =VLOOKUP(A2336,'Hospitalisation Details'!A:F,6,0) -> 563.84 | O2336: =VLOOKUP(A2336,'Hospitalisation Details'!A:G,7,0) -> tier - 2 | P2336: =VLOOKUP(A2336,'Hospitalisation Details'!A:I,8,0) -> tier - 3 | Q2336: =VLOOKUP(A2336,'Hospitalisation Details'!A:I,9,0) -> R1013

Sheet Analysis using Chart 
A1: Distribution of cancer history among smokers and non-smokers | U1: Weight Status | V1: Diabetes Status | W1: charges | X1: Healthcare charges by weight and diabetes status | AD1: BMI | AE1: HBA1C | AF1: Correlation of age with BMI and HBA1C | AV1: charges | AW1: Age | AX1: Age vs Charges
A2: Count of Customer ID | B2: Column Labels | U2: Obesity | V2: Diabetes | W2: 563.84 | X2: Sum of charges | Y2: Column Labels | AD2: 47.41 | AE2: 7.47 | AV2: 563.84 | AW2: 30
A3: Row Labels | B3: No | C3: Yes | D3: Grand Total | U3: Obesity | V3: Prediabetes | W3: 570.62 | X3: Row Labels | Y3: Diabetes | Z3: Normal | AA3: Prediabetes | AB3: Grand Total | AD3: 30.36 | AE3: 5.77 | AV3: 570.62 | AW3: 30
A4: No | B4: 1538 | C4: 307 | D4: 1845 | U4: Obesity | V4: Diabetes | W4: 600 | X4: Normal Weight | Y4: 1600454.1 | Z4: 4437473 | AA4: 1515604.7 | AB4: 7553531.8 | AD4: 34.485 | AE4: 11.87 | AV4: 600 | AW4: 29
A5: yes | B5: 406 | C5: 84 | D5: 490 | U5: Obesity | V5: Prediabetes | W5: 604.54 | X5: Obesity | Y5: 3133306 | Z5: 6922656.9 | AA5: 2744960.8 | AB5: 12800924 | AD5: 38.095 | AE5: 6.05 | AV5: 604.54 | AW5: 30
A6: Grand Total | B6: 1944 | C6: 391 | D6: 2335 | U6: Obesity | V6: Normal | W6: 637.26 | X6: Overweight | Y6: 1555305.7 | Z6: 3629088.6 | AA6: 1660576 | AB6: 6844970.3 | AD6: 35.53 | AE6: 5.45 | AV6: 637.26 | AW6: 24
U7: Obesity | V7: Diabetes | W7: 646.14 | X7: Underweight | Y7: 1178108.7 | Z7: 2202772.4 | AA7: 735134.98 | AB7: 4116016 | AD7: 32.8 | AE7: 6.59 | AV7: 646.14 | AW7: 21
U8: Obesity | V8: Prediabetes | W8: 650 | X8: Grand Total | Y8: 7467174.4 | Z8: 17191991 | AA8: 6656276.5 | AB8: 31315442 | AD8: 36.4 | AE8: 6.07 | AV8: 650 | AW8: 30
U9: Obesity | V9: Diabetes | W9: 650 | AD9: 36.96 | AE9: 7.93 | AV9: 650 | AW9: 27
U10: Obesity | V10: Diabetes | W10: 668 | AD10: 41.14 | AE10: 9.58 | AV10: 668 | AW10: 20
U11: Obesity | V11: Diabetes | W11: 670 | AD11: 38.06 | AE11: 10.79 | AV11: 670 | AW11: 25
U12: Obesity | V12: Prediabetes | W12: 687.54 | AD12: 37.7 | AE12: 5.96 | AV12: 687.54 | AW12: 21
U13: Obesity | V13: Diabetes | W13: 700 | AD13: 42.13 | AE13: 11.9 | AV13: 700 | AW13: 23
U14: Obesity | V14: Diabetes | W14: 722.99 | AD14: 40.92 | AE14: 8.41 | AV14: 722.99 | AW14: 23
U15: Obesity | V15: Diabetes | W15: 750 | AD15: 40.565 | AE15: 7.02 | AV15: 750 | AW15: 20
U16: Obesity | V16: Diabetes | W16: 760 | AD16: 36.385 | AE16: 7.59 | AV16: 760 | AW16: 29
U17: Obesity | V17: Diabetes | W17: 760 | AD17: 39.9 | AE17: 11.32 | AV17: 760 | AW17: 26
U18: Obesity | V18: Diabetes | W18: 770 | AD18: 33.8 | AE18: 7.67 | AV18: 770 | AW18: 29
U19: Obesity | V19: Diabetes | W19: 770.38 | AD19: 36.765 | AE19: 7.29 | AV19: 770.38 | AW19: 26
A20: Differ between patients with and without a history of transplants? | U20: Obesity | V20: Normal | W20: 773.54 | AD20: 36.955 | AE20: 4.72 | AV20: 773.54 | AW20: 27
A21: Row Labels | B21: Count of NumberOfMajorSurgeries | C21: Sum of HBA1C | U21: Obesity | V21: Diabetes | W21: 830.52 | AD21: 42.9 | AE21: 11.41 | AV21: 830.52 | AW21: 18
A22: No | B22: 2191 | C22: 14614.94 | U22: Obesity | V22: Diabetes | W22: 865.41 | AD22: 36.3 | AE22: 11.5 | AV22: 865.41 | AW22: 22
A23: yes | B23: 144 | C23: 747.02 | U23: Obesity | V23: Prediabetes | W23: 896.21 | AD23: 32.2 | AE23: 6.22 | AV23: 896.21 | AW23: 29
A24: Grand Total | B24: 2335 | C24: 15361.96 | U24: Obesity | V24: Diabetes | W24: 915.07 | AD24: 31.3 | AE24: 11.38 | AV24: 915.07 | AW24: 28
U25: Obesity | V25: Diabetes | W25: 928.59 | AD25: 41.8 | AE25: 7.89 | AV25: 928.59 | AW25: 27
U26: Obesity | V26: Normal | W26: 964.71 | AD26: 35.09 | AE26: 4.38 | AV26: 964.71 | AW26: 21
U27: Obesity | V27: Diabetes | W27: 1006.65 | AD27: 33.88 | AE27: 7.01 | AV27: 1006.65 | AW27: 28
U28: Obesity | V28: Diabetes | W28: 1012 | AD28: 30.875 | AE28: 11.88 | AV28: 1012 | AW28: 22
U29: Obesity | V29: Normal | W29: 1019 | AD29: 36.86 | AE29: 5.19 | AV29: 1019 | AW29: 23
U30: Obesity | V30: Diabetes | W30: 1033.74 | AD30: 35.86 | AE30: 6.74 | AV30: 1033.74 | AW30: 27
U31: Obesity | V31: Diabetes | W31: 1044 | AD31: 37.05 | AE31: 8.44 | AV31: 1044 | AW31: 28
U32: Obesity | V32: Diabetes | W32: 1047 | AD32: 43.89 | AE32: 8.71 | AV32: 1047 | AW32: 20
U33: Obesity | V33: Normal | W33: 1049 | AD33: 42.35 | AE33: 5.08 | AV33: 1049 | AW33: 20
U34: Obesity | V34: Diabetes | W34: 1056 | AD34: 31.35 | AE34: 6.86 | AV34: 1056 | AW34: 28
U35: Obesity | V35: Prediabetes | W35: 1068 | AD35: 47.6 | AE35: 5.95 | AV35: 1068 | AW35: 29
A36: Average charges by hospital tier within states | U36: Obesity | V36: Prediabetes | W36: 1070 | AD36: 46.2 | AE36: 6.09 | AV36: 1070 | AW36: 18
A37: Sum of charges | B37: Column Labels | U37: Obesity | V37: Diabetes | W37: 1071 | AD37: 32.015 | AE37: 11.75 | AV37: 1071 | AW37: 25
A38: Row Labels | B38: tier - 1 | C38: tier - 2 | D38: tier - 3 | E38: Grand Total | U38: Obesity | V38: Diabetes | W38: 1082 | AD38: 40.565 | AE38: 7.37 | AV38: 1082 | AW38: 24
A39: R1011 | B39: 3948573.4 | C39: 6041135.3 | D39: 1295050.7 | E39: 11284759 | U39: Obesity | V39: Diabetes | W39: 1086 | AD39: 32.45 | AE39: 11.91 | AV39: 1086 | AW39: 20
A40: R1012 | B40: 1651225.7 | C40: 3506095.9 | D40: 1761130 | E40: 6918451.6 | U40: Obesity | V40: Diabetes | W40: 1121.87 | AD40: 34.96 | AE40: 6.52 | AV40: 1121.87 | AW40: 18
A41: R1013 | B41: 2133286 | C41: 3164731.6 | D41: 1172565.7 | E41: 6470583.3 | U41: Obesity | V41: Normal | W41: 1131.51 | AD41: 35.5 | AE41: 5.14 | AV41: 1131.51 | AW41: 18
A42: R1014 | B42: 138918.6 | C42: 2395.17 | D42: 33900.97 | E42: 175214.74 | U42: Obesity | V42: Normal | W42: 1132 | AD42: 52.58 | AE42: 4.19 | AV42: 1132 | AW42: 20
A43: R1015 | B43: 43047.04 | C43: 115037.35 | D43: 30283.02 | E43: 188367.41 | U43: Obesity | V43: Diabetes | W43: 1135 | AD43: 35.2 | AE43: 11.68 | AV43: 1135 | AW43: 18
A44: R1016 | B44: 318948.93 | C44: 192911.56 | D44: 357852.37 | E44: 869712.86 | U44: Obesity | V44: Diabetes | W44: 1135.94 | AD44: 38.06 | AE44: 6.98 | AV44: 1135.94 | AW44: 18
A45: R1017 | B45: 238494.17 | C45: 181849.95 | D45: 112675.76 | E45: 533019.88 | U45: Obesity | V45: Diabetes | W45: 1136.4 | AD45: 34.21 | AE45: 8.34 | AV45: 1136.4 | AW45: 18
A46: R1018 | B46: 33475.82 | C46: 60837.32 | D46: 25141.94 | E46: 119455.08 | U46: Obesity | V46: Diabetes | W46: 1137 | AD46: 38.94 | AE46: 8.49 | AV46: 1137 | AW46: 20
A47: R1019 | B47: 138108.05 | C47: 89283.92 | D47: 127069.76 | E47: 354461.73 | U47: Obesity | V47: Normal | W47: 1137.01 | AD47: 30.21 | AE47: 5.34 | AV47: 1137.01 | AW47: 18
A48: R1020 | C48: 20281.63 | D48: 35149.36 | E48: 55430.99 | U48: Obesity | V48: Normal | W48: 1137.01 | AD48: 33.63 | AE48: 4.43 | AV48: 1137.01 | AW48: 18
A49: R1021 | C49: 360404.4 | D49: 264932.07 | E49: 625336.47 | U49: Obesity | V49: Normal | W49: 1137.47 | AD49: 40.37 | AE49: 4.47 | AV49: 1137.47 | AW49: 18
A50: R1022 | C50: 90918.24 | D50: 58189.06 | E50: 149107.3 | U50: Obesity | V50: Normal | W50: 1141 | AD50: 53.09 | AE50: 4.82 | AV50: 1141 | AW50: 21
A51: R1023 | B51: 73047.03 | C51: 322970.27 | D51: 127856.37 | E51: 523873.67 | U51: Obesity | V51: Normal | W51: 1141.45 | AD51: 31.79 | AE51: 5.51 | AV51: 1141.45 | AW51: 18
A52: R1024 | B52: 458250.62 | C52: 1119178.1 | D52: 480995.24 | E52: 2058423.9 | U52: Obesity | V52: Diabetes | W52: 1142 | AD52: 41.895 | AE52: 10.87 | AV52: 1142 | AW52: 20
A53: R1025 | C53: 130834.7 | D53: 220716.59 | E53: 351551.29 | U53: Obesity | V53: Diabetes | W53: 1146.8 | AD53: 31.16 | AE53: 9.34 | AV53: 1146.8 | AW53: 18
A54: R1026 | B54: 93548.99 | C54: 500623.53 | D54: 454980.85 | E54: 1049153.4 | U54: Obesity | V54: Normal | W54: 1149 | AD54: 34.105 | AE54: 5.03 | AV54: 1149 | AW54: 19
A55: Grand Total | B55: 9268924.4 | C55: 15899489 | D55: 6558489.6 | E55: 31726903 | U55: Obesity | V55: Diabetes | W55: 1149.4 | AD55: 51.93 | AE55: 11.05 | AV55: 1149.4 | AW55: 18
U56: Obesity | V56: Diabetes | W56: 1158.32 | AD56: 38.95 | AE56: 11.95 | AV56: 1158.32 | AW56: 28
U57: Obesity | V57: Diabetes | W57: 1163.46 | AD57: 36.63 | AE57: 7.72 | AV57: 1163.46 | AW57: 18
U58: Obesity | V58: Prediabetes | W58: 1165 | AD58: 34.2 | AE58: 5.75 | AV58: 1165 | AW58: 20
U59: Obesity | V59: Diabetes | W59: 1167 | AD59: 50.63 | AE59: 11.89 | AV59: 1167 | AW59: 21
U60: Obesity | V60: Prediabetes | W60: 1178 | AD60: 36.48 | AE60: 6.2 | AV60: 1178 | AW60: 26
U61: Obesity | V61: Diabetes | W61: 1178.07 | AD61: 54.82 | AE61: 10.61 | AV61: 1178.07 | AW61: 25
U62: Obesity | V62: Prediabetes | W62: 1191 | AD62: 38.06 | AE62: 6.04 | AV62: 1191 | AW62: 20
U63: Obesity | V63: Diabetes | W63: 1200 | AD63: 51.48 | AE63: 9.33 | AV63: 1200 | AW63: 23
U64: Obesity | V64: Diabetes | W64: 1200.55 | AD64: 52.06 | AE64: 11.47 | AV64: 1200.55 | AW64: 30
U65: Obesity | V65: Diabetes | W65: 1210 | AD65: 30.685 | AE65: 7.02 | AV65: 1210 | AW65: 19
U66: Obesity | V66: Diabetes | W66: 1220 | AD66: 36.08 | AE66: 8.8 | AV66: 1220 | AW66: 26
U67: Obesity | V67: Diabetes | W67: 1224 | AD67: 54.99 | AE67: 8.68 | AV67: 1224 | AW67: 18
... U1050: Obesity | V1050: Diabetes | W1050: 8527.53 | AD1050: 30.5 | AE1050: 11.94 | AV1050: 8527.53 | AW1050: 45
U1051: Overweight | V1051: Normal | W1051: 8534.67 | AD1051: 28.16 | AE1051: 5.56 | AV1051: 8534.67 | AW1051: #VALUE!
U1052: Overweight | V1052: Normal | W1052: 8538.29 | AD1052: 29.1 | AE1052: 5.64 | AV1052: 8538.29 | AW1052: 41
U1053: Obesity | V1053: Normal | W1053: 8539.67 | AD1053: 30.22 | AE1053: 4.65 | AV1053: 8539.67 | AW1053: 47
U1054: Normal Weight | V1054: Diabetes | W1054: 8547.69 | AD1054: 24.29 | AE1054: 9.05 | AV1054: 8547.69 | AW1054: #VALUE!
U1055: Overweight | V1055: Normal | W1055: 8551.35 | AD1055: 29.39 | AE1055: 4.52 | AV1055: 8551.35 | AW1055: 47
U1056: Overweight | V1056: Normal | W1056: 8556.91 | AD1056: 25.66 | AE1056: 4.62 | AV1056: 8556.91 | AW1056: 47
U1057: Obesity | V1057: Prediabetes | W1057: 8567.25 | AD1057: 39.11 | AE1057: 5.87 | AV1057: 8567.25 | AW1057: 34
U1058: Obesity | V1058: Prediabetes | W1058: 8569.86 | AD1058: 43.78 | AE1058: 5.71 | AV1058: 8569.86 | AW1058: 47
U1059: Normal Weight | V1059: Diabetes | W1059: 8572.04 | AD1059: 24.35 | AE1059: 9.08 | AV1059: 8572.04 | AW1059: 40
U1060: Obesity | V1060: Normal | W1060: 8573.3 | AD1060: 40.3 | AE1060: 5.3 | AV1060: 8573.3 | AW1060: 35
U1061: Obesity | V1061: Diabetes | W1061: 8582.3 | AD1061: 32.775 | AE1061: 11.76 | AV1061: 8582.3 | AW1061: 39
U1062: Obesity | V1062: Normal | W1062: 8596.83 | AD1062: 39.6 | AE1062: 5.11 | AV1062: 8596.83 | AW1062: 39
U1063: Obesity | V1063: Normal | W1063: 8601.33 | AD1063: 30.97 | AE1063: 5.54 | AV1063: 8601.33 | AW1063: 49
U1064: Overweight | V1064: Diabetes | W1064: 8603.82 | AD1064: 27.645 | AE1064: 8.87 | AV1064: 8603.82 | AW1064: 45
U1065: Obesity | V1065: Prediabetes | W1065: 8604.48 | AD1065: 34.43 | AE1065: 5.96 | AV1065: 8604.48 | AW1065: 45
U1066: Obesity | V1066: Normal | W1066: 8605.36 | AD1066: 39.6 | AE1066: 4.44 | AV1066: 8605.36 | AW1066: 45
... U2336: Underweight | V2336: Normal | W2336: 48970.25 | AD2336: 17.58 | AE2336: 4.51 | AV2336: 48970.25 | AW2336: 59
W2337: 49577.66 | AV2337: 49577.66 | AW2337: 64
W2338: 51194.56 | AV2338: 51194.56 | AW2338: 28
W2339: 52590.83 | AV2339: 52590.83 | AW2339: 60
W2340: 55135.4 | AV2340: 55135.4 | AW2340: 33
W2341: 58571.07 | AV2341: 58571.07 | AW2341: 32
W2342: 60021.4 | AV2342: 60021.4 | AW2342: 52
W2343: 62592.87 | AV2343: 62592.87 | AW2343: 46
W2344: 63770.43 | AV2344: 63770.43 | AW2344: 54

Sheet Dashboard
C1: HEALTHCARE ANALYTICS DASHBOARD
